Workbook

Sheet XP
A1: EXTRATO FINANCEIRO XP
A2: DATA | B2: DINHEIRO | C2: ATIVO | D2: COTAS | E2: VLR COTA | F2: TOTAL | G2: TX CBLC | H2: TX BOVESPA | I2: CORRETAGEM | J2: VLR TOTAL | K2: CUSTODIA | L2: TED | M2: RENDA FI | N2: DIVIDENDOS | O2: JCP | P2: RENDIMENTOS | Q2: IR | R2: SALDO DA CONTA
A3: 41330 | B3: 2000 | C3: BCFF11B | D3: 15 | E3: 129 | F3: =D3*E3 -> 1935 | G3: 0.11 | H3: 1.31 | I3: 31.13 | J3: =SUM(F3:I3) -> 1967.55 | R3: =B3-J3-K3-L3+M3+N3+O3+P3 -> 32.45
A4: 41339 | B4: 1000 | C4: BCFF11B | D4: 7 | E4: 131.69 | F4: =D4*E4 -> 921.83 | G4: 0.05 | H4: 0.62 | I4: 17.26 | J4: =SUM(F4:I4) -> 939.76 | R4: =R3+B4-J4-K4-L4+M4+N4+O4+P4 -> 92.69
A5: 41347 | C5: BCFF11B | M5: 18.34 | R5: =R4+B5-J5-K5-L5+M5+N5+O5+P5 -> 111.03
A6: 41365 | K6: 6.9 | R6: =R5+B6-J6-K6-L6+M6+N6+O6+P6 -> 104.13
A7: 41376 | C7: BCFF11B | M7: 18.43 | R7: =R6+B7-J7-K7-L7+M7+N7+O7+P7 -> 122.56
A8: 41396 | K8: 6.9 | R8: =R7+B8-J8-K8-L8+M8+N8+O8+P8 -> 115.66
A9: 41409 | C9: BCFF11B | M9: 15.66 | R9: =R8+B9-J9-K9-L9+M9+N9+O9+P9 -> 131.32
A10: 41428 | K10: 6.9 | R10: =R9+B10-J10-K10-L10+M10+N10+O10+P10 -> 124.42
A11: 41439 | C11: BCFF11B | M11: 15.33 | R11: =R10+B11-J11-K11-L11+M11+N11+O11+P11 -> 139.75
A12: 41445 | B12: 2000 | C12: BBAS3 | D12: 100 | E12: 20.85 | F12: =D12*E12 -> 2085 | G12: 0.57 | H12: 0.1 | I12: 0 | J12: =SUM(F12:I12) -> 2085.67 | R12: =R11+B12-J12-K12-L12+M12+N12+O12+P12 -> 54.08
A13: 41456 | K13: 6.9 | R13: =R12+B13-J13-K13-L13+M13+N13+O13+P13 -> 47.18
A14: 41470 | C14: BCFF11B | M14: 15.55 | R14: =R13+B14-J14-K14-L14+M14+N14+O14+P14 -> 62.73
A15: 41477 | C15: BCFF11B | D15: -22 | E15: 98.5 | F15: =(D15*E15) -> -2167 | G15: 0.13 | H15: 1.47 | I15: 0 | J15: =SUM(F15:I15) -> -2165.4 | R15: =R14+B15-J15-K15-L15+M15+N15+O15+P15 -> 2228.13
A16: 41479 | C16: SULA11 | D16: 100 | E16: 13.57 | F16: =D16*E16 -> 1357 | G16: 0.37 | H16: 0.06 | I16: 0 | J16: =SUM(F16:I16) -> 1357.43 | R16: =R15+B16-J16-K16-L16+M16+N16+O16+P16 -> 870.7
A17: 41484 | C17: ELET3 | D17: 100 | E17: 4.86 | F17: =D17*E17 -> 486 | J17: =SUM(F17:I17) -> 486 | R17: =R16+B17-J17-K17-L17+M17+N17+O17+P17 -> 384.7
A18: 41484 | B18: 600 | C18: ODPV3 | D18: 100 | E18: 9.5 | F18: =D18*E18 -> 950 | G18: 0.39 | H18: 0.07 | J18: =SUM(F18:I18) -> 950.46 | R18: =R17+B18-J18-K18-L18+M18+N18+O18+P18 -> 34.24
A19: 41487 | K19: 6.9 | R19: =R18+B19-J19-K19-L19+M19+N19+O19+P19 -> 27.34
A20: 41501 | B20: 2400 | C20: SULA11 | N20: 3.6 | R20: =R19+B20-J20-K20-L20+M20+N20+O20+P20 -> 2430.94
A21: 41502 | C21: BBAS3 | D21: 100 | E21: 23.07 | F21: =D21*E21 -> 2307 | G21: 0.63 | H21: 0.11 | I21: 15.77 | J21: =SUM(F21:I21) -> 2323.51 | R21: =R20+B21-J21-K21-L21+M21+N21+O21+P21 -> 107.43
A22: 41505 | C22: OIBR3 | D22: 300 | E22: 4.25 | F22: =D22*E22 -> 1275 | G22: 0.35 | H22: 0.06 | I22: 15.77 | J22: =SUM(F22:I22) -> 1291.18 | R22: =R21+B22-J22-K22-L22+M22+N22+O22+P22 -> -1183.75
A23: 41506 | B23: 1300 | F23: =D23*E23 -> 0 | J23: =SUM(F23:I23) -> 0 | R23: =R22+B23-J23-K23-L23+M23+N23+O23+P23 -> 116.25
A24: 41513 | C24: BVMF3 | D24: 100 | E24: 11.54 | F24: =D24*E24 -> 1154 | G24: 0.31 | H24: 0.05 | I24: 94.66 | J24: =SUM(F24:I24) -> 1249.02 | R24: =R23+B24-J24-K24-L24+M24+N24+O24+P24 -> -1132.77
A25: 41515 | B25: 1100 | R25: =R24+B25-J25-K25-L25+M25+N25+O25+P25 -> -32.77
A26: 41516 | C26: BBAS3 | N26: 153.96 | P26: 1.71 | Q26: 0.5 | R26: =R25+B26-J26-K26-L26+M26+N26+O26+P26 -> 122.9
A27: 41519 | K27: 6.9 | R27: =R26+B27-J27-K27-L27+M27+N27+O27+P27 -> 116
A28: 41521 | C28: ODPV3 | N28: 5.87 | R28: =R27+B28-J28-K28-L28+M28+N28+O28+P28 -> 121.87
A29: 41535 | C29: CMIG3 | D29: 100 | E29: 18.38 | F29: =D29*E29 -> 1838 | G29: 0.5 | H29: 0.09 | I29: 15.77 | J29: =SUM(F29:I29) -> 1854.36 | R29: =R28+B29-J29-K29-L29+M29+N29+O29+P29 -> -1732.49
A30: 41536 | B30: 1750 | R30: =R29+B30-J30-K30-L30+M30+N30+O30+P30 -> 17.51
A31: 41543 | C31: OIBR3 | D31: 200 | E31: 4.86 | F31: =D31*E31 -> 972 | G31: 0.26 | H31: 0.04 | I31: 15.77 | J31: =SUM(F31:I31) -> 988.07 | R31: =R30+B31-J31-K31-L31+M31+N31+O31+P31 -> -970.56
A32: 41544 | R32: =R31+B32-J32-K32-L32+M32+N32+O32+P32 -> -970.56
A33: 41547 | C33: BBAS3 | O33: 53.34 | Q33: 9.41 | R33: =R32+B33-J33-K33-L33+M33+N33+O33+P33 -> -917.22
A34: 41549 | B34: 1000 | K34: 2.75 | R34: =R33+B34-J34-K34-L34+M34+N34+O34+P34 -> 80.03
A35: 41549 | K35: 6.9 | R35: =R34+B35-J35-K35-L35+M35+N35+O35+P35 -> 73.13
A36: 41558 | C36: OIBR3 | N36: 152.43 | R36: =R35+B36-J36-K36-L36+M36+N36+O36+P36 -> 225.56
A37: 41572 | C37: ELET3 | D37: 50 | E37: 7.3 | F37: =D37*E37 -> 365 | G37: 0.1 | H37: 0.01 | I37: 7.72 | J37: =SUM(F37:I37) -> 372.83 | R37: =R36+B37-J37-K37-L37+M37+N37+O37+P37 -> -147.27
A38: 41575 | B38: 200 | R38: =R37+B38-J38-K38-L38+M38+N38+O38+P38 -> 52.73
A39: 41576 | B39: 2100 | C39: ELPL4 | D39: 200 | E39: 10.26 | F39: =D39*E39 -> 2052 | G39: 0.56 | H39: 0.1 | I39: 15.77 | J39: =SUM(F39:I39) -> 2068.43 | R39: =R38+B39-J39-K39-L39+M39+N39+O39+P39 -> 84.3
A40: 41579 | K40: 6.9 | R40: =R39+B40-J40-K40-L40+M40+N40+O40+P40 -> 77.4
A41: 41591 | C41: ODPV3 | N41: 1.52 | R41: =R40+B41-J41-K41-L41+M41+N41+O41+P41 -> 78.92
A42: 41596 | C42: SULA11 | N42: 3.6 | R42: =R41+B42-J42-K42-L42+M42+N42+O42+P42 -> 82.52
A43: 41599 | C43: OIBR3 | D43: 300 | E43: 3.68 | F43: =D43*E43 -> 1104 | G43: 0.3 | H43: 0.05 | I43: 15.77 | J43: =SUM(F43:I43) -> 1120.12 | R43: =R42+B43-J43-K43-L43+M43+N43+O43+P43 -> -1037.6
A44: 41600 | B44: 1050 | R44: =R43+B44-J44-K44-L44+M44+N44+O44+P44 -> 12.4
A45: 41605 | C45: BVMF3 | N45: 11.83 | R45: =R44+B45-J45-K45-L45+M45+N45+O45+P45 -> 24.23
A46: 41607 | C46: BBAS3 | N46: 13.32 | R46: =R45+B46-J46-K46-L46+M46+N46+O46+P46 -> 37.55
A47: 41610 | K47: 6.9 | R47: =R46+B47-J47-K47-L47+M47+N47+O47+P47 -> 30.65
A48: 41610 | C48: PETR3 | D48: 100 | E48: 16.65 | F48: =D48*E48 -> 1665 | G48: 0.45 | H48: 0.08 | I48: 15.77 | J48: =SUM(F48:I48) -> 1681.3 | R48: =R47+B48-J48-K48-L48+M48+N48+O48+P48 -> -1650.65
A49: 41610 | B49: 1650 | R49: =R48+B49-J49-K49-L49+M49+N49+O49+P49 -> -0.65
A50: 41612 | C50: ODPV3 | N50: 6.31 | R50: =R49+B50-J50-K50-L50+M50+N50+O50+P50 -> 5.66
A51: 41621 | C51: ODPV3 | D51: -100 | E51: 9.95 | F51: =(D51*E51) -> -995 | G51: 0.27 | H51: 0.04 | I51: 15.77 | J51: =SUM(F51:I51) -> -978.92 | R51: =R50+B51-J51-K51-L51+M51+N51+O51+P51 -> 984.58
A52: 41627 | C52: CMIG3 | O52: 47.09 | Q52: 8.31 | R52: =R51+B52-J52-K52-L52+M52+N52+O52+P52 -> 1031.67
A53: 41631 | C53: BBAS3 | D53: 50 | E53: 24.49 | F53: =D53*E53 -> 1224.5 | G53: 0.3 | H53: 0.09 | I53: 15.77 | J53: =SUM(F53:I53) -> 1240.66 | R53: =R52+B53-J53-K53-L53+M53+N53+O53+P53 -> -208.99
A54: 41634 | C54: SULA11 | O54: 7.63 | Q54: 1.35 | R54: =R53+B54-J54-K54-L54+M54+N54+O54+P54 -> -201.36
A55: 41635 | B55: 200 | R55: =R54+B55-J55-K55-L55+M55+N55+O55+P55 -> -1.36
A56: 41638 | C56: BBAS3 | O56: 52.65 | Q56: 9.29 | R56: =R55+B56-J56-K56-L56+M56+N56+O56+P56 -> 51.29
A57: 41642 | C57: CMIG4 | D57: 30 | J57: =SUM(F57:I57) -> 0 | R57: =R56+B57-J57-K57-L57+M57+N57+O57+P57 -> 51.29
A58: 41645 | K58: 6.9 | R58: =R57+B58-J58-K58-L58+M58+N58+O58+P58 -> 44.39
A59: 41646 | C59: ELPL4 | D59: 200 | E59: 8.75 | F59: =D59*E59 -> 1750 | G59: 0.48 | H59: 0.08 | I59: 15.77 | J59: =SUM(F59:I59) -> 1766.33 | R59: =R58+B59-J59-K59-L59+M59+N59+O59+P59 -> -1721.94
A60: 41646 | B60: 1750 | R60: =R59+B60-J60-K60-L60+M60+N60+O60+P60 -> 28.06
A61: 41656 | C61: BBAS3 | D61: 50 | E61: 22.45 | F61: =D61*E61 -> 1122.5 | G61: 0.3 | H61: 0.05 | I61: 15.77 | J61: =SUM(F61:I61) -> 1138.62 | R61: =R60+B61-J61-K61-L61+M61+N61+O61+P61 -> -1110.56
A62: 41661 | B62: 1120 | R62: =R61+B62-J62-K62-L62+M62+N62+O62+P62 -> 9.44
A63: 41674 | K63: 6.9 | R63: =R62+B63-J63-K63-L63+M63+N63+O63+P63 -> 2.54
A64: 41694 | C64: BBAS3 | N64: 39.51 | R64: =R63+B64-J64-K64-L64+M64+N64+O64+P64 -> 42.05
A65: 41694 | C65: SULA11 | D65: -100 | E65: 14.8 | F65: =D65*E65 -> -1480 | G65: 0.67 | H65: 0.12 | I65: 31.55 | J65: =SUM(F65:I65) -> -1447.66 | R65: =R64+B65-J65-K65-L65+M65+N65+O65+P65 -> 1489.71
A66: 41694 | C66: BBAS3 | D66: 50 | E66: 19.81 | F66: =D66*E66 -> 990.5 | J66: =SUM(F66:I66) -> 990.5 | R66: =R65+B66-J66-K66-L66+M66+N66+O66+P66 -> 499.21
A67: 41696 | C67: BBAS3 | D67: 50 | E67: 19.47 | F67: =D67*E67 -> 973.5 | G67: 0.26 | H67: 0.04 | I67: 15.77 | J67: =SUM(F67:I67) -> 989.57 | R67: =R66+B67-J67-K67-L67+M67+N67+O67+P67 -> -490.36
A68: 41697 | B68: 500 | R68: =R67+B68-J68-K68-L68+M68+N68+O68+P68 -> 9.64
A69: 41703 | K69: 6.9 | R69: =R68+B69-J69-K69-L69+M69+N69+O69+P69 -> 2.74
A70: 41719 | C70: BBAS3 | D70: 1 | E70: 20.61 | F70: =D70*E70 -> 20.61 | J70: =SUM(F70:I70) -> 20.61 | R70: =R69+B70-J70-K70-L70+M70+N70+O70+P70 -> -17.87
A71: 41719 | C71: BBAS3 | D71: 48 | E71: 20.87 | F71: =D71*E71 -> 1001.76 | G71: 0.28 | H71: 0.05 | I71: 15.77 | J71: =SUM(F71:I71) -> 1017.86 | R71: =R70+B71-J71-K71-L71+M71+N71+O71+P71 -> -1035.73
A72: 41722 | B72: 1040 | R72: =R71+B72-J72-K72-L72+M72+N72+O72+P72 -> 4.27
A73: 41729 | C73: BBAS3 | N73: 106.99 | R73: =R72+B73-J73-K73-L73+M73+N73+O73+P73 -> 111.26
A74: 41732 | K74: 6.9 | R74: =R73+B74-J74-K74-L74+M74+N74+O74+P74 -> 104.36
A75: 41737 | C75: BBAS3 | D75: -49 | E75: 25.4 | F75: =D75*E75 -> -1244.6 | G75: 0.34 | H75: 0.06 | I75: 15.77 | J75: =SUM(F75:I75) -> -1228.43 | R75: =R74+B75-J75-K75-L75+M75+N75+O75+P75 -> 1332.79
A76: 41738 | C76: SUZB5 | D76: 200 | E76: 7.8 | F76: =D76*E76 -> 1560 | G76: 0.42 | H76: 0.07 | I76: 15.77 | J76: =SUM(F76:I76) -> 1576.26 | R76: =R75+B76-J76-K76-L76+M76+N76+O76+P76 -> -243.47
A77: 41740 | C77: CSNA3 | D77: 100 | E77: 9.04 | F77: =D77*E77 -> 904 | G77: 0.24 | H77: 0.04 | I77: 15.77 | J77: =SUM(F77:I77) -> 920.05 | R77: =R76+B77-J77-K77-L77+M77+N77+O77+P77 -> -1163.52
A78: 41743 | B78: 300 | R78: =R77+B78-J78-K78-L78+M78+N78+O78+P78 -> -863.52
A79: 41744 | B79: 870 | R79: =R78+B79-J79-K79-L79+M79+N79+O79+P79 -> 6.48
A80: 41751 | C80: SULA11 | N80: 13.98 | R80: =R79+B80-J80-K80-L80+M80+N80+O80+P80 -> 20.46
A81: 41754 | C81: PETR3 | N81: 45.62 | R81: =R80+B81-J81-K81-L81+M81+N81+O81+P81 -> 66.08
A82: 41765 | K82: 6.9 | R82: =R81+B82-J82-K82-L82+M82+N82+O82+P82 -> 59.18
A83: 41767 | C83: ELET3 | D83: -100 | E83: 7.61 | F83: =D83*E83 -> -761 | G83: 0.2 | H83: 0.03 | I83: 15.77 | J83: =SUM(F83:I83) -> -745 | R83: =R82+B83-J83-K83-L83+M83+N83+O83+P83 -> 804.18
A84: 41771 | C84: SUZB5 | N84: 23.2 | R84: =R83+B84-J84-K84-L84+M84+N84+O84+P84 -> 827.38
A85: 41786 | C85: ELPL4 | D85: 100 | E85: 8.87 | F85: =D85*E85 -> 887 | G85: 0.24 | H85: 0.04 | I85: 15.77 | J85: =SUM(F85:I85) -> 903.05 | R85: =R84+B85-J85-K85-L85+M85+N85+O85+P85 -> -75.67
A86: 41788 | C86: ELET3 | N86: 52.83 | R86: =R85+B86-J86-K86-L86+M86+N86+O86+P86 -> -22.84
A87: 41789 | C87: BVMF3 | N87: 11.15 | R87: =R86+B87-J87-K87-L87+M87+N87+O87+P87 -> -11.69
A88: 41789 | C88: BBAS3 | N88: 32.48 | R88: =R87+B88-J88-K88-L88+M88+N88+O88+P88 -> 20.79
A89: 41792 | K89: 6.9 | R89: =R88+B89-J89-K89-L89+M89+N89+O89+P89 -> 13.89
A90: 41817 | C90: BVMF3 | N90: 7.96 | R90: =R89+B90-J90-K90-L90+M90+N90+O90+P90 -> 21.85
A91: 41820 | C91: CMIG4 | N91: 26.76 | R91: =R90+B91-J91-K91-L91+M91+N91+O91+P91 -> 48.61
A92: 41820 | C92: CMIG3 | N92: 89.2 | R92: =R91+B92-J92-K92-L92+M92+N92+O92+P92 -> 137.81
A93: 41820 | C93: BBAS3 | N93: 109.17 | R93: =R92+B93-J93-K93-L93+M93+N93+O93+P93 -> 246.98
A94: 41820 | C94: CMIG4 | N94: 11.63 | R94: =R93+B94-J94-K94-L94+M94+N94+O94+P94 -> 258.61
A95: 41821 | K95: 6.9 | R95: =R94+B95-J95-K95-L95+M95+N95+O95+P95 -> 251.71
A96: 41821 | C96: OIBR3 | D96: 100 | E96: 1.99 | F96: =D96*E96 -> 199 | G96: 0.05 | I96: 4.2 | J96: =SUM(F96:I96) -> 203.25 | R96: =R95+B96-J96-K96-L96+M96+N96+O96+P96 -> 48.46
A97: 41828 | C97: CMIG3 | N97: 87.42 | R97: =R96+B97-J97-K97-L97+M97+N97+O97+P97 -> 135.88
A98: 41828 | C98: CMIG4 | N98: 26.22 | R98: =R97+B98-J98-K98-L98+M98+N98+O98+P98 -> 162.1
A99: 41830 | C99: OIBR3 | D99: 100 | E99: 1.65 | F99: =D99*E99 -> 165 | G99: 0.04 | I99: 3.48 | J99: =SUM(F99:I99) -> 168.52 | R99: =R98+B99-J99-K99-L99+M99+N99+O99+P99 -> -6.42
A100: 41831 | C100: CMIG4 | D100: -30 | E100: 18.5 | F100: =D100*E100 -> -555 | J100: =SUM(F100:I100) -> -555 | R100: =R99+B100-J100-K100-L100+M100+N100+O100+P100 -> 548.58
...

Sheet Modal-Silna
A1: EXTRATO FINANCEIRO MODAL
A2: DATA | B2: DINHEIRO | C2: ATIVO | D2: COTAS | E2: VLR COTA | F2: TOTAL | G2: TX LIQUID | H2: EMOL | I2: CORRETAGEM | J2: VLR TOTAL | K2: CUSTODIA | L2: TED | M2: RENDA | N2: DIVIDENDOS | O2: JCP | P2: SALDO DA CONTA | S2: ATIVOS | T2: QTD | U2: PREÇO | V2: TOTAL
A3: 43164 | B3: 50 | P3: =B3-J3-K3-L3+M3+N3+O3 -> 50 | S3: ABCP11 | T3: 1 | U3: 96.27 | V3: =T3*U3 -> 96.27
A4: 43165 | C4: ABCP11 | D4: 2 | E4: 16.56 | F4: =D4*E4 -> 33.12 | G4: 0 | H4: 0 | I4: 0 | J4: =SUM(F4:I4) -> 33.12 | P4: =P3+B4-J4-K4-L4+M4+N4+O4 -> 16.88 | S4: BCFF11 | T4: 8 | U4: 82.98 | V4: =T4*U4 -> 663.84
A5: 43196 | C5: ABCP11 | M5: 0.16 | P5: =P4+B5-J5-K5-L5+M5+N5+O5 -> 17.04 | S5: EDGA11 | T5: 14 | U5: 49.69 | V5: =T5*U5 -> 695.66
A6: 43228 | C6: ABCP11 | M6: 0.16 | P6: =P5+B6-J6-K6-L6+M6+N6+O6 -> 17.2 | S6: MXRF11 | T6: 105 | U6: 10.58 | V6: =T6*U6 -> 1110.9
A7: 43258 | C7: ABCP11 | M7: 0.17 | P7: =P6+B7-J7-K7-L7+M7+N7+O7 -> 17.37 | S7: SPTW11 | T7: 5 | U7: 81 | V7: =T7*U7 -> 405
A8: 43287 | C8: ABCP11 | M8: 0.17 | P8: =P7+B8-J8-K8-L8+M8+N8+O8 -> 17.54 | S8: VISC11 | T8: 3 | U8: 107.56 | V8: =T8*U8 -> 322.68
A9: 43319 | C9: ABCP11 | M9: 0.17 | P9: =P8+B9-J9-K9-L9+M9+N9+O9 -> 17.71
A10: 43353 | C10: ABCP11 | M10: 0.17 | P10: =P9+B10-J10-K10-L10+M10+N10+O10 -> 17.88 | U10: TOTAL | V10: =SUM(V3:V8) -> 3294.35
A11: 43361 | B11: 800 | P11: =P10+B11-J11-K11-L11+M11+N11+O11 -> 817.88
A12: 43362 | B12: 950 | P12: =P11+B12-J12-K12-L12+M12+N12+O12 -> 1767.88
A13: 43361 | C13: MXRF11 | D13: 50 | E13: 9.96 | F13: =D13*E13 -> 498 | G13: 0.1 | H13: 0.02 | I13: 0 | J13: =SUM(F13:I13) -> 498.12 | P13: =P12+B13-J13-K13-L13+M13+N13+O13 -> 1269.76
A14: 43361 | C14: VISC11 | D14: 3 | E14: 96.59 | F14: =D14*E14 -> 289.77 | G14: 0.11 | H14: 0.01 | I14: 0 | J14: =SUM(F14:I14) -> 289.89 | P14: =P13+B14-J14-K14-L14+M14+N14+O14 -> 979.87
A15: 43362 | C15: EDGA11 | D15: 10 | E15: 37.01 | F15: =D15*E15 -> 370.1 | G15: 0.1 | H15: 0.02 | I15: 0 | J15: =SUM(F15:I15) -> 370.22 | P15: =P14+B15-J15-K15-L15+M15+N15+O15 -> 609.65
A16: 43362 | C16: MXRF11 | D16: 20 | E16: 9.93 | F16: =D16*E16 -> 198.6 | G16: 0.05 | H16: 0.02 | I16: 0 | J16: =SUM(F16:I16) -> 198.67 | P16: =P15+B16-J16-K16-L16+M16+N16+O16 -> 410.98
A17: 43362 | C17: SPTW11 | D17: 5 | E17: 72.35 | F17: =D17*E17 -> 361.75 | G17: 0.1 | H17: 0.02 | I17: 0 | J17: =SUM(F17:I17) -> 361.87 | P17: =P16+B17-J17-K17-L17+M17+N17+O17 -> 49.11
A18: 43006 | M18: 1.76 | P18: =P17+B18-J18-K18-L18+M18+N18+O18 -> 50.87
A19: 43378 | C19: ABCP11 | M19: 0.17 | P19: =P18+B19-J19-K19-L19+M19+N19+O19 -> 51.04
A20: 43378 | C20: SPTW11 | M20: 2.75 | P20: =P19+B20-J20-K20-L20+M20+N20+O20 -> 53.79
A21: 43388 | C21: VISC11 | M21: 1.83 | P21: =P20+B21-J21-K21-L21+M21+N21+O21 -> 55.62
A22: 43388 | C22: MXRF11 | M22: 4.9 | P22: =P21+B22-J22-K22-L22+M22+N22+O22 -> 60.52
A23: 43388 | B23: 500 | P23: =P22+B23-J23-K23-L23+M23+N23+O23 -> 560.52
A24: 43388 | C24: MXRF11 | D24: 30 | E24: 9.86 | F24: =D24*E24 -> 295.8 | G24: 0.06 | H24: 0.01 | I24: 0 | J24: =SUM(F24:I24) -> 295.87 | P24: =P23+B24-J24-K24-L24+M24+N24+O24 -> 264.65
A25: 43388 | C25: EDGA11 | D25: 4 | E25: 38.94 | F25: =D25*E25 -> 155.76 | G25: 0.06 | H25: 0.01 | I25: 0 | J25: =SUM(F25:I25) -> 155.83 | P25: =P24+B25-J25-K25-L25+M25+N25+O25 -> 108.82
A26: 43404 | C26: EDGA11 | M26: 3.07 | P26: =P25+B26-J26-K26-L26+M26+N26+O26 -> 111.89
A27: 43412 | C27: ABCP11 | M27: 0.17 | P27: =P26+B27-J27-K27-L27+M27+N27+O27 -> 112.06
A28: 43412 | C28: SPTW11 | M28: 2.75 | P28: =P27+B28-J28-K28-L28+M28+N28+O28 -> 114.81
A29: 43417 | B29: 500 | P29: =P28+B29-J29-K29-L29+M29+N29+O29 -> 614.81
A30: 43417 | C30: BCFF11 | D30: 7 | E30: 80.75 | F30: =D30*E30 -> 565.25 | G30: 0.15 | H30: 0.02 | I30: 0 | J30: =SUM(F30:I30) -> 565.42 | P30: =P29+B30-J30-K30-L30+M30+N30+O30 -> 49.39
A31: 43420 | C31: VISC11 | M31: 1.83 | P31: =P30+B31-J31-K31-L31+M31+N31+O31 -> 51.22
A32: 43420 | C32: MXRF11 | M32: 6 | P32: =P31+B32-J32-K32-L32+M32+N32+O32 -> 57.22
A33: 43434 | C33: EDGA11 | M33: 4.22 | P33: =P32+B33-J33-K33-L33+M33+N33+O33 -> 61.44
A34: 43439 | C34: MXRF11 | D34: 5 | E34: 10.09 | F34: =D34*E34 -> 50.45 | G34: 0.01 | H34: 0 | I34: 0 | J34: =SUM(F34:I34) -> 50.46 | P34: =P33+B34-J34-K34-L34+M34+N34+O34 -> 10.98
A35: 43441 | C35: ABCP11 | M35: 0.18 | P35: =P34+B35-J35-K35-L35+M35+N35+O35 -> 11.16
A36: 43441 | C36: SPTW11 | M36: 3.05 | P36: =P35+B36-J36-K36-L36+M36+N36+O36 -> 14.21
A37: 43448 | C37: VISC11 | M37: 1.81 | P37: =P36+B37-J37-K37-L37+M37+N37+O37 -> 16.02
A38: 43448 | C38: BCFF11 | M38: 4.06 | P38: =P37+B38-J38-K38-L38+M38+N38+O38 -> 20.08
A39: 43451 | C39: MXRF11 | M39: 6 | P39: =P38+B39-J39-K39-L39+M39+N39+O39 -> 26.08
A40: 43462 | C40: EDGA11 | M40: 4.72 | P40: =P39+B40-J40-K40-L40+M40+N40+O40 -> 30.8
A41: 43473 | C41: ABCP11 | M41: 0.18 | P41: =P40+B41-J41-K41-L41+M41+N41+O41 -> 30.98
A42: 43473 | C42: SPTW11 | M42: 3.05 | P42: =P41+B42-J42-K42-L42+M42+N42+O42 -> 34.03
A43: 43480 | C43: MXRF11 | M43: 6.3 | P43: =P42+B43-J43-K43-L43+M43+N43+O43 -> 40.33
A44: 43480 | C44: BCFF11 | M44: 4.06 | P44: =P43+B44-J44-K44-L44+M44+N44+O44 -> 44.39
A45: 43480 | C45: VISC11 | M45: 1.81 | P45: =P44+B45-J45-K45-L45+M45+N45+O45 -> 46.2
A46: 43487 | B46: 100 | P46: =P45+B46-J46-K46-L46+M46+N46+O46 -> 146.2
A47: 43487 | C47: ABCP11 | D47: 3 | E47: 18.96 | F47: =D47*E47 -> 56.88 | G47: 0.01 | H47: 0 | I47: 0 | J47: =SUM(F47:I47) -> 56.89 | P47: =P46+B47-J47-K47-L47+M47+N47+O47 -> 89.31
A48: 43487 | C48: BCFF11 | D48: 1 | E48: 83.78 | F48: =D48*E48 -> 83.78 | G48: 0.03 | H48: 0 | I48: 0 | J48: =SUM(F48:I48) -> 83.81 | P48: =P47+B48-J48-K48-L48+M48+N48+O48 -> 5.5
A49: 43496 | C49: EDGA11 | M49: 5.51 | P49: =P48+B49-J49-K49-L49+M49+N49+O49 -> 11.01
A50: 43503 | C50: ABCP11 | M50: 0.65 | P50: =P49+B50-J50-K50-L50+M50+N50+O50 -> 11.66
A51: 43503 | C51: SPTW11 | M51: 3.05 | P51: =P50+B51-J51-K51-L51+M51+N51+O51 -> 14.71
A52: 43510 | C52: VISC11 | M52: 1.81 | P52: =P51+B52-J52-K52-L52+M52+N52+O52 -> 16.52
A53: 43510 | C53: BCFF11 | M53: 4.24 | P53: =P52+B53-J53-K53-L53+M53+N53+O53 -> 20.76
A54: 43510 | C54: MXRF11 | M54: 6.3 | P54: =P53+B54-J54-K54-L54+M54+N54+O54 -> 27.06
A55: 43524 | C55: EDGA11 | M55: 3.7 | P55: =P54+B55-J55-K55-L55+M55+N55+O55 -> 30.76
A56: 43535 | C56: ABCP11 | M56: 0.45 | P56: =P55+B56-J56-K56-L56+M56+N56+O56 -> 31.21
A57: 43535 | C57: SPTW11 | M57: 3.05 | P57: =P56+B57-J57-K57-L57+M57+N57+O57 -> 34.26
A58: 43539 | C58: MXRF11 | M58: 7.35 | P58: =P57+B58-J58-K58-L58+M58+N58+O58 -> 41.61
A59: 43542 | C59: VISC11 | M59: 1.81 | P59: =P58+B59-J59-K59-L59+M59+N59+O59 -> 43.42
A60: 43542 | C60: BCFF11 | M60: 3.44 | P60: =P59+B60-J60-K60-L60+M60+N60+O60 -> 46.86
... A69: 43593 | C69: SPTW11 | M69: 3.06 | P69: =P68+B69-J69-K69-L69+M69+N69+O69 -> 72.35
A70: 43594 | B70: 500 | P70: =P69+B70-J70-K70-L70+M70+N70+O70 -> 572.35
A71: 43595 | C71: BCFF11 | D71: 6 | E71: 85.2 | F71: =D71*E71 -> 511.2 | G71: 0.14 | H71: 0.02 | I71: 0 | J71: =SUM(F71:I71) -> 511.36 | P71: =P70+B71-J71-K71-L71+M71+N71+O71 -> 60.99
A72: 43600 | C72: BCFF11 | M72: 4.24 | P72: =P71+B72-J72-K72-L72+M72+N72+O72 -> 65.23
A73: 43600 | C73: MXRF11 | M73: 7.35 | P73: =P72+B73-J73-K73-L73+M73+N73+O73 -> 72.58
A74: 43600 | C74: VISC11 | M74: 1.47 | P74: =P73+B74-J74-K74-L74+M74+N74+O74 -> 74.05
A75: 43607 | C75: MXRF11 | D75: 6 | E75: 11.46 | F75: =D75*E75 -> 68.76 | G75: 0 | H75: 0 | I75: 0 | J75: =SUM(F75:I75) -> 68.76 | P75: =P74+B75-J75-K75-L75+M75+N75+O75 -> 5.29
P76: =P75+B76-J76-K76-L76+M76+N76+O76 -> 5.29
A77: 43684 | C77: MXR11 | D77: 4 | E77: 11.32 | F77: =D77*E77 -> 45.28 | G77: 0 | H77: 0 | I77: 0 | J77: =SUM(F77:I77) -> 45.28 | P77: =P76+B77-J77-K77-L77+M77+N77+O77 -> -39.99
P78: =P77+B78-J78-K78-L78+M78+N78+O78 -> -39.99
P79: =P78+B79-J79-K79-L79+M79+N79+O79 -> -39.99
A80: 43858 | C80: VINO11 | D80: 2 | E80: 66.66 | F80: =D80*E80 -> 133.32 | G80: 0 | H80: 0 | I80: 0 | J80: =SUM(F80:I80) -> 133.32 | P80: =P79+B80-J80-K80-L80+M80+N80+O80 -> -173.31
A81: 44048 | C81: MXRF11 | D81: 6 | E81: 10.62 | F81: =D81*E81 -> 63.72 | G81: 0 | H81: 0 | I81: 0 | J81: =SUM(F81:I81) -> 63.72 | P81: =P80+B81-J81-K81-L81+M81+N81+O81 -> -237.03
A83: TOTAL | B83: =SUM(B3:B82) -> 3400 | D83: =SUM(D4:D82) -> 164 | G83: =SUM(G3:G82) -> 0.92 | H83: =SUM(H3:H82) -> 0.15 | I83: =SUM(I3:I82) -> 0 | J83: =SUM(J3:J82) -> 3782.61 | K83: =SUM(K3:K82) -> 0 | L83: =SUM(L3:L82) -> 0 | M83: =SUM(M3:M82) -> 145.58 | N83: =SUM(N3:N82) -> 0 | O83: =SUM(O3:O82) -> 0
A85: ATUAL | B85: 3994.21
A86: P/L | B86: =B85/B83-1 -> 0.17476765
A89: Como acessar a conta da Modal de Silna:
A90: 01 - Acesse o site https://www.modalmais.com.br/
A91: 02 - Entre com o login/senha: silnabatinga/Onibus10w
A92: 03 - Para comprar/vender ações, vá em "Bolsa" / "Acessar Modal Investidor"
A93: 04 - Para transferir para o banco vá em "Serviços" / Transferencia "para o meu banco"

Sheet MODAL
A1: DATA | B1: DINHEIRO | C1: ATIVO | D1: COTAS | E1: VLR COTA | F1: TOTAL | G1: TX LIQUID | H1: EMOL | I1: ISS SP | J1: CORRETAGEM | K1: VLR TOTAL | L1: CUSTODIA | M1: TED | N1: RENDA | O1: DIVIDENDOS | P1: JCP | Q1: SALDO DA CONTA
A2: 41799 | B2: 200 | Q2: =B2-K2-L2-M2+N2+O2+P2 -> 200
A3: 41810 | B3: 700 | Q3: =Q2+B3-K3-L3-M3+N3+O3+P3 -> 900
A4: 41813 | C4: ETER3 | D4: 100 | E4: 8.48 | F4: =D4*E4 -> 848 | G4: 0.23 | H4: 0.04 | J4: 8.99 | K4: =SUM(F4:J4) -> 857.26 | Q4: =Q3+B4-K4-L4-M4+N4+O4+P4 -> 42.74
A5: 41842 | B5: 500 | Q5: =Q4+B5-K5-L5-M5+N5+O5+P5 -> 542.74
A6: 41849 | C6: BBAS3 | D6: 400 | Q6: =Q5+B6-K6-L6-M6+N6+O6+P6 -> 542.74
A7: 41849 | B7: 500 | Q7: =Q6+B7-K7-L7-M7+N7+O7+P7 -> 1042.74
A8: 41850 | B8: 3000 | Q8: =Q7+B8-K8-L8-M8+N8+O8+P8 -> 4042.74
A9: 41851 | C9: ETER3 | D9: 100 | E9: 8.52 | F9: =D9*E9 -> 852 | G9: 0.23 | H9: 0.04 | J9: 8.99 | K9: =SUM(F9:J9) -> 861.26 | Q9: =Q8+B9-K9-L9-M9+N9+O9+P9 -> 3181.48
A10: 41858 | C10: ETER3 | D10: 100 | E10: 8.59 | F10: =D10*E10 -> 859 | G10: 0.23 | H10: 0.04 | J10: 8.99 | K10: =SUM(F10:J10) -> 868.26 | Q10: =Q9+B10-K10-L10-M10+N10+O10+P10 -> 2313.22
A11: 41864 | C11: VALE5 | D11: 80 | E11: 27.76 | F11: =D11*E11 -> 2220.8 | G11: 0.61 | H11: 0.11 | J11: 5.99 | K11: =SUM(F11:J11) -> 2227.51 | Q11: =Q10+B11-K11-L11-M11+N11+O11+P11 -> 85.71
A12: 41870 | C12: BBAS3 | D12: -200 | E12: 29.98 | F12: =D12*E12 -> -5996 | G12: 1.64 | H12: 0.29 | J12: 8.99 | K12: =SUM(F12:J12) -> -5985.08 | Q12: =Q11+B12-K12-L12-M12+N12+O12+P12 -> 6070.79
A13: 41876 | C13: ETER3 | D13: 200 | E13: 8.39 | F13: =D13*E13 -> 1678 | G13: 0.46 | H13: 0.08 | J13: 8.99 | K13: =SUM(F13:J13) -> 1687.53 | Q13: =Q12+B13-K13-L13-M13+N13+O13+P13 -> 4383.26
A14: 41878 | C14: VALE5 | D14: 50 | E14: 27.25 | F14: =D14*E14 -> 1362.5 | G14: 0.43 | H14: 0 | J14: 5.99 | K14: =SUM(F14:J14) -> 1368.92 | Q14: =Q13+B14-K14-L14-M14+N14+O14+P14 -> 3014.34
A15: 41879 | C15: ETER3 | O15: 39.9 | P15: 17.09 | Q15: =Q14+B15-K15-L15-M15+N15+O15+P15 -> 3071.33
A16: 41879 | C16: VALE5 | D16: 70 | E16: 26.12 | F16: =D16*E16 -> 1828.4 | G16: 0.59 | H16: 0 | J16: 5.99 | K16: =SUM(F16:J16) -> 1834.98 | Q16: =Q15+B16-K16-L16-M16+N16+O16+P16 -> 1236.35
A17: 41880 | C17: BBAS3 | O17: 15.69 | Q17: =Q16+B17-K17-L17-M17+N17+O17+P17 -> 1252.04
A18: 41883 | C18: ETER3 | D18: 100 | E18: 8.36 | F18: =D18*E18 -> 836 | G18: 0.26 | H18: 0 | J18: 8.99 | K18: =SUM(F18:J18) -> 845.25 | Q18: =Q17+B18-K18-L18-M18+N18+O18+P18 -> 406.79
A19: 41884 | C19: BBAS3 | D19: -200 | E19: 35.9 | F19: =D19*E19 -> -7180 | G19: 2.32 | H19: 0 | J19: 8.99 | K19: =SUM(F19:J19) -> -7168.69 | Q19: =Q18+B19-K19-L19-M19+N19+O19+P19 -> 7575.48
A20: 41887 | C20: VALE5 | D20: 100 | E20: 24.7 | F20: =D20*E20 -> 2470 | G20: 0.67 | H20: 0.12 | J20: 8.99 | K20: =SUM(F20:J20) -> 2479.78 | Q20: =Q19+B20-K20-L20-M20+N20+O20+P20 -> 5095.7
A21: 41887 | B21: -3500 | Q21: =Q20+B21-K21-L21-M21+N21+O21+P21 -> 1595.7
A22: 41894 | C22: ETER3 | D22: 200 | E22: 7.87 | F22: =D22*E22 -> 1574 | G22: 0.43 | H22: 0.07 | J22: 8.99 | K22: =SUM(F22:J22) -> 1583.49 | Q22: =Q21+B22-K22-L22-M22+N22+O22+P22 -> 12.21
A23: 41913 | C23: ETER3 | D23: 800 | E23: 0 | F23: =D23*E23 -> 0 | Q23: =Q22+B23-K23-L23-M23+N23+O23+P23 -> 12.21 | S23: Desdobramento da ETER3 de 1:2
A24: 41943 | C24: VALE5 | O24: 102.01 | P24: 165.97 | Q24: =Q23+B24-K24-L24-M24+N24+O24+P24 -> 280.19
A25: 41943 | B25: -280.19 | Q25: =Q24+B25-K25-L25-M25+N25+O25+P25 -> -1.7053026e-13
A26: 41970 | C26: ETER3 | O26: 106.4 | P26: 45.56 | Q26: =Q25+B26-K26-L26-M26+N26+O26+P26 -> 151.96
A27: 41971 | B27: -151.96 | Q27: =Q26+B27-K27-L27-M27+N27+O27+P27 -> -1.7053026e-13
A28: 42041 | C28: ETER3 | D28: -1600 | E28: 3.1 | F28: =D28*E28 -> -4960 | G28: 1.36 | H28: 0.24 | J28: 8.99 | K28: =SUM(F28:J28) -> -4949.41 | Q28: =Q27+B28-K28-L28-M28+N28+O28+P28 -> 4949.41
A29: 42046 | B29: -4949.41 | Q29: =Q28+B29-K29-L29-M29+N29+O29+P29 -> 9.094947e-13
A30: 42094 | C30: ETER3 | O30: 44.88 | Q30: =Q29+B30-K30-L30-M30+N30+O30+P30 -> 44.88
A31: 42124 | C31: VALE5 | O31: 153.45 | Q31: =Q30+B31-K31-L31-M31+N31+O31+P31 -> 198.33
A32: 42164 | C32: VALE5 | D32: -300 | E32: 17 | F32: =D32*E32 -> -5100 | G32: 1.36 | H32: 0.24 | J32: 8.99 | K32: =SUM(F32:J32) -> -5089.41 | Q32: 0 | S32: Ajuste de saldo
A33: TOTAL | B33: =SUM(B2:B32) -> -3981.56 | D33: =SUM(D2:D32) -> 0 | G33: =SUM(G2:G32) -> 10.82 | H33: =SUM(H2:H32) -> 1.27 | J33: =SUM(J2:J32) -> 116.86 | K33: =SUM(K2:K32) -> -8578.35 | L33: =SUM(L2:L32) -> 0 | M33: =SUM(M2:M32) -> 0 | N33: =SUM(N2:N32) -> 0 | O33: =SUM(O2:O32) -> 462.33 | P33: =SUM(P2:P32) -> 228.62
A36: 42440 | B36: 1400 | Q36: =Q32+B36-K36-L36-M36+N36+O36+P36 -> 1400
A37: 42444 | C37: PETR4 | D37: 200 | E37: 6.7 | F37: =D37*E37 -> 1340 | G37: 0.36 | H37: 0.06 | J37: 8.99 | K37: =SUM(F37:J37) -> 1349.41 | Q37: =Q36+B37-K37-L37-M37+N37+O37+P37 -> 50.59
A38: 42445 | B38: 2300 | Q38: =Q37+B38-K38-L38-M38+N38+O38+P38 -> 2350.59
A39: 42445 | C39: BBAS3 | D39: 100 | E39: 18.22 | F39: =D39*E39 -> 1822 | G39: 0.36 | H39: 0.06 | J39: 8.99 | K39: =SUM(F39:J39) -> 1831.41 | Q39: =Q38+B39-K39-L39-M39+N39+O39+P39 -> 519.18
A40: 42446 | C40: PETRD10 | D40: 100 | E40: 0.3 | F40: =D40*E40 -> 30 | G40: 0.36 | H40: 0.06 | J40: 8.99 | K40: =SUM(F40:J40) -> 39.41 | Q40: =Q39+B40-K40-L40-M40+N40+O40+P40 -> 479.77
A41: 42446 | C41: PETR4 | D41: -200 | E41: 8.14 | F41: =D41*E41 -> -1628 | K41: =SUM(F41:J41) -> -1628 | Q41: =Q40+B41-K41-L41-M41+N41+O41+P41 -> 2107.77
A42: 42452 | C42: BBAS3 | D42: -100 | E42: 21 | F42: =D42*E42 -> -2100 | G42: 1.23 | H42: 0.06 | J42: 8.99 | K42: =SUM(F42:J42) -> -2089.72 | Q42: =Q41+B42-K42-L42-M42+N42+O42+P42 -> 4197.49
A43: 42452 | C43: PETR4 | D43: 500 | E43: 7.9 | F43: =D43*E43 -> 3950 | G43: 1.23 | H43: 0.06 | J43: 8.99 | K43: =SUM(F43:J43) -> 3960.28 | Q43: =Q42+B43-K43-L43-M43+N43+O43+P43 -> 237.21
A44: 42459 | C44: PETR4 | D44: -500 | E44: 9 | F44: =D44*E44 -> -4500 | G44: 1.23 | H44: 0.06 | J44: 8.99 | K44: =SUM(F44:J44) -> -4489.72 | Q44: =Q43+B44-K44-L44-M44+N44+O44+P44 -> 4726.93
A45: 42464 | C45: PETR4 | D45: 600 | E45: 7.8 | F45: =D45*E45 -> 4680 | G45: 1.23 | H45: 0.06 | J45: 8.99 | K45: =SUM(F45:J45) -> 4690.28 | Q45: =Q44+B45-K45-L45-M45+N45+O45+P45 -> 36.65
A46: 42468 | C46: PETR4 | D46: -600 | E46: 8.25 | F46: =D46*E46 -> -4950 | G46: 1.23 | H46: 0.06 | J46: 8.99 | K46: =SUM(F46:J46) -> -4939.72 | Q46: =Q45+B46-K46-L46-M46+N46+O46+P46 -> 4976.37
A47: 42487 | C47: CMIG3 | D47: 600 | E47: 7.48 | F47: =D47*E47 -> 4488 | G47: 1.23 | H47: 0.44 | J47: 8.99 | K47: =SUM(F47:J47) -> 4498.66 | Q47: =Q46+B47-K47-L47-M47+N47+O47+P47 -> 477.71
A48: 42571 | B48: 500 | Q48: =Q47+B48-K48-L48-M48+N48+O48+P48 -> 977.71
A49: 42572 | C49: ITSA4 | D49: 100 | E49: 8.34 | F49: =D49*E49 -> 834 | G49: 1.23 | H49: 0.44 | J49: 8.99 | K49: =SUM(F49:J49) -> 844.66 | Q49: =Q48+B49-K49-L49-M49+N49+O49+P49 -> 133.05
A50: 42577 | B50: 5000 | Q50: =Q49+B50-K50-L50-M50+N50+O50+P50 -> 5133.05
A51: 42577 | C51: CMIG3 | D51: 400 | E51: 8.9 | F51: =D51*E51 -> 3560 | G51: 1.23 | H51: 0.44 | J51: 8.99 | K51: =SUM(F51:J51) -> 3570.66 | Q51: =Q50+B51-K51-L51-M51+N51+O51+P51 -> 1562.39
A52: 42578 | B52: 5000 | Q52: =Q51+B52-K52-L52-M52+N52+O52+P52 -> 6562.39
A53: 42578 | C53: PETR4 | D53: 100 | E53: 11.65 | F53: =D53*E53 -> 1165 | G53: 0.32 | H53: 0.05 | J53: 8.99 | K53: =SUM(F53:J53) -> 1174.36 | Q53: =Q52+B53-K53-L53-M53+N53+O53+P53 -> 5388.03
A54: 42579 | C54: BBAS3 | D54: 49 | E54: 20.69 | F54: =D54*E54 -> 1013.81 | G54: 0.56 | H54: 0.1 | J54: 11.98 | K54: =SUM(F54:J54) -> 1026.45 | Q54: =Q53+B54-K54-L54-M54+N54+O54+P54 -> 4361.58
A55: 42579 | C55: BBAS3 | D55: 51 | E55: 20.7 | F55: =D55*E55 -> 1055.7 | G55: 0 | H55: 0 | J55: 0 | K55: =SUM(F55:J55) -> 1055.7 | Q55: =Q54+B55-K55-L55-M55+N55+O55+P55 -> 3305.88
A56: 42584 | C56: TAEE11 | D56: 100 | E56: 23.35 | F56: =D56*E56 -> 2335 | G56: 0.64 | H56: 0.11 | J56: 8.99 | K56: =SUM(F56:J56) -> 2344.74 | Q56: =Q55+B56-K56-L56-M56+N56+O56+P56 -> 961.14
A57: 42583 | C57: NTNB | K57: 602.92 | Q57: =Q56+B57-K57-L57-M57+N57+O57+P57 -> 358.22
A58: 42584 | B58: 2000 | Q58: =Q57+B58-K58-L58-M58+N58+O58+P58 -> 2358.22
A59: 42586 | B59: 1500 | Q59: =Q58+B59-K59-L59-M59+N59+O59+P59 -> 3858.22
A60: 42586 | C60: ITSA4 | D60: 100 | E60: 8.66 | F60: =D60*E60 -> 866 | G60: 0.23 | H60: 0.04 | J60: 8.99 | K60: =SUM(F60:J60) -> 875.26 | Q60: =Q59+B60-K60-L60-M60+N60+O60+P60 -> 2982.96
A61: 42591 | C61: KLBN4 | D61: 500 | E61: 2.51 | F61: =D61*E61 -> 1255 | G61: 0.34 | H61: 0.06 | J61: 8.99 | K61: =SUM(F61:J61) -> 1264.39 | Q61: =Q60+B61-K61-L61-M61+N61+O61+P61 -> 1718.57
A62: 42597 | C62: NTNB | N62: 16.94 | Q62: =Q61+B62-K62-L62-M62+N62+O62+P62 -> 1735.51
A63: 42598 | C63: PETRI29 | D63: 10000 | E63: 0.01 | F63: =D63*E63 -> 100 | G63: 0.08 | H63: 0.03 | J63: 5.99 | K63: =SUM(F63:J63) -> 106.1 | Q63: =Q62+B63-K63-L63-M63+N63+O63+P63 -> 1629.41
A64: 42593 | C64: ETER3 | D64: 800 | E64: 1.76 | F64: =D64*E64 -> 1408 | G64: 0.38 | H64: 0.09 | J64: 8.99 | K64: =SUM(F64:J64) -> 1417.46 | Q64: =Q63+B64-K64-L64-M64+N64+O64+P64 -> 211.95
A65: 42600 | B65: 5000 | Q65: =Q64+B65-K65-L65-M65+N65+O65+P65 -> 5211.95
A66: 42600 | C66: CMIG3 | D66: 100 | E66: 9.44 | F66: =D66*E66 -> 944 | G66: 0.35 | H66: 0.06 | J66: 8.99 | K66: =SUM(F66:J66) -> 953.4 | Q66: =Q65+B66-K66-L66-M66+N66+O66+P66 -> 4258.55
A67: 42600 | C67: ETER3 | D67: 200 | E67: 1.73 | F67: =D67*E67 -> 346 | G67: 0 | H67: 0 | J67: 8.99 | K67: =SUM(F67:J67) -> 354.99 | Q67: =Q66+B67-K67-L67-M67+N67+O67+P67 -> 3903.56
A68: 42606 | C68: CMIG3 | D68: 100 | E68: 8.85 | F68: =D68*E68 -> 885 | G68: 0.24 | H68: 0.04 | J68: 8.99 | K68: =SUM(F68:J68) -> 894.27 | Q68: =Q67+B68-K68-L68-M68+N68+O68+P68 -> 3009.29
A69: 42607 | C69: ITSA4 | P69: 13.43 | Q69: =Q68+B69-K69-L69-M69+N69+O69+P69 -> 3022.72
A70: 42608 | C70: ITSA4 | D70: 100 | E70: 8.55 | F70: =D70*E70 -> 855 | G70: 0.23 | H70: 0.04 | J70: 8.99 | K70: =SUM(F70:J70) -> 864.26 | Q70: =Q69+B70-K70-L70-M70+N70+O70+P70 -> 2158.46
A71: 42611 | C71: TAEE11 | P71: 6.05 | Q71: =Q70+B71-K71-L71-M71+N71+O71+P71 -> 2164.51
A72: 42611 | C72: TAEE11 | O72: 50.51 | Q72: =Q71+B72-K72-L72-M72+N72+O72+P72 -> 2215.02
A73: 42612 | C73: NTNB | K73: 592 | Q73: =Q72+B73-K73-L73-M73+N73+O73+P73 -> 1623.02
A74: 42613 | C74: ITSA4 | D74: 100 | E74: 8.57 | F74: =D74*E74 -> 857 | G74: 0.23 | H74: 0.04 | J74: 8.99 | K74: =SUM(F74:J74) -> 866.26 | Q74: =Q73+B74-K74-L74-M74+N74+O74+P74 -> 756.76
A75: 42613 | C75: BBAS3 | P75: 11.87 | Q75: =Q74+B75-K75-L75-M75+N75+O75+P75 -> 768.63
A76: 42615 | B76: 2000 | Q76: =Q75+B76-K76-L76-M76+N76+O76+P76 -> 2768.63
A77: 42615 | C77: ETER3 | D77: 800 | E77: 1.65 | F77: =D77*E77 -> 1320 | G77: 0 | H77: 0 | J77: 8.99 | K77: =SUM(F77:J77) -> 1328.99 | Q77: =Q76+B77-K77-L77-M77+N77+O77+P77 -> 1439.64
A78: 42615 | C78: KLBN4 | D78: 500 | E78: 2.58 | F78: =D78*E78 -> 1290 | G78: 0 | H78: 0 | J78: 8.99 | K78: =SUM(F78:J78) -> 1298.99 | Q78: =Q77+B78-K78-L78-M78+N78+O78+P78 -> 140.65
A79: 42621 | B79: 2000 | Q79: =Q78+B79-K79-L79-M79+N79+O79+P79 -> 2140.65
A80: 42615 | C80: ITSA4 | D80: 200 | E80: 8.41 | F80: =D80*E80 -> 1682 | G80: 0 | H80: 0 | J80: 8.99 | K80: =SUM(F80:J80) -> 1690.99 | Q80: =Q79+B80-K80-L80-M80+N80+O80+P80 -> 449.66
A81: 42633 | B81: 1000 | Q81: =Q80+B81-K81-L81-M81+N81+O81+P81 -> 1449.66
A82: 42633 | C82: CMIG3 | D82: 100 | E82: 8.6 | F82: =D82*E82 -> 860 | G82: 0.23 | H82: 0.04 | J82: 8.99 | K82: =SUM(F82:J82) -> 869.26 | Q82: =Q81+B82-K82-L82-M82+N82+O82+P82 -> 580.4
A83: 42639 | B83: 600 | Q83: =Q82+B83-K83-L83-M83+N83+O83+P83 -> 1180.4
A84: 42639 | C84: NTNB | K84: 568.05 | Q84: =Q83+B84-K84-L84-M84+N84+O84+P84 -> 612.35
A85: 42639 | C85: NTNB | K85: 538.15 | Q85: =Q84+B85-K85-L85-M85+N85+O85+P85 -> 74.2
A86: 42643 | C86: BBAS3 | P86: 10.77 | Q86: =Q85+B86-K86-L86-M86+N86+O86+P86 -> 84.97
A87: 42646 | B87: 2500 | Q87: =Q86+B87-K87-L87-M87+N87+O87+P87 -> 2584.97
A88: 42646 | C88: TAEE11 | D88: 100 | E88: 20.81 | F88: =D88*E88 -> 2081 | G88: 0.64 | H88: 0.11 | J88: 8.99 | K88: =SUM(F88:J88) -> 2090.74 | Q88: =Q87+B88-K88-L88-M88+N88+O88+P88 -> 494.23
A89: 42646 | C89: ITSA4 | O89: 6 | Q89: =Q88+B89-K89-L89-M89+N89+O89+P89 -> 500.23
A90: 42649 | B90: 1000 | Q90: =Q89+B90-K90-L90-M90+N90+O90+P90 -> 1500.23
A91: 42653 | B91: 1000 | Q91: =Q90+B91-K91-L91-M91+N91+O91+P91 -> 2500.23
A92: 42653 | C92: ITSA4 | D92: 200 | E92: 8.81 | F92: =D92*E92 -> 1762 | G92: 0 | H92: 0 | J92: 8.99 | K92: =SUM(F92:J92) -> 1770.99 | Q92: =Q91+B92-K92-L92-M92+N92+O92+P92 -> 729.24
A93: 42654 | C93: NTNB | K93: 603.85 | Q93: =Q92+B93-K93-L93-M93+N93+O93+P93 -> 125.39
A94: 42660 | B94: 1000 | Q94: =Q93+B94-K94-L94-M94+N94+O94+P94 -> 1125.39
A95: 42663 | B95: 1000 | Q95: =Q94+B95-K95-L95-M95+N95+O95+P95 -> 2125.39
A96: 42663 | C96: CMIG3 | D96: 200 | E96: 8.85 | F96: =D96*E96 -> 1770 | G96: 0.23 | H96: 0.04 | J96: 8.99 | K96: =SUM(F96:J96) -> 1779.26 | Q96: =Q95+B96-K96-L96-M96+N96+O96+P96 -> 346.13
A97: 42668 | B97: 2000 | Q97: =Q96+B97-K97-L97-M97+N97+O97+P97 -> 2346.13
A98: 42668 | C98: ITSA4 | D98: 200 | E98: 8.81 | F98: =D98*E98 -> 1762 | G98: 0 | H98: 0 | J98: 8.99 | K98: =SUM(F98:J98) -> 1770.99 | Q98: =Q97+B98-K98-L98-M98+N98+O98+P98 -> 575.14
A99: 42674 | B99: 1500 | Q99: =Q98+B99-K99-L99-M99+N99+O99+P99 -> 2075.14
A100: 42675 | C100: TAEE11 | D100: 76 | E100: 20.46 | F100: =D100*E100 -> 1554.96 | G100: 0 | H100: 0 | J100: 8.99 | K100: =SUM(F100:J100) -> 1563.95 | Q100: =Q99+B100-K100-L100-M100+N100+O100+P100 -> 511.19
A101: 42683 | B101: 1000 | Q101: =Q100+B101-K101-L101-M101+N101+O101+P101 -> 1511.19
A102: 42683 | C102: NTNB | K102: 450.17 | Q102: =Q101+B102-K102-L102-M102+N102+O102+P102 -> 1061.02
...

Sheet Dividendos
A1: PROVENTOS - 2013
A2: ATIVO | B2: JANEIRO | C2: FEVEREIRO | D2: MARÇO | E2: ABRIL | F2: MAIO | G2: JUNHO | H2: JULHO | I2: AGOSTO | J2: SETEMBRO | K2: OUTUBRO | L2: NOVEMBRO | M2: DEZEMBRO | N2: TOTAL
A3: AÇÕES
A4: ABCB4 | N4: =SUM(B4:M4) -> 0
A5: BBAS3 | I5: 155.67 | J5: 53.34 | L5: 13.32 | M5: 52.65 | N5: =SUM(B5:M5) -> 274.98
A6: BVMF3 | L6: 11.83 | N6: =SUM(B6:M6) -> 11.83
A7: CMIG3 | M7: 47.09 | N7: =SUM(B7:M7) -> 47.09
A8: CMIG4 | N8: =SUM(B8:M8) -> 0
A9: ECOR3 | N9: =SUM(B9:M9) -> 0
A10: ELET3 | N10: =SUM(B10:M10) -> 0
A11: ELPL4 | N11: =SUM(B11:M11) -> 0
A12: ETER3 | N12: =SUM(B12:M12) -> 0
A13: HGTX3 | N13: =SUM(B13:M13) -> 0
A14: ITSA4 | N14: =SUM(B14:M14) -> 0
A15: KLBN4 | N15: =SUM(B15:M15) -> 0
A16: ODPV3 | J16: 5.87 | L16: 1.52 | M16: 6.31 | N16: =SUM(B16:M16) -> 13.7
A17: OIBR3 | K17: 152.43 | N17: =SUM(B17:M17) -> 152.43
A18: PETR3 | N18: =SUM(B18:M18) -> 0
A19: PETR4 | N19: =SUM(B19:M19) -> 0
A20: SULA11 | I20: 3.6 | L20: 3.6 | M20: 7.63 | N20: =SUM(B20:M20) -> 14.83
A21: SUZB5 | N21: =SUM(B21:M21) -> 0
A22: TAEE11 | N22: =SUM(B22:M22) -> 0
A23: TIET11 | N23: =SUM(B23:M23) -> 0
A24: VALE5 | N24: =SUM(B24:M24) -> 0
N25: =SUM(B25:M25) -> 0
N26: =SUM(B26:M26) -> 0
A27: TOTAIS | B27: =SUM(B4:B26) -> 0 | C27: =SUM(C4:C26) -> 0 | D27: =SUM(D4:D26) -> 0 | E27: =SUM(E4:E26) -> 0 | F27: =SUM(F4:F26) -> 0 | G27: =SUM(G4:G26) -> 0 | H27: =SUM(H4:H26) -> 0 | I27: =SUM(I4:I26) -> 159.27 | ... N27: =SUM(N4:N26) -> 514.86
N28: =SUM(B28:M28) -> 0
A29: FIIs
A30: BCFF11 | N30: =SUM(B30:M30) -> 0
A31: BPFF11 | N31: =SUM(B31:M31) -> 0
A32: EDGA11 | N32: =SUM(B32:M32) -> 0
A33: FIGS11 | N33: =SUM(B33:M33) -> 0
A34: GGRC11 | N34: =SUM(B34:M34) -> 0
A35: MXRF11 | N35: =SUM(B35:M35) -> 0
A36: RBGS11 | N36: =SUM(B36:M36) -> 0
A37: RBRR11 | N37: =SUM(B37:M37) -> 0
A38: SDIL11 | N38: =SUM(B38:M38) -> 0
A39: SPTW11 | N39: =SUM(B39:M39) -> 0
A40: VISC11 | N40: =SUM(B40:M40) -> 0
A41: XPLG11 | N41: =SUM(B41:M41) -> 0
A42: HGRU11 | N42: =SUM(B42:M42) -> 0
A43: XPML11
A44: HTMX11
N46: =SUM(B46:M46) -> 0
A47: TOTAIS | B47: =SUM(B30:B46) -> 0 | C47: =SUM(C30:C46) -> 0 | D47: =SUM(D30:D46) -> 0 | E47: =SUM(E30:E46) -> 0 | F47: =SUM(F30:F46) -> 0 | G47: =SUM(G30:G46) -> 0 | H47: =SUM(H30:H46) -> 0 | I47: =SUM(I30:I46) -> 0 | ... N47: =SUM(N30:N46) -> 0
N48: =SUM(B48:M48) -> 0
A49: TESOURO
A50: NTN-B | N50: =SUM(B50:M50) -> 0
A51: NTN-F | N51: =SUM(B51:M51) -> 0
N52: =SUM(B52:M52) -> 0
A53: TOTAIS | B53: =SUM(B50:B52) -> 0 | C53: =SUM(C50:C52) -> 0 | D53: =SUM(D50:D52) -> 0 | E53: =SUM(E50:E52) -> 0 | F53: =SUM(F50:F52) -> 0 | G53: =SUM(G50:G52) -> 0 | H53: =SUM(H50:H52) -> 0 | I53: =SUM(I50:I52) -> 0 | ... N53: =SUM(N50:N52) -> 0
B54: JANEIRO | C54: FEVEREIRO | D54: MARÇO | E54: ABRIL | F54: MAIO | G54: JUNHO | H54: JULHO | I54: AGOSTO | J54: SETEMBRO | K54: OUTUBRO | L54: NOVEMBRO | M54: DEZEMBRO
A55: TOTAL GERAL | B55: =B27+B47+B53 -> 0 | C55: =C27+C47+C53 -> 0 | D55: =D27+D47+D53 -> 0 | E55: =E27+E47+E53 -> 0 | F55: =F27+F47+F53 -> 0 | G55: =G27+G47+G53 -> 0 | H55: =H27+H47+H53 -> 0 | I55: =I27+I47+I53 -> 159.27 | ... N55: =N27+N47+N53 -> 514.86
A59: PROVENTOS - 2014
A60: ATIVO | B60: JANEIRO | C60: FEVEREIRO | D60: MARÇO | E60: ABRIL | F60: MAIO | G60: JUNHO | H60: JULHO | I60: AGOSTO | J60: SETEMBRO | K60: OUTUBRO | L60: NOVEMBRO | M60: DEZEMBRO | N60: TOTAL
A61: AÇÕES
A62: ABCB4 | N62: =SUM(B62:M62) -> 0
A63: BBAS3 | C63: 39.51 | D63: 106.99 | F63: 32.48 | G63: 109.17 | I63: 15.69 | N63: =SUM(B63:M63) -> 303.84
A64: BVMF3 | F64: 11.15 | G64: 7.96 | I64: 10.93 | N64: =SUM(B64:M64) -> 30.04
A65: CMIG3 | G65: 89.2 | H65: 87.42 | J65: 48 | M65: 349.68 | N65: =SUM(B65:M65) -> 574.3
A66: CMIG4 | G66: 38.39 | H66: 26.22 | J66: 14.4 | N66: =SUM(B66:M66) -> 79.01
A67: ECOR3 | N67: =SUM(B67:M67) -> 0
A68: ELET3 | F68: 52.83 | N68: =SUM(B68:M68) -> 52.83
A69: ELPL4 | L69: 171.14 | N69: =SUM(B69:M69) -> 171.14
A70: ETER3 | I70: 56.99 | L70: 180.46 | N70: =SUM(B70:M70) -> 237.45
A71: HGTX3 | N71: =SUM(B71:M71) -> 0
A72: ITSA4 | N72: =SUM(B72:M72) -> 0
A73: KLBN4 | N73: =SUM(B73:M73) -> 0
A74: ODPV3 | N74: =SUM(B74:M74) -> 0
A75: OIBR3 | N75: =SUM(B75:M75) -> 0
A76: PETR3 | E76: 45.62 | N76: =SUM(B76:M76) -> 45.62
A77: PETR4 | N77: =SUM(B77:M77) -> 0
A78: SULA11 | E78: 13.98 | N78: =SUM(B78:M78) -> 13.98
A79: SUZB5 | F79: 23.2 | N79: =SUM(B79:M79) -> 23.2
A80: TAEE11 | N80: =SUM(B80:M80) -> 0
A81: TIET11 | N81: =SUM(B81:M81) -> 0
A82: VALE5 | K82: 267.98 | N82: =SUM(B82:M82) -> 267.98
N83: =SUM(B83:M83) -> 0
N84: =SUM(B84:M84) -> 0
A85: TOTAIS | B85: =SUM(B62:B84) -> 0 | C85: =SUM(C62:C84) -> 39.51 | D85: =SUM(D62:D84) -> 106.99 | E85: =SUM(E62:E84) -> 59.6 | F85: =SUM(F62:F84) -> 119.66 | G85: =SUM(G62:G84) -> 244.72 | H85: =SUM(H62:H84) -> 113.64 | I85: =SUM(I62:I84) -> 83.61 | ... N85: =SUM(N62:N84) -> 1799.39
N86: =SUM(B86:M86) -> 0
A87: FIIs
A88: BCFF11 | N88: =SUM(B88:M88) -> 0
A89: BPFF11 | N89: =SUM(B89:M89) -> 0
A90: EDGA11 | N90: =SUM(B90:M90) -> 0
A91: FIGS11 | N91: =SUM(B91:M91) -> 0
A92: GGRC11 | N92: =SUM(B92:M92) -> 0
A93: MXRF11 | N93: =SUM(B93:M93) -> 0
A94: RBGS11 | N94: =SUM(B94:M94) -> 0
A95: RBRR11 | N95: =SUM(B95:M95) -> 0
A96: SDIL11 | N96: =SUM(B96:M96) -> 0
A97: SPTW11 | N97: =SUM(B97:M97) -> 0
A98: VISC11 | N98: =SUM(B98:M98) -> 0
A99: XPLG11 | N99: =SUM(B99:M99) -> 0
A100: HGRU11 | N100: =SUM(B100:M100) -> 0
A101: XPML11
A102: HTMX11
N104: =SUM(B104:M104) -> 0
A105: TOTAIS | B105: =SUM(B88:B104) -> 0 | C105: =SUM(C88:C104) -> 0 | D105: =SUM(D88:D104) -> 0 | E105: =SUM(E88:E104) -> 0 | F105: =SUM(F88:F104) -> 0 | G105: =SUM(G88:G104) -> 0 | H105: =SUM(H88:H104) -> 0 | I105: =SUM(I88:I104) -> 0 | ... N105: =SUM(N88:N104) -> 0
...

Sheet Plano de Metas
A1: OBJETIVOS PARA 2016 | T1: RESUMO MENSAL DOS INVESTIMENTOS EM 2016 | AL1: DESPESAS
A2: ATIVOS ATUAIS | C2: OBJETIVO EM 30/12/2016 | E2: FALTA | F2: % | G2: COTAÇÃO | H2: VL TOTAL | J2: STATUS | T2: MÊS | U2: RDB | V2: AÇÕES | W2: FI - FUND IMOB | X2: TESOURO | Y2: SERGUS | AB2: Ouro | AC2: OURO (gramas) | AD2: Criptomoedas U$ | AE2: Hasflare U$ | AF2: TOTAL
A3: ETER3 | B3: 3800 | C3: 5000 | E3: =C3-B3 -> 1200 | F3: =B3/C3 -> 0.76 | G3: 1.41 | H3: =G3*B3 -> 5358 | T3: JULHO | V3: =842+3570+1174+2082 -> 7668 | W3: 0 | X3: 600.92 | Y3: 0 | AB3: 0 | AC3: 0 | AF3: =SUM(U3:AB3) -> 8268.92
A4: CMIG3 | B4: 1800 | C4: 2000 | E4: =C4-B4 -> 200 | F4: =B4/C4 -> 0.9 | G4: 7.53 | H4: =G4*B4 -> 13554 | T4: AGOSTO | U4: 0 | V4: =2344+875+1264+1417+1308+894+864+866 -> 9832 | W4: 0 | X4: 592 | Y4: 0 | AB4: 0 | AC4: 0 | AF4: =SUM(U4:AC4) -> 10424
A5: PETR4 | B5: 100 | C5: 500 | E5: =C5-B5 -> 400 | F5: =B5/C5 -> 0.2 | G5: 15.6 | H5: =G5*B5 -> 1560 | T5: SETEMBRO | U5: 0 | V5: =2628+1691+869 -> 5188 | W5: 0 | X5: =538.15+568.05 -> 1106.2 | Y5: 0 | AB5: 0 | AC5: 0 | AF5: =SUM(U5:AC5) -> 6294.2
A6: ITSA4 | B6: 1300 | C6: 2000 | E6: =C6-B6 -> 700 | F6: =B6/C6 -> 0.65 | G6: 8.07 | H6: =G6*B6 -> 10491 | T6: OUTUBRO | U6: 0 | V6: =2090+1771+1799+1779 -> 7439 | W6: 0 | X6: 603.85 | Y6: 0 | AB6: 0 | AC6: 0 | AF6: =SUM(U6:AC6) -> 8042.85
A7: BBAS3 | B7: 100 | C7: 500 | E7: =C7-B7 -> 400 | F7: =B7/C7 -> 0.2 | G7: 25.68 | H7: =G7*B7 -> 2568 | T7: NOVEMBRO | U7: 0 | V7: =1561+903+1121+1211+883 -> 5679 | W7: 0 | X7: =450.17+585.55 -> 1035.72 | Y7: 0 | AB7: 0 | AC7: 0 | AF7: =SUM(U7:AC7) -> 6714.72
A8: TAE11 | B8: 400 | C8: 500 | E8: =C8-B8 -> 100 | F8: =B8/C8 -> 0.8 | G8: 19.6 | H8: =G8*B8 -> 7840 | T8: DEZEMBRO | U8: 0 | V8: =1559+828+802 -> 3189 | W8: 0 | X8: =295.94+360.29+602.96 -> 1259.19 | Y8: 0 | AB8: 250 | AC8: 2.05 | AF8: =SUM(U8:AB8) -> 4698.19
A9: KLBN4 | B9: 1000 | C9: 2000 | E9: =C9-B9 -> 1000 | F9: =B9/C9 -> 0.5 | G9: 2.7 | H9: =G9*B9 -> 2700 | T9: TOTAIS | U9: =SUM(U3:U8) -> 0 | V9: =SUM(V3:V8) -> 38995 | W9: 0 | X9: =SUM(X3:X8) -> 5197.88 | Y9: =SUM(Y3:Y8) -> 0 | AB9: =SUM(AB3:AB8) -> 250 | AC9: =SUM(AC3:AC8) -> 2.05 | AF9: =SUM(AF3:AF8) -> 44442.88
A10: TOTAL | B10: =SUM(B3:B9) -> 8500 | C10: =SUM(C3:C9) -> 12500 | E10: =SUM(E3:E9) -> 4000 | H10: =SUM(H3:H9) -> 44071
A12: OBJETIVOS PARA 2020 | T12: RESUMO MENSAL DOS INVESTIMENTOS EM 2017 | AL12: DESPESAS
A13: ATIVOS ATUAIS | C13: OBJETIVO EM 30/12/2019 | E13: FALTA | F13: % | G13: COTAÇÃO | H13: VL TOTAL | J13: STATUS | T13: MÊS | U13: RDB | V13: AÇÕES | W13: FI - FUND IMOB | X13: TESOURO | Y13: SERGUS | AB13: OURO | AC13: OURO (gramas) | AF13: TOTAL | AH13: CAPACIDADE DE POUPANÇA
A14: ABCB4 | B14: 861 | C14: 1000 | E14: =C14-B14 -> 139 | F14: =B14/C14 -> 0.861 | G14: 14.44 | H14: =G14*B14 -> 12432.84 | T14: JANEIRO | U14: 0 | V14: =719+852+879+1582 -> 4032 | W14: 0 | X14: 624.04 | Y14: 0 | AB14: 0 | AC14: 0 | AF14: =SUM(U14:AB14) -> 4656.04 | AH14: =AF14/(B62+B71) -> 0.33687376 | AL14: =B75-AF14 -> 9165.28
A15: BBAS3 | B15: 334 | C15: 1000 | E15: =C15-B15 -> 666 | F15: =B15/C15 -> 0.334 | G15: 34.75 | H15: =G15*B15 -> 11606.5 | T15: FEVEREIRO | U15: 0 | V15: =2967+1379+1638 -> 5984 | W15: 0 | X15: =626.97+530.62 -> 1157.59 | Y15: 0 | AB15: 0 | AC15: 0 | AF15: =SUM(U15:AB15) -> 7141.59 | AH15: =AF15/(C$62+C$71) -> 0.47801103 | AL15: =C75-AF15 -> 7798.63
A16: BCFF11 | B16: 615 | C16: 1000 | E16: =C16-B16 -> 385 | F16: =B16/C16 -> 0.615 | G16: 88.7 | H16: =G16*B16 -> 54550.5 | T16: MARÇO | U16: 0 | V16: =1010+1399+977 -> 3386 | W16: 0 | X16: =754.9+792.7 -> 1547.6 | Y16: 0 | AB16: 0 | AC16: 0 | AF16: =SUM(U16:AB16) -> 4933.6 | AH16: =AF16/(D$62+D$71) -> 0.36756029 | AL16: =D75-AF16 -> 8488.96
A17: BMEB4 | B17: 400 | C17: 500 | E17: =C17-B17 -> 100 | F17: =B17/C17 -> 0.8 | G17: 12.12 | H17: =G17*B17 -> 4848 | T17: ABRIL | U17: 0 | V17: 1319 | W17: 0 | X17: 476.82 | Y17: 0 | AB17: 0 | AC17: 0 | AF17: =SUM(U17:AB17) -> 1795.82 | AH17: =AF17/(E$62+E$71) -> 0.17065131 | AL17: =E75-AF17 -> 8727.51
A18: BPFF11 | B18: 245 | C18: 500 | E18: =C18-B18 -> 255 | F18: =B18/C18 -> 0.49 | G18: 95.8 | H18: =G18*B18 -> 23471 | T18: MAIO | U18: 0 | V18: =813+797+1795 -> 3405 | W18: 0 | X18: 1096.42 | Y18: 0 | AB18: 0 | AC18: 0 | AF18: =SUM(U18:AB18) -> 4501.42 | AH18: =AF18/(F$62+F$71) -> 0.26612127 | AL18: =F75-AF18 -> 12413.5
A19: BRSR6 | B19: 1000 | C19: 2000 | E19: =C19-B19 -> 1000 | F19: =B19/C19 -> 0.5 | G19: 14.32 | H19: =G19*B19 -> 14320 | T19: JUNHO | U19: =3000+5000+2000 -> 10000 | V19: =1953+1777 -> 3730 | W19: 0 | X19: 475.11 | Y19: 0 | AB19: 300 | AC19: 2.12 | AF19: =SUM(U19:AB19) -> 14505.11 | AH19: =AF19/(G$62+G$71) -> 1.0904392 | AL19: =G75-AF19 -> -1203.03
A20: CMIG3 | B20: 1500 | C20: 5000 | E20: =C20-B20 -> 3500 | F20: =B20/C20 -> 0.3 | G20: 11.72 | H20: =G20*B20 -> 17580 | T20: JULHO | U20: 5000 | V20: 1365 | W20: 4330 | X20: 944.29 | Y20: 0 | AB20: 350 | AC20: 2.3 | AF20: =SUM(U20:AB20) -> 11989.29 | AH20: =AF20/(H$62+H$71) -> 0.71281405 | AL20: =H75-AF20 -> 4830.37
A21: CMIG4 | B21: 100 | C21: 1000 | E21: =C21-B21 -> 900 | F21: =B21/C21 -> 0.1 | G21: 11.26 | H21: =G21*B21 -> 1126 | T21: AGOSTO | U21: 4000 | V21: 0 | W21: =3970+2090 -> 6060 | X21: 0 | Y21: 0 | AB21: 300 | AC21: 2.1 | AF21: =SUM(U21:AB21) -> 10360 | AH21: =AF21/(I$62+I$71) -> 0.59909985 | AL21: =I75-AF21 -> 6932.61
A22: ECOR3 | B22: 400 | C22: 1000 | E22: =C22-B22 -> 600 | F22: =B22/C22 -> 0.4 | G22: 14.17 | H22: =G22*B22 -> 5668 | T22: SETEMBRO | U22: 0 | V22: 2330 | W22: =2100+1750 -> 3850 | X22: 0 | Y22: 0 | AB22: 0 | AC22: 0 | AF22: =SUM(U22:AB22) -> 6180 | AH22: =AF22/(J$62+J$71) -> 0.39762634 | AL22: =J75-AF22 -> 9362.23
A23: EDGA11 | B23: 116 | C23: 200 | E23: =C23-B23 -> 84 | F23: =B23/C23 -> 0.58 | G23: 33.72 | H23: =G23*B23 -> 3911.52 | T23: OUTUBRO | U23: 2000 | V23: =768+1620 -> 2388 | W23: =1470+2274 -> 3744 | X23: 0 | Y23: 0 | AB23: 0 | AC23: 0 | AF23: =SUM(U23:AB23) -> 8132 | AH23: =AF23/(K$62+K$71) -> 0.47094089 | AL23: =K75-AF23 -> 9135.56
A24: ETER3 | B24: 550 | C24: 550 | E24: =C24-B24 -> 0 | F24: =B24/C24 -> 1 | G24: 8.59 | H24: =G24*B24 -> 4724.5 | T24: NOVEMBRO | U24: 0 | V24: =1657+1970 -> 3627 | W24: =1025+1147+2340+1010 -> 5522 | X24: 0 | Y24: 0 | AB24: 365.42 | AC24: 2.38 | AF24: =SUM(U24:AB24) -> 9514.42 | AH24: =AF24/(L$62+L$71) -> 0.56986497 | AL24: =L75-AF24 -> 7181.5
A25: FIGS11 | B25: 200 | C25: 200 | E25: =C25-B25 -> 0 | F25: =B25/C25 -> 1 | G25: 60.1 | H25: =G25*B25 -> 12020 | T25: DEZEMBRO | U25: 0 | V25: =1591+1576+836 -> 4003 | W25: =993+1184+1165+1019 -> 4361 | X25: 229.43 | Y25: 0 | AB25: 0 | AC25: 0 | AD25: =592 -> 592 | AE25: 2261.7 | AF25: =SUM(U25:AB25) -> 8593.43 | AH25: =AF25/(M$62+M$71) -> 0.51782936 | AL25: =M75-AF25 -> 8001.67
A26: GGRC11 | B26: 40 | C26: 500 | E26: =C26-B26 -> 460 | F26: =B26/C26 -> 0.08 | G26: 123.97 | H26: =G26*B26 -> 4958.8 | T26: TOTAIS | U26: =SUM(U14:U25) -> 21000 | V26: =SUM(V14:V25) -> 35569 | W26: =SUM(W14:W25) -> 27867 | X26: =SUM(X14:X25) -> 6551.3 | Y26: =SUM(Y14:Y25) -> 0 | AB26: =SUM(AB14:AB25) -> 1315.42 | AC26: =SUM(AC14:AC25) -> 8.9 | AD26: =SUM(AD14:AD25) -> 592 | AE26: =SUM(AE14:AE25) -> 2261.7 | AF26: =SUM(AF14:AF25) -> 92302.72 | AH26: =AF26/(N$62+N$71) -> 0.50400773 | AJ26: =AVERAGE(AF14:AF25) -> 7691.8933 | AL26: =N75-AF26 -> 90834.79
A27: HGRU11 | B27: 30 | C27: 200 | E27: =C27-B27 -> 170 | F27: =B27/C27 -> 0.15 | G27: 130.2 | H27: =G27*B27 -> 3906
A28: HGTX3 | B28: 0 | C28: 1000 | E28: =C28-B28 -> 1000 | F28: =B28/C28 -> 0 | G28: 28 | H28: =G28*B28 -> 0
A29: HTMX11 | B29: 10 | C29: 300 | E29: =C29-B29 -> 290 | F29: =B29/C29 -> 0.033333333 | G29: 118.51 | H29: =G29*B29 -> 1185.1 | T29: RESUMO MENSAL DOS INVESTIMENTOS EM 2018 | AL29: DESPESAS
A30: ITSA4 | B30: 3290 | C30: 5000 | E30: =C30-B30 -> 1710 | F30: =B30/C30 -> 0.658 | G30: 9.9 | H30: =G30*B30 -> 32571 | T30: MÊS | U30: RDB | V30: AÇÕES | W30: FI - FUND IMOB | X30: TESOURO | Y30: SERGUS | AB30: OURO | AC30: OURO (gramas) | AD30: Criptomoedas U$ | AE30: Hasflare U$ | AF30: TOTAL | AH30: CAPACIDADE DE POUPANÇA
A31: KLBN4 | B31: 4100 | C31: 5000 | E31: =C31-B31 -> 900 | F31: =B31/C31 -> 0.82 | G31: 3.9 | H31: =G31*B31 -> 15990 | T31: JANEIRO | U31: 0 | V31: =2032 -> 2032 | W31: =2371.5+1212 -> 3583.5 | X31: 0 | Y31: 0 | AE31: =880+660 -> 1540 | AF31: =SUM(U31:AB31) -> 5615.5 | AH31: =AF31/(B62+B71) -> 0.4062926 | AL31: =B97-AF31 -> 12533.04
A32: MALL11 | B32: 25 | C32: 500 | E32: =C32-B32 -> 475 | F32: =B32/C32 -> 0.05 | G32: 88.57 | H32: =G32*B32 -> 2214.25 | T32: FEVEREIRO | U32: 0 | V32: 1078.6 | W32: 7456.65 | X32: 1169.45 | Y32: 0 | AF32: =SUM(U32:AB32) -> 9704.7 | AH32: =AF32/(C62+C71) -> 0.64956875 | AL32: =C97-AF32 -> 11946.12
A33: MXRF11 | B33: 2122 | C33: 5000 | E33: =C33-B33 -> 2878 | F33: =B33/C33 -> 0.4244 | G33: 10.91 | H33: =G33*B33 -> 23151.02 | T33: MARÇO | U33: 0 | V33: =1887+1670 -> 3557 | W33: 8053.64 | X33: 0 | Y33: 0 | AF33: =SUM(U33:AB33) -> 11610.64 | AH33: =AF33/(D62+D71) -> 0.86500936 | AL33: =D97-AF33 -> 6072.7
A34: OIBR3 | B34: 1500 | C34: 5000 | E34: =C34-B34 -> 3500 | F34: =B34/C34 -> 0.3 | G34: 0.82 | H34: =G34*B34 -> 1230 | T34: ABRIL | U34: 0 | V34: =351 -> 351 | W34: =1672+895.6 -> 2567.6 | X34: 0 | Y34: 0 | AF34: =SUM(U34:AB34) -> 2918.6 | AH34: =AF34/(E62+E71) -> 0.27734567 | AL34: =E97-AF34 -> 12319.07
A35: OUFF11 | B35: 70 | C35: 500 | E35: =C35-B35 -> 430 | F35: =B35/C35 -> 0.14 | G35: 85 | H35: =G35*B35 -> 5950 | T35: MAIO | U35: =3000+3000 -> 6000 | V35: =945+801 -> 1746 | W35: =1074.1+1560.6+1925.5+882 -> 5442.2 | X35: =500.08+460.17+655.95 -> 1616.2 | Y35: 502.54 | AF35: =SUM(U35:AB35) -> 15306.94 | AH35: =AF35/(F62+F71) -> 0.90493718 | AL35: =F97-AF35 -> 6363.7
A36: PETR4 | B36: 200 | C36: 1000 | E36: =C36-B36 -> 800 | F36: =B36/C36 -> 0.2 | G36: 20.84 | H36: =G36*B36 -> 4168 | T36: JUNHO | U36: 2000 | V36: =1015+1782 -> 2797 | W36: =706+610.92+393.6+896.5+720+998.2 -> 4325.22 | X36: 0 | Y36: 502.54 | AF36: =SUM(U36:AB36) -> 9624.76 | AH36: =AF36/(G62+G71) -> 0.72355301 | AL36: =G97-AF36 -> 4546.67
A37: PMAM3 | B37: 100 | C37: 500 | E37: =C37-B37 -> 400 | F37: =B37/C37 -> 0.2 | G37: 13.65 | H37: =G37*B37 -> 1365 | T37: JULHO | U37: 1000 | V37: =431.7+892 -> 1323.7 | W37: =887.8+685+480+477.5+736+478.5+501.5+733.2 -> 4979.5 | X37: =490.27+295.49 -> 785.76 | Y37: =502.54+423.88 -> 926.42 | AF37: =SUM(U37:AB37) -> 9015.38 | AH37: =AF37/(H62+H71) -> 0.53600251 | AL37: =H97-AF37 -> 6432.77
A38: RBFF11 | B38: 146 | C38: 500 | E38: =C38-B38 -> 354 | F38: =B38/C38 -> 0.292 | G38: 73.45 | H38: =G38*B38 -> 10723.7 | T38: AGOSTO | U38: =1000 -> 1000 | V38: =552+895.8 -> 1447.8 | W38: =630.7+450.5+665+381+385.5+303.3+779 -> 3595 | X38: =368.86+133.07+506.23+492 -> 1500.16 | Y38: 502.54 | AF38: =SUM(U38:AB38) -> 8045.5 | AH38: =AF38/(I62+I71) -> 0.46525655 | AL38: =I97-AF38 -> 8648.9
A39: RBRR11 | B39: 60 | C39: 500 | E39: =C39-B39 -> 440 | F39: =B39/C39 -> 0.12 | G39: 99.6 | H39: =G39*B39 -> 5976 | T39: SETEMBRO | U39: 0 | V39: =721.5+717.5+485+966 -> 2890 | W39: =714.4+979.7+487.5+781.5+250+810+439.5+676.8+441.9+370.5 -> 5951.8 | X39: =496.6+533.75+475.22+407.52 -> 1913.09 | Y39: 527.65 | AF39: =SUM(U39:AB39) -> 11282.54 | AH39: =AF39/(J62+J71) -> 0.725928 | AL39: =J97-AF39 -> 6813.24
A40: RGBS11 | B40: 75 | C40: 500 | E40: =C40-B40 -> 425 | F40: =B40/C40 -> 0.15 | G40: 42.82 | H40: =G40*B40 -> 3211.5 | T40: OUTUBRO | U40: 0 | V40: =781+753.5+799 -> 2333.5 | W40: =711.5+608.79+969.1+493+436.45+335.55+9.87+616.25 -> 4180.51 | X40: 498.12 | Y40: 527.65 | AF40: =SUM(U40:AB40) -> 7539.78 | AH40: =AF40/(K62+K71) -> 0.4366442 | AL40: =K97-AF40 -> 8152.22
A41: SAPR4 | B41: 600 | C41: 500 | E41: =C41-B41 -> -100 | F41: =B41/C41 -> 1.2 | G41: 5.88 | H41: =G41*B41 -> 3528 | T41: NOVEMBRO | U41: 0 | V41: =586+1042+1597 -> 3225 | W41: =1110.06+503.6+519.5+515.83+597.6+539.94+504.75 -> 4291.28 | X41: =495.01+505.52 -> 1000.53 | Y41: 530.62 | AF41: =SUM(U41:AB41) -> 9047.43 | AH41: =AF41/(L62+L71) -> 0.54189467 | AL41: =L97-AF41 -> 6898.99
A42: SDIL11 | B42: 105 | C42: 500 | E42: =C42-B42 -> 395 | F42: =B42/C42 -> 0.21 | G42: 93.6 | H42: =G42*B42 -> 9828 | T42: DEZEMBRO | U42: 0 | V42: =694+1062+710 -> 2466 | W42: =911.7+481.75+493.92 -> 1887.37 | X42: =994.03+498.24 -> 1492.27 | Y42: =530.62+520.2 -> 1050.82 | AF42: =SUM(U42:AB42) -> 6896.46 | AH42: =AF42/(M62+M71) -> 0.41557207 | AL42: =M97-AF42 -> 11563.7
A43: SPTW11 | B43: 100 | C43: 500 | E43: =C43-B43 -> 400 | F43: =B43/C43 -> 0.2 | G43: 67.95 | H43: =G43*B43 -> 6795 | T43: TOTAIS | U43: =SUM(U31:U42) -> 10000 | V43: =SUM(V31:V42) -> 25247.6 | W43: =SUM(W31:W42) -> 56314.27 | X43: =SUM(X31:X42) -> 9975.58 | Y43: =SUM(Y31:Y42) -> 5070.78 | AF43: =SUM(AF31:AF42) -> 106608.23 | AH43: =AF43/(N71+N84) -> 0.57350287 | AJ43: =AVERAGE(AF31:AF42) -> 8884.0192 | AL43: =N97-AF43 -> 102291.12
A44: TAEE11 | B44: 625 | C44: 1000 | E44: =C44-B44 -> 375 | F44: =B44/C44 -> 0.625 | G44: 28.47 | H44: =G44*B44 -> 17793.75
A45: TIET11 | B45: 500 | C45: 2000 | E45: =C45-B45 -> 1500 | F45: =B45/C45 -> 0.25 | G45: 14.3 | H45: =G45*B45 -> 7150
A46: RECR11 | B46: 148 | C46: 500 | E46: =C46-B46 -> 352 | F46: =B46/C46 -> 0.296 | G46: 99.96 | H46: =G46*B46 -> 14794.08 | T46: RESUMO MENSAL DOS INVESTIMENTOS EM 2019 | AL46: DESPESAS
A47: VGIR11 | B47: 115 | C47: 500 | E47: =C47-B47 -> 385 | F47: =B47/C47 -> 0.23 | G47: 88.22 | H47: =G47*B47 -> 10145.3 | T47: MÊS | U47: RDB | V47: AÇÕES | W47: FI - FUND IMOB | X47: TESOURO | Y47: SERGUS | Z47: FUNDO ALASKA | AB47: OURO | AC47: OURO (gramas) | AD47: Criptomoedas U$ | AE47: Forex | AF47: TOTAL
A48: VINO11 | B48: 90 | C48: 500 | E48: =C48-B48 -> 410 | F48: =B48/C48 -> 0.18 | G48: 60.2 | H48: =G48*B48 -> 5418 | T48: JANEIRO | U48: 2000 | V48: =730+690+1178 -> 2598 | W48: =435+453.75+869.7+576+368.4+276.15+509.8+1084.4+436.5+540.6+1061+1017.5+1065+1069.9+1050.5+596.5+797 -> 12207.7 | X48: =466.86+597.21 -> 1064.07 | Y48: =530.62+447.57 -> 978.19 | Z48: 2000 | AF48: =SUM(U48:AB48) -> 20847.96 | AL48: =B119-AF48 -> -1322.5
A49: VISC11 | B49: 153 | C49: 200 | E49: =C49-B49 -> 47 | F49: =B49/C49 -> 0.765 | G49: 117.22 | H49: =G49*B49 -> 17934.66 | T49: FEVEREIRO | U49: 2000 | V49: =343.98+760 -> 1103.98 | W49: =547.5+1057.53+534.5+482.55+528.5+746.5+298.9+449.55+502.45+472+504.35+1167+1074.2+1062.2 -> 9427.73 | X49: =599.72 -> 599.72 | Y49: =530.62 -> 530.62 | Z49: 0 | AF49: =SUM(U49:AB49) -> 13662.05 | AL49: =C119-AF49 -> 7148.31
A50: WIZS3 | B50: 200 | C50: 1000 | E50: =C50-B50 -> 800 | F50: =B50/C50 -> 0.2 | G50: 10.46 | H50: =G50*B50 -> 2092 | T50: MARÇO | U50: 2000 | V50: =1128 -> 1128 | W50: =932+1073+442.5+641.2+564.5+1034+1079.9+1088+914.7+1019.7 -> 8789.5 | X50: 0 | Y50: =530.62 -> 530.62 | Z50: 0 | AF50: =SUM(U50:AB50) -> 12448.12 | AL50: =D119-AF50 -> 8143.99
A51: XPLG11 | B51: 153 | C51: 500 | E51: =C51-B51 -> 347 | F51: =B51/C51 -> 0.306 | G51: 135.5 | H51: =G51*B51 -> 20731.5 | T51: ABRIL | U51: 0 | V51: =1015 -> 1015 | W51: =537+672.24+838.8+770.4+1106+1010+490.5+540.3+826.65+927.5 -> 7719.39 | X51: 394.61 | Y51: 530.62 | Z51: 0 | AF51: =SUM(U51:AB51) -> 9659.62 | AL51: =E119-AF51 -> 7553.59
A52: XPML11 | B52: 77 | C52: 500 | E52: =C52-B52 -> 423 | F52: =B52/C52 -> 0.154 | G52: 105.02 | H52: =G52*B52 -> 8086.54 | T52: MAIO | U52: 0 | V52: 0 | W52: =514.35+170.8+919.4+1065.9+1441.95+457+807.6+918.9+924.75+929+726.88 -> 8876.53 | X52: 0 | Y52: 530.62 | Z52: 0 | AF52: =SUM(U52:AB52) -> 9407.15 | AL52: =F119-AF52 -> 6303.56
A53: TOTAL | B53: =SUM(B14:B52) -> 20955 | C53: =SUM(C14:C52) -> 48150 | E53: =SUM(E14:E52) -> 27195 | H53: =SUM(H14:H52) -> 407156.06 | T53: JUNHO | U53: 0 | V53: 0 | W53: =719.1+867+506.75+651+506.9+469.45+514.8+577.5+625.35+931.05 -> 6368.9 | X53: 0 | Y53: 530.62 | Z53: 0 | AF53: =SUM(U53:AB53) -> 6899.52 | AL53: =G119-AF53 -> 8386.53
T54: JULHO | U54: 3000 | V54: 0 | W54: =656.94+642.4+944+655.8+634.9+781.6+648+549.5+515+542.5+525.05 -> 7095.69 | X54: 0 | Y54: 978.19 | Z54: 0 | AF54: =SUM(U54:AB54) -> 11073.88 | AL54: =H119-AF54 -> 9964.64
T55: AGOSTO | U55: 2000 | V55: =580+568 -> 1148 | W55: =586+530+522.5+550+755.3+2020 -> 4963.8 | X55: 0 | Y55: 530.62 | Z55: 0 | AF55: =SUM(U55:AB55) -> 8642.42 | AL55: =I119-AF55 -> 9036.09
T56: SETEMBRO | U56: 5000 | V56: =1186 -> 1186 | W56: =543.5+826.8+764.4+871.2+1026.8+475+436.56+440.45+1010 -> 6394.71 | X56: 0 | Y56: 553.49 | Z56: 0 | AF56: =SUM(U56:AB56) -> 13134.2 | AL56: =J119-AF56 -> 9060.56
A57: ANO 2017 | T57: OUTUBRO | U57: 0 | V57: =679.2+285+1196+1370 -> 3530.2 | W57: =882.5+1700+650.2+1028.5+769.5+773.1+770.1+771+650.3+1120+1025.5+1096.8+682.4+789.6+1185.36+1028.4 -> 14923.26 | X57: 0 | Y57: 553.49 | Z57: 0 | AF57: =SUM(U57:AB57) -> 19006.95 | AL57: =K119-AF57 -> 5754.22
A58: RENDA ATIVA | B58: JANEIRO | C58: FEVEREIRO | D58: MARÇO | E58: ABRIL | F58: MAIO | G58: JUNHO | H58: JULHO | I58: AGOSTO | J58: SETEMBRO | K58: OUTUBRO | L58: NOVEMBRO | M58: DEZEMBRO | N58: TOTAIS | P58: MÉDIA | T58: NOVEMBRO | U58: =1000+2000 -> 3000 | V58: 0 | W58: =548.4+1038.5+696+1029.8+1063.5+955+957+3179.88 -> 9468.08 | X58: 0 | Y58: 556.59 | Z58: 0 | AF58: =SUM(U58:AB58) -> 13024.67 | AL58: =L119-AF58 -> 3142.36
A59: Banese | B59: 7305.24 | C59: =3638.48+5110.4 -> 8748.88 | D59: =2563.79+3443.97 -> 6007.76 | E59: 3671.1 | F59: =3671+5250 -> 8921 | G59: 2770 | H59: 6464.13 | I59: =2773.77+3022.46 -> 5796.23 | J59: =2831.32+1678.18 -> 4509.5 | K59: 3767.14 | L59: =3761+2335.76 -> 6096.76 | M59: 3761 | N59: =SUM(B59:M59) -> 67818.74 | P59: =AVERAGE(B59:M59) -> 5651.5617 | T59: DEZEMBRO | U59: =2000+3000 -> 5000 | V59: 0 | W59: =800+534+1053+971 -> 3358 | X59: 0 | Y59: =545.89+556.59 -> 1102.48 | Z59: 0 | AE59: 100 | AF59: =SUM(U59:AB59) -> 9460.48 | AL59: =M119-AF59 -> 14084.07
A60: FGTS | B60: 0 | C60: 0 | D60: 0 | E60: 0 | F60: 0 | G60: 546 | H60: 410.2 | I60: =565.21+820.41 -> 1385.62 | J60: 410.2 | K60: 421.48 | L60: 421.48 | M60: 712.16 | N60: =SUM(B60:M60) -> 4307.14 | P60: =AVERAGE(B60:M60) -> 358.92833 | T60: TOTAIS | U60: =SUM(U48:U59) -> 24000 | V60: =SUM(V48:V59) -> 11709.18 | W60: =SUM(W48:W59) -> 99593.29 | X60: =SUM(X48:X59) -> 2058.4 | Y60: =SUM(Y48:Y59) -> 7906.15 | Z60: =SUM(Z48:Z59) -> 2000 | AF60: =SUM(AF48:AF59) -> 147267.02 | AJ60: =AVERAGE(AF48:AF59) -> 12272.252 | AL60: =N119-AF60 -> 87255.42
A61: Escola | B61: 2959.85 | C61: 2959.85 | D61: 2841.08 | E61: 2959.85 | F61: 2959 | G61: 3919.47 | H61: 2959 | I61: 2959.85 | J61: 2959.85 | K61: 5451.3 | L61: 2959.85 | M61: 3459.58 | N61: =SUM(B61:M61) -> 39348.53 | P61: =AVERAGE(B61:M61) -> 3279.0442
A62: TOTAL | B62: =SUM(B59:B61) -> 10265.09 | C62: =SUM(C59:C61) -> 11708.73 | D62: =SUM(D59:D61) -> 8848.84 | E62: =SUM(E59:E61) -> 6630.95 | F62: =SUM(F59:F61) -> 11880 | G62: =SUM(G59:G61) -> 7235.47 | H62: =SUM(H59:H61) -> 9833.33 | I62: =SUM(I59:I61) -> 10141.7 | ... N62: =SUM(N59:N61) -> 111474.41 | P62: =AVERAGE(B62:M62) -> 9289.5342
T63: RESUMO MENSAL DOS INVESTIMENTOS EM 2020 | AL63: DESPESAS
A64: RENDA PASSIVA | B64: JANEIRO | C64: FEVEREIRO | D64: MARÇO | E64: ABRIL | F64: MAIO | G64: JUNHO | H64: JULHO | I64: AGOSTO | J64: SETEMBRO | K64: OUTUBRO | L64: NOVEMBRO | M64: DEZEMBRO | N64: TOTAIS | P64: MÉDIA | T64: MÊS | U64: RDB | V64: AÇÕES | W64: FI - FUND IMOB | X64: TESOURO | Y64: SERGUS | Z64: FUNDO ALASKA | AA64: PASSFOLIO | AB64: OURO | AC64: OURO (gramas) | AD64: Criptomoedas U$ | AE64: Forex | AF64: TOTAL
A65: RDB BANESE | B65: 139.73 | C65: 118.74 | D65: 72.08 | E65: 0 | F65: 303.17 | G65: 130.91 | H65: 216 | I65: 203.3 | J65: 177.2 | K65: 188.55 | L65: 163.74 | M65: 141.45 | N65: =SUM(B65:M65) -> 1854.87 | P65: =AVERAGE(B65:M65) -> 154.5725 | T65: JANEIRO | U65: =1000+2000 -> 3000 | V65: =910+1035.12+1053.5+1043+1343 -> 5384.62 | W65: =743.6+668.3+658.5 -> 2070.4 | X65: 0 | Y65: =556.59+469.47 -> 1026.06 | Z65: 0 | AE65: 100 | AF65: =SUM(U65:AA65) -> 11481.08 | AL65: =B143-AF65 -> 8248.09
A66: TESOURO DIRETO | B66: 0 | C66: 161.59 | D66: 0 | E66: 0 | F66: 0 | G66: 0 | H66: 0 | I66: 288.45 | J66: 0 | K66: 0 | L66: 0 | M66: 0 | N66: =SUM(B66:M66) -> 450.04 | P66: =AVERAGE(B66:M66) -> 37.503333 | T66: FEVEREIRO | U66: 1000 | V66: =898.5+872.5 -> 1771 | W66: =1072+1370.85+523.5+531.6+691+662.5+526.45+1100+669+869.8+516.3+785.1 -> 9318.1 | X66: 0 | Y66: 556.59 | Z66: 0 | AF66: =SUM(U66:AA66) -> 12645.69 | AL66: =C143-AF66 -> 10606.98
A67: FUNDO IMOB | B67: 0 | C67: 0 | D67: 0 | E67: 0 | F67: 0 | G67: 0 | H67: 0 | I67: 46.5 | J67: 75 | K67: 101.47 | L67: 126.22 | M67: 168.12 | N67: =SUM(B67:M67) -> 517.31 | P67: =AVERAGE(B67:M67) -> 43.109167 | T67: MARÇO | U67: 2000 | V67: =893+806.4+819+653.4+955+1193 -> 5319.8 | W67: =488.25+131.28+963.6+996+757.7+436.05+619.9+314.65+695.2+520+689 -> 6611.63 | X67: =502.71+699.42+992.92+401.8 -> 2596.85 | Y67: 556.59 | Z67: 0 | AF67: =SUM(U67:AA67) -> 17084.87 | AL67: =D143-AF67 -> 3593.39
A68: DIVIDENDOS | B68: 16.5 | C68: 51.16 | D68: 371.64 | E68: 162.38 | F68: 611.75 | G68: 305.7 | H68: 27.33 | I68: =734.61-288.45-46.5 -> 399.66 | J68: 6.48 | K68: =246.09-101.47 -> 144.62 | L68: =351.09-126.22 -> 224.87 | M68: 428.79 | N68: =SUM(B68:M68) -> 2750.88 | P68: =AVERAGE(B68:M68) -> 229.24 | T68: ABRIL | U68: 2000 | V68: =843.54 -> 843.54 | W68: =722.4+791.5+926.8+524.4+1002 -> 3967.1 | X68: =990.9 -> 990.9 | Y68: 556.59 | Z68: 0 | AF68: =SUM(U68:AA68) -> 8358.13 | AL68: =E143-AF68 -> 6505.65
A69: ALUGUEIS | B69: 3400 | C69: 2900 | D69: 4130 | E69: 3730 | F69: 4120 | G69: 2940 | H69: 3680 | I69: 3150 | J69: 3280 | K69: 4130 | L69: =3180+460 -> 3640 | M69: 3820 | N69: =SUM(B69:M69) -> 42920 | P69: =AVERAGE(B69:M69) -> 3576.6667 | T69: MAIO | U69: 2000 | V69: 886 | W69: =999+908.8+899.6+951 -> 3758.4 | X69: =587.85+567.43 -> 1155.28 | Y69: 556.59 | Z69: 0 | AF69: =SUM(U69:AA69) -> 8356.27 | AL69: =F143-AF69 -> 8898.54
A70: INSS | B70: 0 | C70: 0 | D70: 0 | E70: 0 | F70: 0 | G70: 2690 | H70: 3063 | I70: 3063 | J70: 4124 | K70: 3063 | L70: 3063 | M70: 4104 | N70: =SUM(B70:M70) -> 23170 | P70: =AVERAGE(B70:M70) -> 1930.8333 | T70: JUNHO | U70: 1000 | V70: =1395+879.3 -> 2274.3 | W70: =492.3+898.2+531+498.7 -> 2420.2 | X70: =502.96 -> 502.96 | Y70: 556.59 | Z70: 0 | AA70: =550+550 -> 1100 | AF70: =SUM(U70:AA70) -> 7854.05 | AL70: =G143-AF70 -> 8733.81
A71: TOTAL | B71: =SUM(B65:B70) -> 3556.23 | C71: =SUM(C65:C70) -> 3231.49 | D71: =SUM(D65:D70) -> 4573.72 | E71: =SUM(E65:E70) -> 3892.38 | F71: =SUM(F65:F70) -> 5034.92 | G71: =SUM(G65:G70) -> 6066.61 | H71: =SUM(H65:H70) -> 6986.33 | I71: =SUM(I65:I70) -> 7150.91 | ... N71: =SUM(N65:N70) -> 71663.1 | P71: =AVERAGE(B71:M71) -> 5971.925 | T71: JULHO | U71: 1000 | V71: =1363.25+1069 -> 2432.25 | W71: =351.75+507.1+350.35+621.39+699.9+865.5+929 -> 4324.99 | X71: 0 | Y71: =556.59+469.47 -> 1026.06 | Z71: 0 | AA71: =550+550+550+550 -> 2200 | AF71: =SUM(U71:AA71) -> 10983.3 | AL71: =H143-AF71 -> 8847.07
T72: AGOSTO | U72: 0 | V72: =1235.7 -> 1235.7 | W72: =980+1028+1039+434.4 -> 3481.4 | X72: 0 | Y72: 556.59 | Z72: 0 | AA72: =550+550 -> 1100 | AF72: =SUM(U72:AA72) -> 6373.69 | AL72: =I143-AF72 -> 10448.28
A73: Escola+Renda | B73: =B61+B71 -> 6516.08 | C73: =C61+C71 -> 6191.34 | D73: =D61+D71 -> 7414.8 | E73: =E61+E71 -> 6852.23 | F73: =F61+F71 -> 7993.92 | G73: =G61+G71 -> 9986.08 | H73: =H61+H71 -> 9945.33 | I73: =I61+I71 -> 10110.76 | ... M73: =M61+M71 -> 12121.94 | N73: =SUM(B73:M73) -> 111011.63 | P73: =AVERAGE(B73:M73) -> 9250.9692 | T73: SETEMBRO | U73: =1000+1000 -> 2000 | V73: =1030.4+623.7+137.1+886 -> 2677.2 | W73: =715+730.4+680.08+732.8+1018+805.1 -> 4681.38 | X73: =500.24+592.76 -> 1093 | Y73: 556.59 | Z73: 0 | AA73: =550+550+550+650+650+650 -> 3600 | AF73: =SUM(U73:AA73) -> 14608.17 | AL73: =J143-AF73 -> 6460.82
A74: Banese+Renda | B74: =B59+B60+B71 -> 10861.47 | C74: =C59+C60+C71 -> 11980.37 | D74: =D59+D60+D71 -> 10581.48 | E74: =E59+E60+E71 -> 7563.48 | F74: =F59+F60+F71 -> 13955.92 | G74: =G59+G60+G71 -> 9382.61 | H74: =H59+H60+H71 -> 13860.66 | I74: =I59+I60+I71 -> 14332.76 | ... M74: =M59+M60+M71 -> 13135.52 | N74: =SUM(B74:M74) -> 143788.98 | P74: =AVERAGE(B74:M74) -> 11982.415 | T74: OUTUBRO | U74: 1000 | V74: =1200 -> 1200 | W74: =599.2+1800+721.9 -> 3121.1 | X74: =585.28+583.24 -> 1168.52 | Y74: 556.59 | Z74: 0 | AA74: 0 | AF74: =SUM(U74:AA74) -> 7046.21 | AL74: =K143-AF74 -> 10085.93
A75: Banese+Escola+R | B75: =B62+B71 -> 13821.32 | C75: =C62+C71 -> 14940.22 | D75: =D62+D71 -> 13422.56 | E75: =E62+E71 -> 10523.33 | F75: =F62+F71 -> 16914.92 | G75: =G62+G71 -> 13302.08 | H75: =H62+H71 -> 16819.66 | I75: =I62+I71 -> 17292.61 | ... M75: =M62+M71 -> 16595.1 | N75: =SUM(B75:M75) -> 183137.51 | P75: =AVERAGE(B75:M75) -> 15261.459 | T75: NOVEMBRO | U75: 0 | V75: 0 | W75: =845.9+599.4+1001.5+1006+1030 -> 4482.8 | X75: 0 | Y75: 556.59 | Z75: 0 | AA75: 550 | AF75: =SUM(U75:AA75) -> 5589.39 | AL75: =L143-AF75 -> 10338.62
A76: Rend investimen | B76: =SUM(B65:B68) -> 156.23 | C76: =SUM(C65:C68) -> 331.49 | D76: =SUM(D65:D68) -> 443.72 | E76: =SUM(E65:E68) -> 162.38 | F76: =SUM(F65:F68) -> 914.92 | G76: =SUM(G65:G68) -> 436.61 | H76: =SUM(H65:H68) -> 243.33 | I76: =SUM(I65:I68) -> 937.91 | ... N76: =SUM(N65:N68) -> 5573.1 | P76: =AVERAGE(B76:M76) -> 464.425 | T76: DEZEMBRO | U76: 1000 | V76: =1070+1251.6 -> 2321.6 | W76: =777+628.5+921.6+802+594.6+816+807 -> 5346.7 | X76: 0 | Y76: 568.13 | Z76: 0 | AA76: =550+550+550+550+550 -> 2750 | AF76: =SUM(U76:AA76) -> 11986.43 | AL76: =M143-AF76 -> 9282.35
T77: TOTAIS | U77: =SUM(U65:U76) -> 16000 | V77: =SUM(V65:V76) -> 26346.01 | W77: =SUM(W65:W76) -> 53584.2 | X77: =SUM(X65:X76) -> 7507.51 | Y77: =SUM(Y65:Y76) -> 7629.56 | Z77: =SUM(Z65:Z76) -> 0 | AA77: =SUM(AA65:AA76) -> 11300 | AF77: =SUM(AF65:AF76) -> 122367.28 | AJ77: =AVERAGE(AF65:AF76) -> 10197.273 | AL77: =N143-AF77 -> 102049.53
A79: ANO 2018
A80: RENDA ATIVA | B80: JANEIRO | C80: FEVEREIRO | D80: MARÇO | E80: ABRIL | F80: MAIO | G80: JUNHO | H80: JULHO | I80: AGOSTO | J80: SETEMBRO | K80: OUTUBRO | L80: NOVEMBRO | M80: DEZEMBRO | N80: TOTAIS | P80: MÉDIA | T80: RESUMO MENSAL DOS INVESTIMENTOS EM 2021
A81: Banese | B81: 7574.7 | C81: =3761+7161.67 -> 10922.67 | D81: =3761+2649.24 -> 6410.24 | E81: =3761 -> 3761 | F81: =3374.08+5436.9 -> 8810.98 | G81: 2137.77 | H81: 5666.73 | I81: =1686.69+2137.76 -> 3824.45 | J81: =1983.74+3453.81 -> 5437.55 | K81: 3537.26 | L81: 3516.47 | M81: =2106.98+3516.47 -> 5623.45 | N81: =SUM(B81:M81) -> 67223.27 | P81: =AVERAGE(B81:M81) -> 5601.9392 | T81: MÊS | U81: RDB | V81: AÇÕES | W81: FI - FUND IMOB | X81: TESOURO | Y81: SERGUS | Z81: FUNDO ALASKA | AA81: PASSFOLIO | AB81: OURO | AC81: OURO (gramas) | AD81: Criptomoedas U$ | AE81: Forex | AF81: TOTAL
A82: FGTS | B82: 423.87 | C82: 847.75 | D82: 423.87 | E82: 635.81 | F82: 423.87 | G82: 565.17 | H82: 423.87 | I82: 847.75 | J82: 423.87 | K82: 445.06 | L82: 445.06 | M82: 447.57 | N82: =SUM(B82:M82) -> 6353.52 | P82: =AVERAGE(B82:M82) -> 529.46 | T82: JANEIRO | U82: 0 | V82: =1575.75+1565.62 -> 3141.37 | W82: =1034.9 -> 1034.9 | X82: 0 | Y82: =Y76 -> 568.13 | Z82: 0 | AA82: 550 | AF82: =SUM(U82:AA82) -> 5294.4
A83: Escola | B83: 2959.85 | C83: 3381.08 | D83: =3073.43 -> 3073.43 | E83: =93.36+3137.5 -> 3230.86 | F83: =93.36+4143.5 -> 4236.86 | G83: 3138.43 | H83: 3138.43 | I83: =380.58+3137.5 -> 3518.08 | J83: =3141.3 -> 3141.3 | K83: 3660.19 | L83: =380.58+3227.38 -> 3607.96 | M83: 3563.26 | N83: =SUM(B83:M83) -> 40649.73 | P83: =AVERAGE(B83:M83) -> 3387.4775 | T83: FEVEREIRO | U83: 0 | V83: =247.48+1329.5+1477+1441+2821 -> 7315.98 | W83: =631.5+799+1034.9+858+804.5+1028+788 -> 5943.9 | X83: 0 | Y83: 0 | Z83: 0 | AA83: =550+550+550 -> 1650 | AF83: =SUM(U83:AA83) -> 14909.88
A84: TOTAL | B84: =SUM(B81:B83) -> 10958.42 | C84: =SUM(C81:C83) -> 15151.5 | D84: =SUM(D81:D83) -> 9907.54 | E84: =SUM(E81:E83) -> 7627.67 | F84: =SUM(F81:F83) -> 13471.71 | G84: =SUM(G81:G83) -> 5841.37 | H84: =SUM(H81:H83) -> 9229.03 | I84: =SUM(I81:I83) -> 8190.28 | ... N84: =SUM(N81:N83) -> 114226.52 | P84: =AVERAGE(B84:M84) -> 9518.8767 | T84: MARÇO | U84: 0 | V84: =2526+1828.2+950+1197+910 -> 7411.2 | W84: =592.8+906.2+608.3+2030 -> 4137.3 | X84: =1090.85+538.37 -> 1629.22 | Y84: 0 | Z84: 0 | AA84: 550 | AF84: =SUM(U84:AA84) -> 13727.72
T85: ABRIL | V85: =945 -> 945 | W85: =584.5+858.2 -> 1442.7 | X85: =636.41 -> 636.41 | Y85: 0 | Z85: 0 | AF85: =SUM(U85:AA85) -> 3024.11
A86: RENDA PASSIVA | B86: JANEIRO | C86: FEVEREIRO | D86: MARÇO | E86: ABRIL | F86: MAIO | G86: JUNHO | H86: JULHO | I86: AGOSTO | J86: SETEMBRO | K86: OUTUBRO | L86: NOVEMBRO | M86: DEZEMBRO | N86: TOTAIS | P86: MÉDIA | T86: MAIO | AF86: =SUM(U86:AA86) -> 0
A87: RDB BANESE | B87: 159.54 | C87: 102.05 | D87: 67.77 | E87: 66.2 | F87: 83.56 | G87: 106.4 | H87: 115.86 | I87: 129.11 | J87: 109.05 | K87: 127.08 | L87: 116.16 | M87: 25.82 | N87: =SUM(B87:M87) -> 1208.6 | P87: =AVERAGE(B87:M87) -> 100.71667 | T87: JUNHO | AF87: =SUM(U87:AA87) -> 0
A88: TESOURO DIRETO | B88: 0 | C88: 354.23 | D88: 0 | E88: 0 | F88: 0 | G88: 0 | H88: 0 | I88: 397.23 | J88: 0 | K88: 0 | L88: 0 | M88: 0 | N88: =SUM(B88:M88) -> 751.46 | P88: =AVERAGE(B88:M88) -> 62.621667 | T88: JULHO | AF88: =SUM(U88:AA88) -> 0
A89: FUNDO IMOB | B89: =24.4+183.18 -> 207.58 | C89: =185.62+24.4 -> 210.02 | D89: =253.25+2.41 -> 255.66 | E89: 299.73 | F89: 307.13 | G89: 368.37 | H89: 399.14 | I89: 451.86 | J89: 498.75 | K89: 536.8 | L89: 584.17 | M89: 643.83 | N89: =SUM(B89:M89) -> 4763.04 | P89: =AVERAGE(B89:M89) -> 396.92 | T89: AGOSTO | AF89: =SUM(U89:AA89) -> 0
A90: DIVIDENDOS | B90: 0 | C90: 243.02 | D90: =1175.42+6.95 -> 1182.37 | E90: 374.07 | F90: 938.24 | G90: 105.29 | H90: 34.12 | I90: 1085.92 | J90: 7.26 | K90: 35.61 | L90: 906.6 | M90: 316.23 | N90: =SUM(B90:M90) -> 5228.73 | P90: =AVERAGE(B90:M90) -> 435.7275 | T90: SETEMBRO | AF90: =SUM(U90:AA90) -> 0
A91: ALUGUEIS | B91: 3760 | C91: 2500 | D91: 3180 | E91: 3780 | F91: =2480+500+400+400 -> 3780 | G91: 4660 | H91: =400+400+400+400+500+480 -> 2580 | I91: =400+400+1200+400+500+450 -> 3350 | J91: =400+1200+480+400+400+500+400 -> 3780 | K91: =480+400+1200+400+400+500+400+480 -> 4260 | L91: =400+400+1200+500+310+300+90+480 -> 3680 | M91: =400+1200+400+330+70+500+380 -> 3280 | N91: =SUM(B91:M91) -> 42590 | P91: =AVERAGE(B91:M91) -> 3549.1667 | T91: OUTUBRO | AF91: =SUM(U91:AA91) -> 0
A92: INSS | B92: 3063 | C92: 3090 | D92: 3090 | E92: 3090 | F92: 3090 | G92: 3090 | H92: 3090 | I92: 3090 | J92: 4698 | K92: 3090 | L92: 3090 | M92: 4560 | N92: =SUM(B92:M92) -> 40131 | P92: =AVERAGE(B92:M92) -> 3344.25 | T92: NOVEMBRO | AF92: =SUM(U92:AA92) -> 0
A93: TOTAL | B93: =SUM(B87:B92) -> 7190.12 | C93: =SUM(C87:C92) -> 6499.32 | D93: =SUM(D87:D92) -> 7775.8 | E93: =SUM(E87:E92) -> 7610 | F93: =SUM(F87:F92) -> 8198.93 | G93: =SUM(G87:G92) -> 8330.06 | H93: =SUM(H87:H92) -> 6219.12 | I93: =SUM(I87:I92) -> 8504.12 | ... N93: =SUM(N87:N92) -> 94672.83 | P93: =AVERAGE(B93:M93) -> 7889.4025 | T93: DEZEMBRO | AF93: =SUM(U93:AA93) -> 0
T94: TOTAIS | U94: =SUM(U82:U93) -> 0 | V94: =SUM(V82:V93) -> 18813.55 | W94: =SUM(W82:W93) -> 12558.8 | X94: =SUM(X82:X93) -> 2265.63 | Y94: =SUM(Y82:Y93) -> 568.13 | Z94: =SUM(Z82:Z93) -> 0 | AA94: =SUM(AA82:AA93) -> 2750 | AF94: =SUM(AF82:AF93) -> 36956.11 | AJ94: =AVERAGE(AF82:AF93) -> 3079.6758
A95: Escola+Renda | B95: =B83+B93 -> 10149.97 | C95: =C83+C93 -> 9880.4 | D95: =D83+D93 -> 10849.23 | E95: =E83+E93 -> 10840.86 | F95: =F83+F93 -> 12435.79 | G95: =G83+G93 -> 11468.49 | H95: =H83+H93 -> 9357.55 | I95: =I83+I93 -> 12022.2 | ... M95: =M83+M93 -> 12389.14 | N95: =SUM(B95:M95) -> 135322.56 | P95: =AVERAGE(B95:M95) -> 11276.88
A96: Banese+Renda | B96: =B81+B82+B93 -> 15188.69 | C96: =C81+C82+C93 -> 18269.74 | D96: =D81+D82+D93 -> 14609.91 | E96: =E81+E82+E93 -> 12006.81 | F96: =F81+F82+F93 -> 17433.78 | G96: =G81+G82+G93 -> 11033 | H96: =H81+H82+H93 -> 12309.72 | I96: =I81+I82+I93 -> 13176.32 | ... M96: =M81+M82+M93 -> 14896.9 | N96: =SUM(B96:M96) -> 168249.62 | P96: =AVERAGE(B96:M96) -> 14020.802
A97: Banese+Escola+R | B97: =B84+B93 -> 18148.54 | C97: =C84+C93 -> 21650.82 | D97: =D84+D93 -> 17683.34 | E97: =E84+E93 -> 15237.67 | F97: =F84+F93 -> 21670.64 | G97: =G84+G93 -> 14171.43 | H97: =H84+H93 -> 15448.15 | I97: =I84+I93 -> 16694.4 | ... M97: =M84+M93 -> 18460.16 | N97: =SUM(B97:M97) -> 208899.35 | P97: =AVERAGE(B97:M97) -> 17408.279
A98: Rend investimen | B98: =SUM(B87:B90) -> 367.12 | C98: =SUM(C87:C90) -> 909.32 | D98: =SUM(D87:D90) -> 1505.8 | E98: =SUM(E87:E90) -> 740 | F98: =SUM(F87:F90) -> 1328.93 | G98: =SUM(G87:G90) -> 580.06 | H98: =SUM(H87:H90) -> 549.12 | I98: =SUM(I87:I90) -> 2064.12 | ... N98: =SUM(N87:N90) -> 11951.83 | P98: =AVERAGE(B98:M98) -> 995.98583 | T98: INVESTIDO | U98: =U9+U26+U43+U60+U77 -> 71000 | V98: =V9+V26+V43+V60+V77+V94 -> 156680.34 | W98: =W9+W26+W43+W60+W77+W94 -> 249917.56 | X98: =X9+X26+X43+X60+X77+X94 -> 33556.3 | Y98: =Y9+Y26+Y43+Y60+Y77+Y94 -> 21174.62 | Z98: =Z9+Z26+Z43+Z60+Z77+Z94 -> 2000 | AA98: =AA9+AA26+AA43+AA60+AA77+AA94 -> 14050
T99: PROVENTOS | V99: =N68+N90+N112+N136+N160 -> 23357.79 | W99: =N67+N89+N111+N135+N159 -> 39720.29 | X99: =N66+N88+N110+N134+N158 -> 5272.36
T100: PROVENTOS | V100: =V99/V98 -> 0.14907927 | W100: =W99/W98 -> 0.15893357 | X100: =X99/X98 -> 0.15711983
A101: ANO 2019
A102: RENDA ATIVA | B102: JANEIRO | C102: FEVEREIRO | D102: MARÇO | E102: ABRIL | F102: MAIO | G102: JUNHO | H102: JULHO | I102: AGOSTO | J102: SETEMBRO | K102: OUTUBRO | L102: NOVEMBRO | M102: DEZEMBRO | N102: TOTAIS | P102: MÉDIA
...

Sheet Passfolio
A1: CODIGO | B1: QTD | C1: OBJETIVO | D1: COMPANHIA | E1: DESCRICAO | F1: DY (%) | G1: Rendimentos | H1: Periodicidade | J1: Tot Rend | L1: Objetivo
A2: WSR | B2: 60.96 | C2: 300 | D2: Whitestone REIT | E2: Centros comerciais e residenciais e escritorios | F2: 4.83 | G2: 0.035 | H2: Mensal | J2: =B2*G2 -> 2.1336 | L2: =C2*G2 -> 10.5
A3: APLE | B3: 10.14 | C3: 100 | D3: Apple Hospitality REIT | E3: Hoteis e Moteis | F3: 1.42 | G3: 0 | J3: =B3*G3 -> 0 | L3: =C3*G3 -> 0
A4: NNN | B4: 5.53 | C4: 100 | D4: National Retail Properties | E4: Lojas comerciais | F4: 4.89 | G4: 0.52 | H4: Trimestral | I4: Fev-Mai-Ago-Nov | J4: =B4*G4 -> 2.8756 | L4: =C4*G4 -> 52
A5: GEO | B5: 30.03 | C5: 300 | D5: The GEO Group | E5: Servicos de reabilitacao (saude) | F5: 12.99 | G5: 0.34 | H5: Trimestral | I5: Fev-Abr-Jul-Out | J5: =B5*G5 -> 10.2102 | L5: =C5*G5 -> 102
A6: AGNC | B6: 15.11 | C6: 300 | D6: AGNC Investiment | E6: Financiamento imobiliario | F6: 8.93 | G6: 0.12 | H6: Mensal | J6: =B6*G6 -> 1.8132 | L6: =C6*G6 -> 36
A7: O | B7: 14.12 | C7: 100 | D7: O Realty Income Corp | E7: Varejo | F7: 4.57 | G7: 0.23 | H7: Mensal | J7: =B7*G7 -> 3.2476 | L7: =C7*G7 -> 23
A8: SRET | B8: 57.37 | C8: 100 | D8: Global X SuperDividend | E8: ETF de REITs | F8: 6.89 | G8: 0.055 | H8: Mensal | J8: =B8*G8 -> 3.15535 | L8: =C8*G8 -> 5.5
I9: TOTAL | J9: =SUM(J2:J8) -> 23.43555 | L9: =SUM(L2:L8) -> 229
I10: TOTAL MENSAL | J10: =J2+J6+J7+J8 -> 10.34975 | L10: =L2+L6+L7+L8 -> 75
A15: DIVIDENDOS
A16: CODIGO | B16: DATA | C16: VALOR | D16: IMPOSTO | E16: LIQUIDO
A17: WSR | B17: 44025 | C17: 0.52 | D17: 0.16 | E17: =C17-D17 -> 0.36
A18: AGNC | B18: 44055 | C18: 0.91 | D18: 0.27 | E18: =C18-D18 -> 0.64
A19: WSR | B19: 44057 | C19: 1.08 | D19: 0.32 | E19: =C19-D19 -> 0.76
A20: NNN | B20: 44060 | C20: 1.43 | D20: 0.43 | E20: =C20-D20 -> 1
A21: WSR | B21: 44085 | C21: 1.65 | D21: 0.5 | E21: =C21-D21 -> 1.15
A22: AGNC | B22: 44085 | C22: 1.78 | D22: 0.53 | E22: =C22-D22 -> 1.25
A23: AGNC | B23: 44116 | C23: 1.79 | D23: 0.54 | E23: =C23-D23 -> 1.25
A24: WSR | B24: 44120 | C24: 1.66 | D24: 0.5 | E24: =C24-D24 -> 1.16
A25: O | B25: 44120 | C25: 1.69 | D25: 0.51 | E25: =C25-D25 -> 1.18
A26: GEO | B26: 44130 | C26: 6.19 | D26: 1.86 | E26: =C26-D26 -> 4.33
A27: WSR | B27: 44148 | C27: 1.66 | D27: =C27*0.3 -> 0.498 | E27: =C27-D27 -> 1.162
A28: AGNC | B28: 44146 | C28: 1.8 | D28: 0.54 | E28: =C28-D28 -> 1.26
A29: O | B29: 44151 | C29: 1.7 | D29: =C29*0.3 -> 0.51 | E29: =C29-D29 -> 1.19
A30: NNN | B30: 44152 | C30: 2.85 | D30: =C30*0.3 -> 0.855 | E30: =C30-D30 -> 1.995
A31: AGNC | B31: 44175 | C31: 1.81 | D31: 0.54 | E31: =C31-D31 -> 1.27
A32: AGNC | B32: 44209 | C32: 1.81 | D32: 0.5 | E32: =C32-D32 -> 1.31
A33: WSR | B33: 44176 | C33: 1.67 | D33: 0.5 | E33: =C33-D33 -> 1.17
A34: WSR | B34: 44211 | C34: 2.13 | D34: =C34*0.3 -> 0.639 | E34: =C34-D34 -> 1.491
A35: O | B35: 44181 | C35: 2.09 | D35: =C35*0.3 -> 0.627 | E35: =C35-D35 -> 1.463
A36: O | B36: 44215 | C36: 3.31 | D36: =C36*0.3 -> 0.993 | E36: =C36-D36 -> 2.317
A37: GEO | B37: 44229 | C37: 7.51 | D37: =C37*0.3 -> 2.253 | E37: =C37-D37 -> 5.257
A38: AGNC | B38: 44237 | C38: 1.81 | D38: =C38*0.3 -> 0.543 | E38: =C38-D38 -> 1.267
A39: SRET | B39: 44239 | C39: 1.83 | D39: =C39*0.3 -> 0.549 | E39: =C39-D39 -> 1.281
A40: WSR | B40: 44239 | C40: 2.13 | D40: =C40*0.3 -> 0.639 | E40: =C40-D40 -> 1.491
A41: NNN | B41: 44244 | C41: 3.31 | D41: =C41*0.3 -> 0.993 | E41: =C41-D41 -> 2.317
A42: O | B42: 44244 | C42: 3.31 | D42: =C42*0.3 -> 0.993 | E42: =C42-D42 -> 2.317
A43: AGNC | B43: 44265 | C43: 1.81 | D43: =C43*0.3 -> 0.543 | E43: =C43-D43 -> 1.267
A44: SRET | B44: 44267 | C44: 2.87 | D44: =C44*0.3 -> 0.861 | E44: =C44-D44 -> 2.009
A45: WSR | B45: 44267 | C45: 2.18 | D45: =C45*0.3 -> 0.654 | E45: =C45-D45 -> 1.526
A46: NNN
A47: O
A53: TOTAL | C53: =SUM(C17:C52) -> 66.29 | D53: =SUM(D17:D52) -> 19.85 | E53: =SUM(E17:E52) -> 46.44
A59: XT
A60: NOBL
A61: VNQ
A62: GOOD | D62: Gladstone Commercial | E62: Propriedades diversificadas (lojas, galpoes) | F62: 8.19 | G62: 0.12 | H62: Mensal
A63: SRET

Sheet Despesas
A1: DESPESAS FIXAS
A2: DIA VENCTO | B2: CONTA | C2: DESCRICAO | D2: MAIO | E2: JUNHO | F2: JULHO | G2: AGOSTO | H2: SETEMBRO | I2: DEZEMBRO | J2: JANEIRO | K2: FEVEREIRO
A3: 3 | B3: TELEFONE | C3: Conta de telefone OI Total | D3: 259.81 | E3: 259.81 | F3: 259.81 | G3: 265.85 | H3: 277.35 | I3: 278 | J3: 278
A4: 5 | B4: CONDOMINIO | C4: Taxa do Condominio Morada do Rio | D4: 402.4 | E4: 402.4 | F4: 402.4 | G4: 402.4 | H4: 402.4 | I4: 402.4 | J4: 402.4 | K4: 402.4
A5: 6 | B5: LUZ | C5: Conta da Energisa - Condominio | D5: 87 | E5: 87 | F5: 82.68 | G5: 80.19 | H5: 90.62 | I5: 93.44 | J5: 94.83
A6: 5 | B6: INTERNET | C6: Masternet | D6: 99.9 | E6: 99.9 | F6: 99.9 | G6: 99.9 | H6: 99.9 | I6: 99.9 | J6: 99.9 | K6: 99.9
A7: 10 | B7: EDUCACAO | C7: PUC Minas EAD | D7: 290 | E7: 0 | F7: 0 | G7: 0 | H7: 0 | I7: 0 | J7: 0
A8: 18 | B8: SILNA | C8: Fatura do Cartao Mastercard | D8: 206.39 | E8: 0 | F8: 91.8 | G8: 91.8 | J8: 296.86
A9: 18 | B9: SILNA | C9: Fatura do Cartao Nubank | D9: 63.52 | E9: 0 | F9: 69.87 | G9: 402.87 | J9: 430.84
A10: 20 | B10: SILNA | C10: Psicologa | D10: 0 | E10: 360 | F10: 450 | G10: 450 | H10: 360 | I10: 360 | J10: 0
A11: 20 | B11: BANESE CARD | C11: Fatura do Cartao Banesecard | D11: 152.45 | E11: 152.45 | F11: 152.45 | G11: 161.16 | I11: 132.11 | J11: 132.11
A12: 25 | B12: NUBANK | C12: Fatura do Cartao Nubank | D12: 1084.15 | E12: 1542.18 | F12: 1343.63 | G12: 1672.64 | I12: 2885.8 | J12: 2077.92
A13: 27 | B13: LUZ | C13: Conta da Energisa - Casa | D13: 166.72 | E13: 136.6 | F13: 122.37 | G13: 130.94 | I13: 114.64
A14: 27 | B14: AGUA | C14: Conta da Deso - Condominio | D14: 37.98 | E14: 37.74 | F14: 38.49 | I14: 37.74 | J14: 71.5
A15: 30 | B15: ILNA | C15: Fatura do Cartao | E15: =222+126.96 -> 348.96 | F15: =210+120 -> 330 | G15: 0 | H15: 0 | I15: 0 | J15: 0
A16: 31 | B16: DARF | C16: Imposto de Renda | E16: 1595 | F16: 1603 | G16: 1605.65 | H16: 1608.19 | I16: 1613.26 | J16: 1618.18
C18: TOTAL | D18: =SUM(D3:D16) -> 2850.32 | E18: =SUM(E3:E16) -> 5022.04 | F18: =SUM(F3:F16) -> 5046.4 | G18: =SUM(G3:G16) -> 5363.4 | H18: =SUM(H3:H16) -> 2838.46 | I18: =SUM(I3:I16) -> 6017.29 | J18: =SUM(J3:J16) -> 5502.54

Sheet Forex
A3: DATA | B3: SALDO ANT | C3: LUCRO | D3: SALDO ATUAL | E3: P/L | F3: GIRO | G3: LUCRO | R3: DEPOSITOS | S3: VALOR | V3: RETIRADAS | W3: VALOR
A4: 42551 | B4: =B5-C4 -> 1347.29 | C4: 23.53 | D4: =B4+C4 -> 1370.82 | E4: =D4/B4-1 -> 0.017464688 | R4: 42549 | S4: 200 | T4: Credicard | V4: 42911 | W4: 78.09 | X4: Transferencia
A5: 42582 | B5: =B6-C5 -> 1370.82 | C5: -81.35 | D5: =B5+C5 -> 1289.47 | E5: =D5/B5-1 -> -0.059344042 | R5: 42673 | S5: =125+78.09 -> 203.09 | T5: Transferencia | V5: 42912 | W5: 200 | X5: Transferencia
A6: 42613 | B6: =B7-C6 -> 1289.47 | C6: 2.03 | D6: =B6+C6 -> 1291.5 | E6: =D6/B6-1 -> 0.0015742902 | R6: 42696 | S6: 300 | T6: Credicard | V6: 42930 | W6: 100 | X6: Neteller
A7: 42643 | B7: =B8-C7 -> 1291.5 | C7: 17.46 | D7: =B7+C7 -> 1308.96 | E7: =D7/B7-1 -> 0.013519164 | R7: 42697 | S7: 100 | T7: Boleto | V7: 43050 | W7: 1047.4 | X7: Transferencia
A8: 42674 | B8: =B9-C8 -> 1308.96 | C8: -37.07 | D8: =B8+C8 -> 1271.89 | E8: =D8/B8-1 -> -0.028320193 | R8: 42760 | S8: 300 | T8: Credicard | V8: 43139 | W8: 50 | X8: Banco
A9: 42704 | B9: =B10-C9 -> 1271.89 | C9: -20.43 | D9: =B9+C9 -> 1251.46 | E9: =D9/B9-1 -> -0.01606271 | R9: 42912 | S9: 100 | T9: Neteller | V9: 43157 | W9: 100 | X9: Banco
A10: 42735 | B10: =B11-C10 -> 1251.46 | C10: 33.24 | D10: =B10+C10 -> 1284.7 | E10: =D10/B10-1 -> 0.026560977 | H10: =D10/B4-1 -> -0.04645622 | I10: Em 2016 | R10: 43050 | S10: 1047.4 | T10: Transferencia | V10: 43732 | W10: 50 | X10: Bitcoin
A11: 42766 | B11: =B12-C11 -> 1284.7 | C11: 11.6 | D11: =B11+C11 -> 1296.3 | E11: =D11/B11-1 -> 0.0090293454 | R11: 43182 | S11: =3.81+76.19 -> 80 | T11: Neteller | V11: 43917 | W11: 100 | X11: Bitcoin
A12: 42794 | B12: =B13-C12 -> 1296.3 | C12: 99.29 | D12: =B12+C12 -> 1395.59 | E12: =D12/B12-1 -> 0.076594924 | R12: 43476 | S12: =14.71+1.29 -> 16 | T12: Neteller | V12: 43956 | W12: 200 | X12: Bitcoin | Y12: 1BTC = 8666
A13: 42825 | B13: =B14-C13 -> 1395.59 | C13: 31.4 | D13: =B13+C13 -> 1426.99 | E13: =D13/B13-1 -> 0.022499445 | R13: 43503 | S13: =34.65+0.35 -> 35 | T13: Bitcoin | V13: 43962 | W13: 168 | X13: Bitcoin | Y13: 1BTC = 8600
A14: 42855 | B14: =B15-C14 -> 1426.99 | C14: 88.82 | D14: =B14+C14 -> 1515.81 | E14: =D14/B14-1 -> 0.062242903 | R14: 43524 | S14: 100 | T14: Bitcoin | V14: 43980 | W14: 100 | X14: Banco
A15: 42886 | B15: =B16-C15 -> 1515.81 | C15: -18.68 | D15: =B15+C15 -> 1497.13 | E15: =D15/B15-1 -> -0.012323444 | R15: 43524 | S15: =3.83+379.17 -> 383 | T15: Bitcoin | V15: 44005 | W15: 100 | X15: Banco
A16: 42916 | B16: =B17-C16 -> 1497.13 | C16: -18.78 | D16: =B16+C16 -> 1478.35 | E16: =D16/B16-1 -> -0.012544001 | R16: 43792 | S16: 100 | T16: Boleto | V16: 44099 | W16: 100 | X16: Banco
A17: 42947 | B17: =B18-C17 -> 1478.35 | C17: 82.23 | D17: =B17+C17 -> 1560.58 | E17: =D17/B17-1 -> 0.055622823 | R17: 43823 | S17: 100 | T17: Boleto | V17: 44138 | W17: 100 | X17: Banco
A18: 42978 | B18: =B19-C18 -> 1560.58 | C18: -54.05 | D18: =B18+C18 -> 1506.53 | E18: =D18/B18-1 -> -0.034634559 | R18: 43833 | S18: 100 | T18: Boleto | V18: 44154 | W18: 100 | X18: Banco
A19: 43008 | B19: =B20-C19 -> 1506.53 | C19: 24.99 | D19: =B19+C19 -> 1531.52 | E19: =D19/B19-1 -> 0.016587788 | R19: 43867 | S19: 100 | T19: Boleto
A20: 43039 | B20: =B21-C20 -> 1531.52 | C20: 27.44 | D20: =B20+C20 -> 1558.96 | E20: =D20/B20-1 -> 0.017916841 | R20: 43897 | S20: 100 | T20: Boleto
A21: 43069 | B21: =B22-C21 -> 1558.96 | C21: 9.44 | D21: =B21+C21 -> 1568.4 | E21: =D21/B21-1 -> 0.0060553189
A22: 43100 | B22: =B23-C22 -> 1568.4 | C22: 36.53 | D22: =B22+C22 -> 1604.93 | E22: =D22/B22-1 -> 0.023291252 | H22: =D22/B11-1 -> 0.24926442 | I22: Em 2017
A23: 43131 | B23: =B24-C23 -> 1604.93 | C23: -137.33 | D23: =B23+C23 -> 1467.6 | E23: =D23/B23-1 -> -0.085567595
A24: 43159 | B24: =B25-C24 -> 1467.6 | C24: 90.65 | D24: =B24+C24 -> 1558.25 | E24: =D24/B24-1 -> 0.061767512 | R24: TOTAL | S24: =SUM(S4:S21) -> 3364.49 | V24: TOTAL | W24: =SUM(W4:W20) -> 2593.49
A25: 43190 | B25: =B26-C25 -> 1558.25 | C25: 128.38 | D25: =B25+C25 -> 1686.63 | E25: =D25/B25-1 -> 0.082387293 | R25: SALDO | S25: =S24-W24 -> 771
A26: 43220 | B26: =B27-C26 -> 1686.63 | C26: 40.25 | D26: =B26+C26 -> 1726.88 | E26: =D26/B26-1 -> 0.023864155 | R26: SALDO FLUTANTE | S26: 1573.41
A27: 43251 | B27: =B28-C27 -> 1726.88 | C27: 3.57 | D27: =B27+C27 -> 1730.45 | E27: =D27/B27-1 -> 0.0020673121 | R27: P/L | S27: =S26-S25 -> 802.41 | V27: SAQ BANCO | W27: =W8+W9+W14+W15+W16+W17+W18 -> 650
A28: 43281 | B28: =B29-C28 -> 1730.45 | C28: -257.08 | D28: =B28+C28 -> 1473.37 | E28: =D28/B28-1 -> -0.14856251 | R28: DEP BITCOIN | S28: =S13+S14+S15 -> 518 | V28: SAQ BITCOIN | W28: =W10+W11+W12+W13 -> 518
A29: 43312 | B29: =B30-C29 -> 1473.37 | C29: 50.65 | D29: =B29+C29 -> 1524.02 | E29: =D29/B29-1 -> 0.034376973
A30: 43343 | B30: =B31-C30 -> 1524.02 | C30: -355.55 | D30: =B30+C30 -> 1168.47 | E30: =D30/B30-1 -> -0.23329746
A31: 43373 | B31: =B32-C31 -> 1168.47 | C31: 50.58 | D31: =B31+C31 -> 1219.05 | E31: =D31/B31-1 -> 0.043287376
A32: 43404 | B32: =B33-C32 -> 1219.05 | C32: 47.51 | D32: =B32+C32 -> 1266.56 | E32: =D32/B32-1 -> 0.038972971
A33: 43434 | B33: =B34-C33 -> 1266.56 | C33: -45.16 | D33: =B33+C33 -> 1221.4 | E33: =D33/B33-1 -> -0.035655634
A34: 43465 | B34: =B35-C34 -> 1221.4 | C34: 60.82 | D34: =B34+C34 -> 1282.22 | E34: =D34/B34-1 -> 0.049795317 | H34: =D34/B23-1 -> -0.20107419 | I34: Em 2018
A35: 43496 | B35: =B36-C35 -> 1282.22 | C35: -284.69 | D35: =B35+C35 -> 997.53 | E35: =D35/B35-1 -> -0.22202898 | N35: MÊS/ANO | P35: LUCRO | R35: LUCRO PERCENT
A36: 43524 | B36: =B37-C36 -> 997.53 | C36: 23.5 | D36: =B36+C36 -> 1021.03 | E36: =D36/B36-1 -> 0.023558189
A37: 43555 | B37: =B38-C37 -> 1021.03 | C37: 35.95 | D37: =B37+C37 -> 1056.98 | E37: =D37/B37-1 -> 0.035209543
A38: 43585 | B38: =B39-C38 -> 1056.98 | C38: 42.65 | D38: =B38+C38 -> 1099.63 | E38: =D38/B38-1 -> 0.040350811
A39: 43616 | B39: =B40-C39 -> 1099.63 | C39: 4.64 | D39: =B39+C39 -> 1104.27 | E39: =D39/B39-1 -> 0.0042196011
A40: 43646 | B40: =B41-C40 -> 1104.27 | C40: 55.21 | D40: =B40+C40 -> 1159.48 | E40: =D40/B40-1 -> 0.04999683
A41: 43677 | B41: =B42-C41 -> 1159.48 | C41: 13.13 | D41: =B41+C41 -> 1172.61 | E41: =D41/B41-1 -> 0.011324042
A42: 43708 | B42: =B43-C42 -> 1172.61 | C42: 5.81 | D42: =B42+C42 -> 1178.42 | E42: =D42/B42-1 -> 0.004954759
A43: 43738 | B43: =B44-C43 -> 1178.42 | C43: 47.42 | D43: =B43+C43 -> 1225.84 | E43: =D43/B43-1 -> 0.040240322
A44: 43769 | B44: =B45-C44 -> 1225.84 | C44: 33.81 | D44: =B44+C44 -> 1259.65 | E44: =D44/B44-1 -> 0.027581087
A45: 43799 | B45: =B46-C45 -> 1259.65 | C45: 32.55 | D45: =B45+C45 -> 1292.2 | E45: =D45/B45-1 -> 0.025840511
A46: 43830 | B46: =1342.57-C46 -> 1292.2 | C46: 50.37 | D46: =B46+C46 -> 1342.57 | E46: =D46/B46-1 -> 0.038980034 | H46: =D46/B35-1 -> 0.047066806 | I46: Em 2019
A47: 43861 | B47: =D46 -> 1342.57 | C47: 33.78 | D47: =B47+C47 -> 1376.35 | E47: =D47/B47-1 -> 0.025160699
A48: 43889 | B48: =D47 -> 1376.35 | C48: 33.36 | D48: =B48+C48 -> 1409.71 | E48: =D48/B48-1 -> 0.024238021
A49: 43921 | B49: =D48 -> 1409.71 | C49: 100.87 | D49: =B49+C49 -> 1510.58 | E49: =D49/B49-1 -> 0.071553724
A50: 43951 | B50: =D49 -> 1510.58 | C50: 35.08 | D50: =B50+C50 -> 1545.66 | E50: =D50/B50-1 -> 0.023222868
A51: 43982 | B51: =D50 -> 1545.66 | C51: 52.39 | D51: =B51+C51 -> 1598.05 | E51: =D51/B51-1 -> 0.033894906
A52: 44012 | B52: =D51 -> 1598.05 | C52: 89.39 | D52: =B52+C52 -> 1687.44 | E52: =D52/B52-1 -> 0.055936923
A53: 44043 | B53: =D52 -> 1687.44 | C53: 101.19 | D53: =B53+C53 -> 1788.63 | E53: =D53/B53-1 -> 0.059966577
A54: 44074 | B54: =D53 -> 1788.63 | C54: 109.67 | D54: =B54+C54 -> 1898.3 | E54: =D54/B54-1 -> 0.061315085
A55: 44104 | B55: =D54 -> 1898.3 | C55: 84.78 | D55: =B55+C55 -> 1983.08 | E55: =D55/B55-1 -> 0.044661012
A56: 44135 | B56: =D55 -> 1983.08 | C56: 48.67 | D56: =B56+C56 -> 2031.75 | E56: =D56/B56-1 -> 0.024542631
A57: 44165 | B57: =D56 -> 2031.75 | C57: 142.13 | D57: =B57+C57 -> 2173.88 | E57: =D57/B57-1 -> 0.069954473
A58: 44195 | B58: =D57 -> 2173.88 | C58: 112.69 | D58: =B58+C58 -> 2286.57 | E58: =D58/B58-1 -> 0.051838188 | H58: =D58/$B$47-1 -> 0.70312907 | I58: Em 2020
A59: 44227 | B59: =D58 -> 2286.57 | C59: 98.31 | D59: =B59+C59 -> 2384.88 | E59: =D59/B59-1 -> 0.042994529 | F59: =1077.31+98.31 -> 1175.62 | G59: =C59/F59 -> 0.08362396
A60: 44255 | B60: =D59 -> 2384.88 | C60: 50.1 | D60: =B60+C60 -> 2434.98 | E60: =D60/B60-1 -> 0.021007346
A75: MERCADO DE FOREX - 2019 (valores em dólares)
A76: MESES | B76: SALDO ANT | C76: LUCRO | D76: SALDO ATUAL | E76: PERCENT
A77: 43889 | B77: 997.53 | C77: 23.5 | D77: 1021.03 | E77: 0.023558189
A78: 43921 | B78: 1021.03 | C78: 35.95 | D78: 1056.98 | E78: 0.035209543
A79: 43951 | B79: 1056.98 | C79: 42.65 | D79: 1099.63 | E79: 0.040350811
A80: 43982 | B80: 1099.63 | C80: 4.64 | D80: 1104.27 | E80: 0.0042196011
A81: 44012 | B81: 1104.27 | C81: 55.21 | D81: 1159.48 | E81: 0.04999683
A82: 44043 | B82: 1159.48 | C82: 13.13 | D82: 1172.61 | E82: 0.011324042
A83: 44074 | B83: 1172.61 | C83: 5.81 | D83: 1178.42 | E83: 0.004954759
A84: 44104 | B84: 1178.42 | C84: 47.42 | D84: 1225.84 | E84: 0.040240322
A85: 44135 | B85: 1225.84 | C85: 33.81 | D85: 1259.65 | E85: 0.027581087
A86: 44165 | B86: 1259.65 | C86: 32.55 | D86: 1292.2 | E86: 0.025840511
A87: dez | B87: 1292.2 | C87: 50.37 | D87: 1342.57 | E87: 0.038980034
D88: LUCRO ANUAL | E88: =D87/B77-1 -> 0.34589436
A91: MERCADO DE FOREX - 2020 (valores em dólares)
A92: MESES | B92: SALDO ANT | C92: LUCRO | D92: SALDO ATUAL | E92: PERCENT
A93: 43861 | B93: 1342.57 | C93: 33.78 | D93: 1376.35 | E93: 0.025160699
A94: 43889 | B94: 1376.35 | C94: 33.36 | D94: 1409.71 | E94: 0.024238021
A95: 43921 | B95: 1409.71 | C95: 100.87 | D95: 1510.58 | E95: 0.071553724
A96: 43951 | B96: 1510.58 | C96: 35.08 | D96: 1545.66 | E96: 0.023222868
A97: 43982 | B97: 1545.66 | C97: 52.39 | D97: 1598.05 | E97: 0.033894906
A98: 44012 | B98: 1598.05 | C98: 89.39 | D98: 1687.44 | E98: 0.055936923
A99: 44043 | B99: 1687.44 | C99: 101.19 | D99: 1788.63 | E99: 0.059966577
A100: 44074 | B100: 1788.63 | C100: 109.67 | D100: 1898.3 | E100: 0.061315085
A101: 44104 | B101: 1898.3 | C101: 84.78 | D101: 1983.08 | E101: 0.044661012
A102: 44135 | B102: 1983.08 | C102: 48.67 | D102: 2031.75 | E102: 0.024542631
A103: 44165 | B103: 2031.75 | C103: 142.13 | D103: 2173.88 | E103: 0.069954473
A104: dez | B104: 2173.88 | C104: 112.69 | D104: 2286.57 | E104: 0.051838188
D105: LUCRO ANUAL | E105: 0.7031

Sheet Rentabilidade
A1: RENTABILIDADE
B2: 2017 | P2: 2018 | AE2: 2019
A3: ACOES | B3: Janeiro | C3: Fevereiro | D3: Marco | E3: Abril | F3: Maio | G3: Junho | H3: Julho | I3: Agosto | J3: Setembro | K3: Outubro | L3: Novembro | M3: Dezembro | N3: TOTAL | P3: Janeiro | Q3: Fevereiro | R3: Marco | S3: Abril | T3: Maio | U3: Junho | V3: Julho | W3: Agosto | X3: Setembro | Y3: Outubro | Z3: Novembro | AA3: Dezembro | AC3: TOTAL | AE3: Janeiro | AF3: Fevereiro | AG3: Marco | AH3: Abril | AI3: Maio | AJ3: Junho | AK3: Julho | AL3: Agosto | AM3: Setembro | AN3: Outubro | AP3: TOTAL
A4: Investido | B4: 43027 | C4: 49011 | D4: 52397 | E4: 53716 | F4: 57121 | G4: 60851 | H4: 62216 | I4: 62216 | J4: 64546 | K4: 66934 | L4: 70561 | M4: 74564 | N4: =M4 -> 74564 | P4: 76596 | Q4: 77674 | R4: 81231.6 | S4: 81582 | T4: 83328.6 | U4: 86131.16 | V4: 87449.3 | W4: 88897.1 | X4: 91787.1 | Y4: 94120.6 | Z4: =Y4+3255 -> 97375.6 | AA4: =Z4+2466 -> 99841.6 | AC4: =AA4 -> 99841.6 | AE4: =AA4+2598 -> 102439.6 | AF4: =AE4+1103.98 -> 103543.58 | AG4: =AF4+1128 -> 104671.58 | AH4: =AG4+1015 -> 105686.58 | AI4: =AH4 -> 105686.58 | AP4: =AI4 -> 105686.58
A5: Retorno | B5: 16.5 | C5: 51.16 | D5: 371.64 | E5: 162.38 | F5: 611.75 | G5: 305.7 | H5: 27.33 | I5: 446.16 | J5: 6.48 | K5: 144.62 | L5: 205.89 | M5: 428.79 | N5: =SUM(B5:M5) -> 2778.4 | P5: 0 | Q5: 243.02 | R5: =1175.42+6.95 -> 1182.37 | S5: 374.07 | T5: 938.24 | U5: 98.72 | V5: 34.12 | W5: 1085.92 | X5: 7.26 | Y5: 35.61 | Z5: 906.6 | AA5: 316.23 | AC5: =SUM(P5:AA5) -> 5222.16 | AE5: 153.8 | AF5: 517.17 | AG5: 2045.37 | AH5: 108.9 | AI5: 426.7 | AP5: =SUM(AE5:AN5) -> 3251.94 | AR5: =N5+AC5+AP5 -> 11252.5
A6: Percentual | B6: =B5/B4 -> 0.00038348014 | C6: =C5/C4 -> 0.0010438473 | D6: =D5/D4 -> 0.0070927725 | E6: =E5/E4 -> 0.0030229354 | F6: =F5/F4 -> 0.010709721 | G6: =G5/G4 -> 0.0050237465 | H6: =H5/H4 -> 0.00043927607 | I6: =I5/I4 -> 0.0071711457 | ... N6: =N5/N4 -> 0.037261949 | P6: =P5/P4 -> 0 | Q6: =Q5/Q4 -> 0.0031287175 | R6: =R5/R4 -> 0.014555542 | S6: =S5/S4 -> 0.0045852026 | T6: =T5/T4 -> 0.01125952 | U6: =U5/U4 -> 0.001146159 | V6: =V5/V4 -> 0.00039016893 | W6: =W5/W4 -> 0.012215472 | ... AA6: =AA5/AA4 -> 0.003167317 | AC6: =AC5/AC4 -> 0.05230445 | AE6: =AE5/AE4 -> 0.0015013725 | AF6: =AF5/AF4 -> 0.0049947085 | AG6: =AG5/AG4 -> 0.019540834 | AH6: =AH5/AH4 -> 0.0010304052 | AI6: =AI5/AI4 -> 0.0040374095 | AJ6: =AJ5/AJ4 -> #DIV/0! | AK6: =AK5/AK4 -> #DIV/0! | AL6: =AL5/AL4 -> #DIV/0! | ... AN6: =AN5/AN4 -> #DIV/0! | AP6: =AP5/AP4 -> 0.030769659
A7: Valor atual | G7: 66430 | H7: 71854 | I7: 73267 | J7: 77930 | K7: 80941 | L7: 76630 | M7: 81588 | N7: =L7/L4-1 -> 0.086010686 | P7: 90275.71 | Q7: 94931.53 | R7: 95899.83 | S7: 95094.16 | T7: 85862.3 | U7: 82778.7 | V7: 93873.2 | W7: 90173 | X7: 94036.5 | Y7: 118841.71 | Z7: 131431.13 | AA7: 141015.72 | AC7: =AA7/AA4-1 -> 0.41239443 | AE7: 142214.31 | AF7: 138718.96 | AG7: 138754.57 | AP7: =AN7/AN4-1 -> #DIV/0!
A10: FIIs | B10: Janeiro | C10: Fevereiro | D10: Marco | E10: Abril | F10: Maio | G10: Junho | H10: Julho | I10: Agosto | J10: Setembro | K10: Outubro | L10: Novembro | M10: Dezembro | N10: TOTAL | P10: Janeiro | Q10: Fevereiro | R10: Marco | S10: Abril | T10: Maio | U10: Junho | V10: Julho | W10: Agosto | X10: Setembro | Y10: Outubro | Z10: Novembro | AA10: Dezembro | AC10: TOTAL | AE10: Janeiro | AF10: Fevereiro | AG10: Marco | AH10: Abril | AI10: Maio | AJ10: Junho | AK10: Julho | AL10: Agosto | AM10: Setembro | AN10: Outubro | AP10: TOTAL
A11: Investido | B11: 0 | C11: 0 | D11: 0 | E11: 0 | F11: 0 | G11: 0 | H11: 4330 | I11: 10390 | J11: 14240 | K11: 17984 | L11: 23506 | M11: 27867 | N11: =M11 -> 27867 | P11: 31450.5 | Q11: 38907.15 | R11: 46960.79 | S11: 49528.39 | T11: 54970.59 | U11: 56681.11 | V11: 64275.31 | W11: 67238.41 | X11: 73822.11 | Y11: 78002.62 | Z11: =Y11+4291.28 -> 82293.9 | AA11: =Z11+1887.37 -> 84181.27 | AC11: =AA11 -> 84181.27 | AE11: =AA11+12207.7 -> 96388.97 | AF11: =AE11+9427.73 -> 105816.7 | AG11: =AF11+8789.5 -> 114606.2 | AH11: =AG11+7719.39 -> 122325.59 | AI11: =AH11+7220.65 -> 129546.24 | AP11: =AI11 -> 129546.24
A12: Retorno | B12: 0 | C12: 0 | D12: 0 | E12: 0 | F12: 0 | G12: 0 | H12: 0 | I12: 46.5 | J12: 75 | K12: 101.47 | L12: 126.22 | M12: 168.12 | N12: =SUM(B12:M12) -> 517.31 | P12: =24.4+183.18 -> 207.58 | Q12: =185.62+24.4 -> 210.02 | R12: =253.25+2.41 -> 255.66 | S12: 299.73 | T12: 307.13 | U12: 368.37 | V12: 399.14 | W12: 451.86 | X12: 498.75 | Y12: 536.8 | Z12: 584.17 | AA12: 643.83 | AC12: =SUM(P12:AA12) -> 4763.04 | AE12: 684.7 | AF12: 735.65 | AG12: 746.13 | AH12: 858.78 | AI12: 842.72 | AP12: =SUM(AE12:AN12) -> 3867.98 | AR12: =N12+AC12+AP12 -> 9148.33
A13: Percentual | H13: =H12/H11 -> 0 | I13: =I12/I11 -> 0.0044754572 | J13: =J12/J11 -> 0.0052668539 | K13: =K12/K11 -> 0.0056422375 | L13: =L12/L11 -> 0.0053696928 | M13: =M12/M11 -> 0.0060329422 | N13: =N12/N11 -> 0.018563534 | P13: =P12/P11 -> 0.006600213 | Q13: =Q12/Q11 -> 0.0053979795 | R13: =R12/R11 -> 0.0054441163 | S13: =S12/S11 -> 0.0060516807 | T13: =T12/T11 -> 0.0055871694 | U13: =U12/U11 -> 0.0064989906 | V13: =V12/V11 -> 0.0062098495 | W13: =W12/W11 -> 0.006720266 | ... AA13: =AA12/AA11 -> 0.0076481384 | AC13: =AC12/AC11 -> 0.056580757 | AE13: =AE12/AE11 -> 0.0071035099 | AF13: =AF12/AF11 -> 0.0069521163 | AG13: =AG12/AG11 -> 0.0065103808 | AH13: =AH12/AH11 -> 0.0070204444 | AI13: =AI12/AI11 -> 0.0065051676 | AJ13: =AJ12/AJ11 -> #DIV/0! | AK13: =AK12/AK11 -> #DIV/0! | AL13: =AL12/AL11 -> #DIV/0! | ... AN13: =AN12/AN11 -> #DIV/0! | AP13: =AP12/AP11 -> 0.02985791
A14: Valor atual | H14: 4330 | I14: 10533 | J14: 14360 | K14: =16931+2274 -> 19205 | L14: 25657 | M14: 30049 | N14: =M14/M11-1 -> 0.078300499 | P14: =4491.6+29336.4 -> 33828 | Q14: 39580 | R14: =5388+1021.9+1021.9+2614.5+1224.86+41366 -> 52637.16 | S14: 56507.8 | T14: 58446.4 | U14: 59394.04 | V14: 63609.68 | W14: 68305.15 | X14: 74143.55 | Y14: 83136.32 | Z14: 88650.75 | AA14: 96410.06 | AC14: =AA14/AA11-1 -> 0.14526735 | AP14: =AN14/AN11-1 -> #DIV/0!
A17: RDB | B17: Janeiro | C17: Fevereiro | D17: Marco | E17: Abril | F17: Maio | G17: Junho | H17: Julho | I17: Agosto | J17: Setembro | K17: Outubro | L17: Novembro | M17: Dezembro | N17: TOTAL | P17: Janeiro | Q17: Fevereiro | R17: Marco | S17: Abril | T17: Maio | U17: Junho | V17: Julho | W17: Agosto | X17: Setembro | Y17: Outubro | Z17: Novembro | AA17: Dezembro | AC17: TOTAL | AE17: Janeiro | AF17: Fevereiro | AG17: Marco | AH17: Abril | AI17: Maio | AJ17: Junho | AK17: Julho | AL17: Agosto | AM17: Setembro | AN17: Outubro | AP17: TOTAL
A18: Investido | G18: 25434 | H18: 30571 | I18: 34860.66 | J18: 35037.86 | K18: 37226.55 | L18: 32350 | M18: 32492 | N18: 32492 | P18: 32658.91 | Q18: 12623.05 | R18: 12674.41 | S18: 12734.02 | T18: 18790.08 | U18: 20885.86 | V18: 21982.54 | W18: 23092.46 | X18: 23180.85 | Y18: 23290.84 | AC18: =AA18 -> 0 | AP18: =AN18 -> 0
A19: Retorno | G19: 130.91 | H19: 216 | I19: 203.3 | J19: 177.2 | K19: 188.55 | L19: 163.74 | M19: 141.45 | N19: =SUM(B19:M19) -> 1221.15 | P19: 159.54 | Q19: 92.48 | R19: 53.94 | S19: 54.56 | T19: 61.11 | U19: 95.78 | V19: 106.4 | W19: 115.86 | X19: 109.05 | Y19: 127.08 | Z19: 116.16 | AA19: 25.82 | AC19: =SUM(P19:AA19) -> 1117.78 | AP19: =SUM(AE19:AN19) -> 0
A20: Percentual | G20: =G19/G18 -> 0.0051470473 | H20: =H19/H18 -> 0.0070655196 | I20: =I19/I18 -> 0.0058317886 | J20: =J19/J18 -> 0.0050573865 | K20: =K19/K18 -> 0.0050649335 | L20: =L19/L18 -> 0.0050615147 | M20: =M19/M18 -> 0.0043533793 | N20: =N19/N18 -> 0.037583097 | P20: =P19/P18 -> 0.0048850375 | Q20: =Q19/Q18 -> 0.0073262801 | R20: =R19/R18 -> 0.0042558194 | S20: =S19/S18 -> 0.0042845857 | T20: =T19/T18 -> 0.003252248 | U20: =U19/U18 -> 0.0045858777 | V20: =V19/V18 -> 0.004840205 | W20: =W19/W18 -> 0.0050172221 | ... Y20: =Y19/Y18 -> 0.0054562223 | AC20: =AC19/AC18 -> #DIV/0! | AE20: =AE19/AE18 -> #DIV/0! | AF20: =AF19/AF18 -> #DIV/0! | AG20: =AG19/AG18 -> #DIV/0! | AH20: =AH19/AH18 -> #DIV/0! | AI20: =AI19/AI18 -> #DIV/0! | AJ20: =AJ19/AJ18 -> #DIV/0! | AK20: =AK19/AK18 -> #DIV/0! | AL20: =AL19/AL18 -> #DIV/0! | ... AN20: =AN19/AN18 -> #DIV/0! | AP20: =AP19/AP18 -> #DIV/0!
A23: TESOURO | B23: Janeiro | C23: Fevereiro | D23: Marco | E23: Abril | F23: Maio | G23: Junho | H23: Julho | I23: Agosto | J23: Setembro | K23: Outubro | L23: Novembro | M23: Dezembro | N23: TOTAL | P23: Janeiro | Q23: Fevereiro | R23: Marco | S23: Abril | T23: Maio | U23: Junho | V23: Julho | W23: Agosto | X23: Setembro | Y23: Outubro | Z23: Novembro | AA23: Dezembro | AC23: TOTAL | AE23: Janeiro | AF23: Fevereiro | AG23: Marco | AH23: Abril | AI23: Maio | AJ23: Junho | AK23: Julho | AL23: Agosto | AM23: Setembro | AN23: Outubro | AP23: TOTAL
A24: Investido | B24: 5821.92 | C24: 6979.51 | D24: 8527.11 | E24: 9003.93 | F24: 10100.35 | G24: 10575.46 | H24: 11519.75 | I24: 11519.75 | J24: 11519.75 | K24: 11519.75 | L24: 11519.75 | M24: 11749.18 | N24: =M24 -> 11749.18 | P24: 11749.18 | Q24: 12918.63 | R24: 12918.63 | S24: 12918.63 | T24: 14534.83 | U24: 14535.16 | V24: 15321.19 | W24: 16821.35 | X24: 18733.84 | Y24: 19231.96 | Z24: =Y24+1000.53 -> 20232.49 | AA24: =Z24+1492.27 -> 21724.76 | AC24: =AA24 -> 21724.76 | AE24: =AA24+1064.07 -> 22788.83 | AF24: =AE24+599.72 -> 23388.55 | AP24: =AF24 -> 23388.55
A25: Retorno | C25: 161.59 | I25: 288.45 | N25: =SUM(B25:M25) -> 450.04 | Q25: 354.23 | W25: 397.23 | AC25: =SUM(P25:AB25) -> 751.46 | AE25: 256.1 | AF25: 409.15 | AP25: =SUM(AE25:AO25) -> 665.25 | AR25: =N25+AC25+AP25 -> 1866.75
A26: Percentual | C26: =C25/C24 -> 0.023152055 | I26: =I25/I24 -> 0.025039606 | N26: =N25/N24 -> 0.03830395 | Q26: =Q25/Q24 -> 0.02742009 | W26: =W25/W24 -> 0.023614633 | AC26: =AC25/AC24 -> 0.034590025 | AE26: =AE25/AE24 -> 0.011237962 | AF26: =AF25/AF24 -> 0.017493603 | AK26: =AK25/AK24 -> #DIV/0! | AL26: =AL25/AL24 -> #DIV/0! | AP26: =AP25/AP24 -> 0.028443405
AP29: =AP4+AP11+AP24 -> 258621.37
AP30: =AR5+AR12+AR25 -> 22267.58
AP32: =AP30/AP29 -> 0.086101083
A47: Aporte | B47: 10000 | D47: Taxa | E47: 0.006
S48: ATIVO | T48: INVESTIDO | U48: COTAS | X48: DYC
A49: MÊS | B49: APORTES | C49: JUROS MENSAL | D49: JUROS TOTAL | E49: ACUMULADO | S49: BCFF11 | T49: 45535.39 | U49: 590 | W49: =U49*V49 -> 0 | X49: =W49/T49 -> 0
A50: 1 | B50: =B47 -> 10000 | C50: 0 | D50: 0 | E50: =B50+D50 -> 10000 | S50: BPFF11 | T50: 14376.77 | U50: 155 | V50: 1.5 | W50: =U50*V50 -> 232.5 | X50: =W50/T50 -> 0.016171922
A51: =A50+1 -> 2 | B51: =$B$47+B50 -> 20000 | C51: =B50*$E$47 -> 60 | D51: =C51 -> 60 | E51: =B51+D51 -> 20060 | S51: EDGA11 | T51: 4123.04 | U51: 96 | V51: 0.2 | W51: =U51*V51 -> 19.2 | X51: =W51/T51 -> 0.0046567581
A52: =A51+1 -> 3 | B52: =$B$47+B51 -> 30000 | C52: =B51*$E$47 -> 120 | D52: =D51+C52 -> 180 | E52: =B52+D52 -> 30180 | S52: FIGS11 | T52: 13048.12 | U52: 190 | V52: 1.92 | W52: =U52*V52 -> 364.8 | X52: =W52/T52 -> 0.027958051
A53: =A52+1 -> 4 | B53: =$B$47+B52 -> 40000 | C53: =B52*$E$47 -> 180 | D53: =D52+C53 -> 360 | E53: =B53+D53 -> 40360 | S53: GGRC11 | T53: 4918.8 | U53: 40 | V53: 0.66 | W53: =U53*V53 -> 26.4 | X53: =W53/T53 -> 0.0053671627
A54: =A53+1 -> 5 | B54: =$B$47+B53 -> 50000 | C54: =B53*$E$47 -> 240 | D54: =D53+C54 -> 600 | E54: =B54+D54 -> 50600 | S54: HGRU11 | T54: 3200.42 | U54: 30 | V54: 0.74 | W54: =U54*V54 -> 22.2 | X54: =W54/T54 -> 0.0069365896
A55: =A54+1 -> 6 | B55: =$B$47+B54 -> 60000 | C55: =B54*$E$47 -> 300 | D55: =D54+C55 -> 900 | E55: =B55+D55 -> 60900 | S55: HTMX11 | T55: 1495.42 | U55: 10 | V55: 0.47 | W55: =U55*V55 -> 4.7 | X55: =W55/T55 -> 0.0031429297
A56: =A55+1 -> 7 | B56: =$B$47+B55 -> 70000 | C56: =B55*$E$47 -> 360 | D56: =D55+C56 -> 1260 | E56: =B56+D56 -> 71260 | S56: MALL11 | T56: 2601.24 | U56: 25 | V56: 0.34 | W56: =U56*V56 -> 8.5 | X56: =W56/T56 -> 0.0032676723
A57: =A56+1 -> 8 | B57: =$B$47+B56 -> 80000 | C57: =B56*$E$47 -> 420 | D57: =D56+C57 -> 1680 | E57: =B57+D57 -> 81680 | S57: MXRF11 | T57: 15586.23 | U57: 1442 | V57: 0.13 | W57: =U57*V57 -> 187.46 | X57: =W57/T57 -> 0.012027283
A58: =A57+1 -> 9 | B58: =$B$47+B57 -> 90000 | C58: =B57*$E$47 -> 480 | D58: =D57+C58 -> 2160 | E58: =B58+D58 -> 92160 | S58: OUFF11 | T58: 2883.91 | U58: 30 | V58: 0.55 | W58: =U58*V58 -> 16.5 | X58: =W58/T58 -> 0.0057213991
A59: =A58+1 -> 10 | B59: =$B$47+B58 -> 100000 | C59: =B58*$E$47 -> 540 | D59: =D58+C59 -> 2700 | E59: =B59+D59 -> 102700 | S59: RBGS11 | T59: 3582.9 | U59: 75 | V59: 0.31 | W59: =U59*V59 -> 23.25 | X59: =W59/T59 -> 0.0064891568
A60: =A59+1 -> 11 | B60: =$B$47+B59 -> 110000 | C60: =B59*$E$47 -> 600 | D60: =D59+C60 -> 3300 | E60: =B60+D60 -> 113300 | S60: RBRR11 | T60: 4034.85 | U60: 40 | V60: 0.55 | W60: =U60*V60 -> 22 | X60: =W60/T60 -> 0.0054524951
A61: =A60+1 -> 12 | B61: =$B$47+B60 -> 120000 | C61: =B60*$E$47 -> 660 | D61: =D60+C61 -> 3960 | E61: =B61+D61 -> 123960 | G61: 1 ano | S61: SDIL11 | T61: 8800.75 | U61: 105 | V61: 0.57 | W61: =U61*V61 -> 59.85 | X61: =W61/T61 -> 0.0068005568
A62: =A61+1 -> 13 | B62: =$B$47+B61 -> 130000 | C62: =B61*$E$47 -> 720 | D62: =D61+C62 -> 4680 | E62: =B62+D62 -> 134680 | S62: SPTW11 | T62: 6241.73 | U62: 100 | V62: 0.73 | W62: =U62*V62 -> 73 | X62: =W62/T62 -> 0.011695475
A63: =A62+1 -> 14 | B63: =$B$47+B62 -> 140000 | C63: =B62*$E$47 -> 780 | D63: =D62+C63 -> 5460 | E63: =B63+D63 -> 145460 | S63: VGIR11 | T63: 3097.48 | U63: 95 | V63: 0.6 | W63: =U63*V63 -> 57 | X63: =W63/T63 -> 0.018402056
A64: =A63+1 -> 15 | B64: =$B$47+B63 -> 150000 | C64: =B63*$E$47 -> 840 | D64: =D63+C64 -> 6300 | E64: =B64+D64 -> 156300 | S64: VISC11 | T64: 14502.95 | U64: 145 | V64: 0.77 | W64: =U64*V64 -> 111.65 | X64: =W64/T64 -> 0.0076984338
A65: =A64+1 -> 16 | B65: =$B$47+B64 -> 160000 | C65: =B64*$E$47 -> 900 | D65: =D64+C65 -> 7200 | E65: =B65+D65 -> 167200 | S65: XPLG11 | T65: 15125.58 | U65: 153 | V65: 0.64 | W65: =U65*V65 -> 97.92 | X65: =W65/T65 -> 0.0064738013
A66: =A65+1 -> 17 | B66: =$B$47+B65 -> 170000 | C66: =B65*$E$47 -> 960 | D66: =D65+C66 -> 8160 | E66: =B66+D66 -> 178160 | S66: XPML11 | T66: 7672.01 | U66: 72 | V66: 0.59 | W66: =U66*V66 -> 42.48 | X66: =W66/T66 -> 0.0055370105
A67: =A66+1 -> 18 | B67: =$B$47+B66 -> 180000 | C67: =B66*$E$47 -> 1020 | D67: =D66+C67 -> 9180 | E67: =B67+D67 -> 189180
A68: =A67+1 -> 19 | B68: =$B$47+B67 -> 190000 | C68: =B67*$E$47 -> 1080 | D68: =D67+C68 -> 10260 | E68: =B68+D68 -> 200260 | T68: =SUM(T49:T66) -> 170827.59 | W68: =SUM(W51:W66) -> 1136.91 | X68: =W68/T68 -> 0.0066553067
A69: =A68+1 -> 20 | B69: =$B$47+B68 -> 200000 | C69: =B68*$E$47 -> 1140 | D69: =D68+C69 -> 11400 | E69: =B69+D69 -> 211400
A70: =A69+1 -> 21 | B70: =$B$47+B69 -> 210000 | C70: =B69*$E$47 -> 1200 | D70: =D69+C70 -> 12600 | E70: =B70+D70 -> 222600
A71: =A70+1 -> 22 | B71: =$B$47+B70 -> 220000 | C71: =B70*$E$47 -> 1260 | D71: =D70+C71 -> 13860 | E71: =B71+D71 -> 233860
A72: =A71+1 -> 23 | B72: =$B$47+B71 -> 230000 | C72: =B71*$E$47 -> 1320 | D72: =D71+C72 -> 15180 | E72: =B72+D72 -> 245180
A73: =A72+1 -> 24 | B73: =$B$47+B72 -> 240000 | C73: =B72*$E$47 -> 1380 | D73: =D72+C73 -> 16560 | E73: =B73+D73 -> 256560 | G73: 2 anos
A74: =A73+1 -> 25 | B74: =$B$47+B73 -> 250000 | C74: =B73*$E$47 -> 1440 | D74: =D73+C74 -> 18000 | E74: =B74+D74 -> 268000
A75: =A74+1 -> 26 | B75: =$B$47+B74 -> 260000 | C75: =B74*$E$47 -> 1500 | D75: =D74+C75 -> 19500 | E75: =B75+D75 -> 279500
A76: =A75+1 -> 27 | B76: =$B$47+B75 -> 270000 | C76: =B75*$E$47 -> 1560 | D76: =D75+C76 -> 21060 | E76: =B76+D76 -> 291060
A77: =A76+1 -> 28 | B77: =$B$47+B76 -> 280000 | C77: =B76*$E$47 -> 1620 | D77: =D76+C77 -> 22680 | E77: =B77+D77 -> 302680
A78: =A77+1 -> 29 | B78: =$B$47+B77 -> 290000 | C78: =B77*$E$47 -> 1680 | D78: =D77+C78 -> 24360 | E78: =B78+D78 -> 314360
A79: =A78+1 -> 30 | B79: =$B$47+B78 -> 300000 | C79: =B78*$E$47 -> 1740 | D79: =D78+C79 -> 26100 | E79: =B79+D79 -> 326100
A80: =A79+1 -> 31 | B80: =$B$47+B79 -> 310000 | C80: =B79*$E$47 -> 1800 | D80: =D79+C80 -> 27900 | E80: =B80+D80 -> 337900
A81: =A80+1 -> 32 | B81: =$B$47+B80 -> 320000 | C81: =B80*$E$47 -> 1860 | D81: =D80+C81 -> 29760 | E81: =B81+D81 -> 349760
A82: =A81+1 -> 33 | B82: =$B$47+B81 -> 330000 | C82: =B81*$E$47 -> 1920 | D82: =D81+C82 -> 31680 | E82: =B82+D82 -> 361680
A83: =A82+1 -> 34 | B83: =$B$47+B82 -> 340000 | C83: =B82*$E$47 -> 1980 | D83: =D82+C83 -> 33660 | E83: =B83+D83 -> 373660
A84: =A83+1 -> 35 | B84: =$B$47+B83 -> 350000 | C84: =B83*$E$47 -> 2040 | D84: =D83+C84 -> 35700 | E84: =B84+D84 -> 385700
A85: =A84+1 -> 36 | B85: =$B$47+B84 -> 360000 | C85: =B84*$E$47 -> 2100 | D85: =D84+C85 -> 37800 | E85: =B85+D85 -> 397800 | G85: 3 anos
A86: =A85+1 -> 37 | B86: =$B$47+B85 -> 370000 | C86: =B85*$E$47 -> 2160 | D86: =D85+C86 -> 39960 | E86: =B86+D86 -> 409960
A87: =A86+1 -> 38 | B87: =$B$47+B86 -> 380000 | C87: =B86*$E$47 -> 2220 | D87: =D86+C87 -> 42180 | E87: =B87+D87 -> 422180
A88: =A87+1 -> 39 | B88: =$B$47+B87 -> 390000 | C88: =B87*$E$47 -> 2280 | D88: =D87+C88 -> 44460 | E88: =B88+D88 -> 434460
A89: =A88+1 -> 40 | B89: =$B$47+B88 -> 400000 | C89: =B88*$E$47 -> 2340 | D89: =D88+C89 -> 46800 | E89: =B89+D89 -> 446800
A90: =A89+1 -> 41 | B90: =$B$47+B89 -> 410000 | C90: =B89*$E$47 -> 2400 | D90: =D89+C90 -> 49200 | E90: =B90+D90 -> 459200
A91: =A90+1 -> 42 | B91: =$B$47+B90 -> 420000 | C91: =B90*$E$47 -> 2460 | D91: =D90+C91 -> 51660 | E91: =B91+D91 -> 471660
A92: =A91+1 -> 43 | B92: =$B$47+B91 -> 430000 | C92: =B91*$E$47 -> 2520 | D92: =D91+C92 -> 54180 | E92: =B92+D92 -> 484180
A93: =A92+1 -> 44 | B93: =$B$47+B92 -> 440000 | C93: =B92*$E$47 -> 2580 | D93: =D92+C93 -> 56760 | E93: =B93+D93 -> 496760
A94: =A93+1 -> 45 | B94: =$B$47+B93 -> 450000 | C94: =B93*$E$47 -> 2640 | D94: =D93+C94 -> 59400 | E94: =B94+D94 -> 509400
A95: =A94+1 -> 46 | B95: =$B$47+B94 -> 460000 | C95: =B94*$E$47 -> 2700 | D95: =D94+C95 -> 62100 | E95: =B95+D95 -> 522100
A96: =A95+1 -> 47 | B96: =$B$47+B95 -> 470000 | C96: =B95*$E$47 -> 2760 | D96: =D95+C96 -> 64860 | E96: =B96+D96 -> 534860
A97: =A96+1 -> 48 | B97: =$B$47+B96 -> 480000 | C97: =B96*$E$47 -> 2820 | D97: =D96+C97 -> 67680 | E97: =B97+D97 -> 547680 | G97: 4 anos
A98: =A97+1 -> 49 | B98: =$B$47+B97 -> 490000 | C98: =B97*$E$47 -> 2880 | D98: =D97+C98 -> 70560 | E98: =B98+D98 -> 560560
A99: =A98+1 -> 50 | B99: =$B$47+B98 -> 500000 | C99: =B98*$E$47 -> 2940 | D99: =D98+C99 -> 73500 | E99: =B99+D99 -> 573500
A100: =A99+1 -> 51 | B100: =$B$47+B99 -> 510000 | C100: =B99*$E$47 -> 3000 | D100: =D99+C100 -> 76500 | E100: =B100+D100 -> 586500
A101: =A100+1 -> 52 | B101: =$B$47+B100 -> 520000 | C101: =B100*$E$47 -> 3060 | D101: =D100+C101 -> 79560 | E101: =B101+D101 -> 599560
A102: =A101+1 -> 53 | B102: =$B$47+B101 -> 530000 | C102: =B101*$E$47 -> 3120 | D102: =D101+C102 -> 82680 | E102: =B102+D102 -> 612680
A103: =A102+1 -> 54 | B103: =$B$47+B102 -> 540000 | C103: =B102*$E$47 -> 3180 | D103: =D102+C103 -> 85860 | E103: =B103+D103 -> 625860
A104: =A103+1 -> 55 | B104: =$B$47+B103 -> 550000 | C104: =B103*$E$47 -> 3240 | D104: =D103+C104 -> 89100 | E104: =B104+D104 -> 639100
A105: =A104+1 -> 56 | B105: =$B$47+B104 -> 560000 | C105: =B104*$E$47 -> 3300 | D105: =D104+C105 -> 92400 | E105: =B105+D105 -> 652400
A106: =A105+1 -> 57 | B106: =$B$47+B105 -> 570000 | C106: =B105*$E$47 -> 3360 | D106: =D105+C106 -> 95760 | E106: =B106+D106 -> 665760
A107: =A106+1 -> 58 | B107: =$B$47+B106 -> 580000 | C107: =B106*$E$47 -> 3420 | D107: =D106+C107 -> 99180 | E107: =B107+D107 -> 679180
A108: =A107+1 -> 59 | B108: =$B$47+B107 -> 590000 | C108: =B107*$E$47 -> 3480 | D108: =D107+C108 -> 102660 | E108: =B108+D108 -> 692660
A109: =A108+1 -> 60 | B109: =$B$47+B108 -> 600000 | C109: =B108*$E$47 -> 3540 | D109: =D108+C109 -> 106200 | E109: =B109+D109 -> 706200 | G109: 5 anos
A110: =A109+1 -> 61 | B110: =$B$47+B109 -> 610000 | C110: =B109*$E$47 -> 3600 | D110: =D109+C110 -> 109800 | E110: =B110+D110 -> 719800
A111: =A110+1 -> 62 | B111: =$B$47+B110 -> 620000 | C111: =B110*$E$47 -> 3660 | D111: =D110+C111 -> 113460 | E111: =B111+D111 -> 733460
A112: =A111+1 -> 63 | B112: =$B$47+B111 -> 630000 | C112: =B111*$E$47 -> 3720 | D112: =D111+C112 -> 117180 | E112: =B112+D112 -> 747180
A113: =A112+1 -> 64 | B113: =$B$47+B112 -> 640000 | C113: =B112*$E$47 -> 3780 | D113: =D112+C113 -> 120960 | E113: =B113+D113 -> 760960
A114: =A113+1 -> 65 | B114: =$B$47+B113 -> 650000 | C114: =B113*$E$47 -> 3840 | D114: =D113+C114 -> 124800 | E114: =B114+D114 -> 774800
A115: =A114+1 -> 66 | B115: =$B$47+B114 -> 660000 | C115: =B114*$E$47 -> 3900 | D115: =D114+C115 -> 128700 | E115: =B115+D115 -> 788700
A116: =A115+1 -> 67 | B116: =$B$47+B115 -> 670000 | C116: =B115*$E$47 -> 3960 | D116: =D115+C116 -> 132660 | E116: =B116+D116 -> 802660
A117: =A116+1 -> 68 | B117: =$B$47+B116 -> 680000 | C117: =B116*$E$47 -> 4020 | D117: =D116+C117 -> 136680 | E117: =B117+D117 -> 816680
A118: =A117+1 -> 69 | B118: =$B$47+B117 -> 690000 | C118: =B117*$E$47 -> 4080 | D118: =D117+C118 -> 140760 | E118: =B118+D118 -> 830760
A119: =A118+1 -> 70 | B119: =$B$47+B118 -> 700000 | C119: =B118*$E$47 -> 4140 | D119: =D118+C119 -> 144900 | E119: =B119+D119 -> 844900
A120: =A119+1 -> 71 | B120: =$B$47+B119 -> 710000 | C120: =B119*$E$47 -> 4200 | D120: =D119+C120 -> 149100 | E120: =B120+D120 -> 859100
A121: =A120+1 -> 72 | B121: =$B$47+B120 -> 720000 | C121: =B120*$E$47 -> 4260 | D121: =D120+C121 -> 153360 | E121: =B121+D121 -> 873360 | G121: 6 anos
A122: =A121+1 -> 73 | B122: =$B$47+B121 -> 730000 | C122: =B121*$E$47 -> 4320 | D122: =D121+C122 -> 157680 | E122: =B122+D122 -> 887680
A123: =A122+1 -> 74 | B123: =$B$47+B122 -> 740000 | C123: =B122*$E$47 -> 4380 | D123: =D122+C123 -> 162060 | E123: =B123+D123 -> 902060
...

Sheet Resumo_Geral
A1: RESUMO GERAL
A2: CORRETORA | B2: ATIVO | C2: COMPRAS | D2: VENDAS | E2: COTAS | F2: PREÇO MÉDIO | G2: PREÇO MÉDIO CORRETAGEM | H2: DIVIDENDOS | I2: JCP | J2: RENDA FI | K2: BÔNUS EM AÇÕES | M2: POSIÇÃO ATUAL
A3: XP | B3: BBAS3 | C3: =SUMIFS(XP!$D$3:$D$307,XP!$C$3:$C$307,B3,XP!$D$3:$D$307,">0",XP!$E$3:$E$307,">0") -> 649 | D3: =SUMIFS(XP!$D$3:$D$307,XP!$C$3:$C$307,B3,XP!$D$3:$D$307,"<0",XP!$E$3:$E$307,">0") -> -249 | E3: =SUMIF(XP!$C$3:C$307,B3,XP!$D$3:D$307) -> 0 | F3: =IF(C3<>0,(SUMIFS(XP!$F$3:$F$307,XP!$C$3:$C$307,$B3,XP!$F$3:$F$307,">0",XP!$F$3:$F$307,">0"))/$C3,0) -> 21.532157 | G3: =IF($C3<>0,(SUMIFS(XP!$J$3:$J$307,XP!$C$3:$C$307,$B3,XP!$J$3:$J$307,">0",XP!$J$3:$J$307,">0")+SUMIFS(MODAL!$K$2:$K$1644,MODAL!$C$2:$C$1644,$B3,MODAL!$K$2:$K$1644,">0",MODAL!$K$2:$K$1644,">0"))/$C3,0) -> 36.368521 | H3: =SUMIFS(XP!$N$3:$N$307,XP!$C$3:$C$307,$B3)+SUMIFS(MODAL!$O$2:$O$1644,MODAL!$C$2:$C$1644,$B3) -> 526.97 | I3: =SUMIFS(XP!$O$3:$O$307,XP!$C$3:$C$307,$B3)+SUMIFS(MODAL!$P$2:$P$1636,MODAL!$C$2:$C$1636,$B3) -> 955.24 | J3: =SUMIFS(XP!$M$3:$M$307,XP!$C$3:$C$307,$B3)+SUMIFS(MODAL!$N$2:$N$1644,MODAL!$C$2:$C$1644,$B3) -> 0 | M3: =(E3+K3)*L3 -> 0
A4: XP | B4: BCFF11B | C4: =SUMIFS(XP!$D$3:$D$307,XP!$C$3:$C$307,B4,XP!$D$3:$D$307,">0",XP!$E$3:$E$307,">0") -> 22 | D4: =SUMIFS(XP!$D$3:$D$307,XP!$C$3:$C$307,B4,XP!$D$3:$D$307,"<0",XP!$E$3:$E$307,">0") -> -22 | E4: =SUMIF(XP!$C$3:C$307,B4,XP!$D$3:D$307) -> 0 | F4: =IF(C4<>0,(SUMIFS(XP!$F$3:$F$307,XP!$C$3:$C$307,$B4,XP!$F$3:$F$307,">0",XP!$F$3:$F$307,">0"))/$C4,0) -> 129.85591 | G4: =IF($C4<>0,(SUMIFS(XP!$J$3:$J$307,XP!$C$3:$C$307,$B4,XP!$J$3:$J$307,">0",XP!$J$3:$J$307,">0")+SUMIFS(MODAL!$K$2:$K$1644,MODAL!$C$2:$C$1644,$B4,MODAL!$K$2:$K$1644,">0",MODAL!$K$2:$K$1644,">0"))/$C4,0) -> 132.15045 | H4: =SUMIFS(XP!$N$3:$N$307,XP!$C$3:$C$307,$B4)+SUMIFS(MODAL!$O$2:$O$1644,MODAL!$C$2:$C$1644,$B4) -> 0 | I4: =SUMIFS(XP!$O$3:$O$307,XP!$C$3:$C$307,$B4)+SUMIFS(MODAL!$P$2:$P$1636,MODAL!$C$2:$C$1636,$B4) -> 0 | J4: =SUMIFS(XP!$M$3:$M$307,XP!$C$3:$C$307,$B4)+SUMIFS(MODAL!$N$2:$N$1644,MODAL!$C$2:$C$1644,$B4) -> 83.31 | L4: 69.8 | M4: =(E4+K4)*L4 -> 0
B5: BVMF3 | C5: =SUMIFS(XP!$D$3:$D$307,XP!$C$3:$C$307,B5,XP!$D$3:$D$307,">0",XP!$E$3:$E$307,">0") -> 100 | D5: =SUMIFS(XP!$D$3:$D$307,XP!$C$3:$C$307,B5,XP!$D$3:$D$307,"<0",XP!$E$3:$E$307,">0") -> -100 | E5: =SUMIF(XP!$C$3:C$307,B5,XP!$D$3:D$307) -> 0 | F5: =IF(C5<>0,(SUMIFS(XP!$F$3:$F$307,XP!$C$3:$C$307,$B5,XP!$F$3:$F$307,">0",XP!$F$3:$F$307,">0"))/$C5,0) -> 11.54 | G5: =IF($C5<>0,(SUMIFS(XP!$J$3:$J$307,XP!$C$3:$C$307,$B5,XP!$J$3:$J$307,">0",XP!$J$3:$J$307,">0")+SUMIFS(MODAL!$K$2:$K$1644,MODAL!$C$2:$C$1644,$B5,MODAL!$K$2:$K$1644,">0",MODAL!$K$2:$K$1644,">0"))/$C5,0) -> 12.4902 | H5: =SUMIFS(XP!$N$3:$N$307,XP!$C$3:$C$307,$B5)+SUMIFS(MODAL!$O$2:$O$1644,MODAL!$C$2:$C$1644,$B5) -> 41.87 | I5: =SUMIFS(XP!$O$3:$O$307,XP!$C$3:$C$307,$B5)+SUMIFS(MODAL!$P$2:$P$1636,MODAL!$C$2:$C$1636,$B5) -> 0 | J5: =SUMIFS(XP!$M$3:$M$307,XP!$C$3:$C$307,$B5)+SUMIFS(MODAL!$N$2:$N$1644,MODAL!$C$2:$C$1644,$B5) -> 0 | M5: =(E5+K5)*L5 -> 0
A6: XP | B6: CMIG3 | C6: =SUMIFS(XP!$D$3:$D$307,XP!$C$3:$C$307,B6,XP!$D$3:$D$307,">0",XP!$E$3:$E$307,">0") -> 800 | D6: =SUMIFS(XP!$D$3:$D$307,XP!$C$3:$C$307,B6,XP!$D$3:$D$307,"<0",XP!$E$3:$E$307,">0") -> -800 | E6: =SUMIF(XP!$C$3:C$307,B6,XP!$D$3:D$307) -> 0 | F6: =IF(C6<>0,(SUMIFS(XP!$F$3:$F$399,XP!$C$3:$C$399,$B6,XP!$F$3:$F$399,">0",XP!$F$3:$F$399,">0"))/$C6,0) -> 11.0575 | G6: =IF($C6<>0,(SUMIFS(XP!$J$3:$J$399,XP!$C$3:$C$399,$B6,XP!$J$3:$J$399,">0",XP!$J$3:$J$399,">0"))/$C6,0) -> 11.182162 | H6: =SUMIFS(XP!$N$3:$N$307,XP!$C$3:$C$307,$B6) -> 754.64 | I6: =SUMIFS(XP!$O$3:$O$307,XP!$C$3:$C$307,$B6) -> 149.76 | J6: =SUMIFS(XP!$M$3:$M$307,XP!$C$3:$C$307,$B6)+SUMIFS(MODAL!$N$2:$N$1644,MODAL!$C$2:$C$1644,$B6) -> 0 | M6: =(E6+K6)*L6 -> 0
A7: XP | B7: CMIG4 | C7: =SUMIFS(XP!$D$3:$D$307,XP!$C$3:$C$307,B7,XP!$D$3:$D$307,">0",XP!$E$3:$E$307,">0") -> 200 | D7: =SUMIFS(XP!$D$3:$D$307,XP!$C$3:$C$307,B7,XP!$D$3:$D$307,"<0",XP!$E$3:$E$307,">0") -> -230 | E7: =SUMIF(XP!$C$3:C$307,B7,XP!$D$3:D$307) -> 0 | F7: =IF(C7<>0,(SUMIFS(XP!$F$3:$F$307,XP!$C$3:$C$307,$B7,XP!$F$3:$F$307,">0",XP!$F$3:$F$307,">0"))/$C7,0) -> 11.86 | G7: =IF($C7<>0,(SUMIFS(XP!$J$3:$J$307,XP!$C$3:$C$307,$B7,XP!$J$3:$J$307,">0",XP!$J$3:$J$307,">0")+SUMIFS(MODAL!$K$2:$K$1644,MODAL!$C$2:$C$1644,$B7,MODAL!$K$2:$K$1644,">0",MODAL!$K$2:$K$1644,">0"))/$C7,0) -> 18.80785 | H7: =SUMIFS(XP!$N$3:$N$307,XP!$C$3:$C$307,$B7)+SUMIFS(MODAL!$O$2:$O$1644,MODAL!$C$2:$C$1644,$B7) -> 103.98 | I7: =SUMIFS(XP!$O$3:$O$307,XP!$C$3:$C$307,$B7)+SUMIFS(MODAL!$P$2:$P$1636,MODAL!$C$2:$C$1636,$B7) -> 13.14 | J7: =SUMIFS(XP!$M$3:$M$307,XP!$C$3:$C$307,$B7)+SUMIFS(MODAL!$N$2:$N$1644,MODAL!$C$2:$C$1644,$B7) -> 0 | M7: =(E7+K7)*L7 -> 0
A8: XP | B8: CSNA3 | C8: =SUMIFS(XP!$D$3:$D$307,XP!$C$3:$C$307,B8,XP!$D$3:$D$307,">0",XP!$E$3:$E$307,">0") -> 100 | D8: =SUMIFS(XP!$D$3:$D$307,XP!$C$3:$C$307,B8,XP!$D$3:$D$307,"<0",XP!$E$3:$E$307,">0") -> -100 | E8: =SUMIF(XP!$C$3:C$307,B8,XP!$D$3:D$307) -> 0 | F8: =IF(C8<>0,(SUMIFS(XP!$F$3:$F$307,XP!$C$3:$C$307,$B8,XP!$F$3:$F$307,">0",XP!$F$3:$F$307,">0"))/$C8,0) -> 9.04 | G8: =IF($C8<>0,(SUMIFS(XP!$J$3:$J$307,XP!$C$3:$C$307,$B8,XP!$J$3:$J$307,">0",XP!$J$3:$J$307,">0")+SUMIFS(MODAL!$K$2:$K$1644,MODAL!$C$2:$C$1644,$B8,MODAL!$K$2:$K$1644,">0",MODAL!$K$2:$K$1644,">0"))/$C8,0) -> 28.7304 | H8: =SUMIFS(XP!$N$3:$N$307,XP!$C$3:$C$307,$B8)+SUMIFS(MODAL!$O$2:$O$1644,MODAL!$C$2:$C$1644,$B8) -> 0 | I8: =SUMIFS(XP!$O$3:$O$307,XP!$C$3:$C$307,$B8)+SUMIFS(MODAL!$P$2:$P$1636,MODAL!$C$2:$C$1636,$B8) -> 0 | J8: =SUMIFS(XP!$M$3:$M$307,XP!$C$3:$C$307,$B8)+SUMIFS(MODAL!$N$2:$N$1644,MODAL!$C$2:$C$1644,$B8) -> 0 | M8: =(E8+K8)*L8 -> 0
A9: XP | B9: ELET3 | C9: =SUMIFS(XP!$D$3:$D$307,XP!$C$3:$C$307,B9,XP!$D$3:$D$307,">0",XP!$E$3:$E$307,">0") -> 150 | D9: =SUMIFS(XP!$D$3:$D$307,XP!$C$3:$C$307,B9,XP!$D$3:$D$307,">0",XP!$E$3:$E$307,">0") -> 150 | E9: =SUMIF(XP!$C$3:C$307,B9,XP!$D$3:D$307) -> 0 | F9: =IF(C9<>0,(SUMIFS(XP!$F$3:$F$307,XP!$C$3:$C$307,$B9,XP!$F$3:$F$307,">0",XP!$F$3:$F$307,">0"))/$C9,0) -> 5.6733333 | G9: =IF($C9<>0,(SUMIFS(XP!$J$3:$J$307,XP!$C$3:$C$307,$B9,XP!$J$3:$J$307,">0",XP!$J$3:$J$307,">0")+SUMIFS(MODAL!$K$2:$K$1644,MODAL!$C$2:$C$1644,$B9,MODAL!$K$2:$K$1644,">0",MODAL!$K$2:$K$1644,">0"))/$C9,0) -> 5.7255333 | H9: =SUMIFS(XP!$N$3:$N$307,XP!$C$3:$C$307,$B9)+SUMIFS(MODAL!$O$2:$O$1644,MODAL!$C$2:$C$1644,$B9) -> 52.83 | I9: =SUMIFS(XP!$O$3:$O$307,XP!$C$3:$C$307,$B9)+SUMIFS(MODAL!$P$2:$P$1636,MODAL!$C$2:$C$1636,$B9) -> 0 | J9: =SUMIFS(XP!$M$3:$M$307,XP!$C$3:$C$307,$B9)+SUMIFS(MODAL!$N$2:$N$1644,MODAL!$C$2:$C$1644,$B9) -> 0 | M9: =(E9+K9)*L9 -> 0
A10: XP | B10: ELPL4 | C10: =SUMIFS(XP!$D$3:$D$307,XP!$C$3:$C$307,B10,XP!$D$3:$D$307,">0",XP!$E$3:$E$307,">0")+SUMIFS(MODAL!$D$2:$D$1644,MODAL!$C$2:$C$1644,B10,MODAL!$D$2:$D$1644,">0",MODAL!$E$2:$E$1644,">0") -> 500 | D10: =SUMIFS(XP!$D$3:$D$307,XP!$C$3:$C$307,B10,XP!$D$3:$D$307,">0",XP!$E$3:$E$307,">0") -> 500 | E10: =SUMIF(XP!$C$3:C$307,B10,XP!$D$3:D$307) -> 0 | F10: =IF(C10<>0,(SUMIFS(XP!$F$3:$F$307,XP!$C$3:$C$307,$B10,XP!$F$3:$F$307,">0",XP!$F$3:$F$307,">0")+SUMIFS(MODAL!$F$2:$F$1644,MODAL!$C$2:$C$1644,$B10,MODAL!$F$2:$F$1644,">0",MODAL!$F$2:$F$1644,">0"))/$C10,0) -> 9.378 | G10: =IF($C10<>0,(SUMIFS(XP!$J$3:$J$307,XP!$C$3:$C$307,$B10,XP!$J$3:$J$307,">0",XP!$J$3:$J$307,">0")+SUMIFS(MODAL!$K$2:$K$1644,MODAL!$C$2:$C$1644,$B10,MODAL!$K$2:$K$1644,">0",MODAL!$K$2:$K$1644,">0"))/$C10,0) -> 9.47562 | H10: =SUMIFS(XP!$N$3:$N$307,XP!$C$3:$C$307,$B10)+SUMIFS(MODAL!$O$2:$O$1644,MODAL!$C$2:$C$1644,$B10) -> 171.14 | I10: =SUMIFS(XP!$O$3:$O$307,XP!$C$3:$C$307,$B10)+SUMIFS(MODAL!$P$2:$P$1636,MODAL!$C$2:$C$1636,$B10) -> 0 | J10: =SUMIFS(XP!$M$3:$M$307,XP!$C$3:$C$307,$B10)+SUMIFS(MODAL!$N$2:$N$1644,MODAL!$C$2:$C$1644,$B10) -> 0 | M10: =(E10+K10)*L10 -> 0
A11: MODAL | B11: ETER3 | C11: =SUMIFS(MODAL!$D$2:$D$1644,MODAL!$C$2:$C$1644,B11,MODAL!$D$2:$D$1644,">0",MODAL!$E$2:$E$1644,">0") -> 4100 | D11: =SUMIFS(MODAL!$D$2:$D$1644,MODAL!$C$2:$C$1644,B11,MODAL!$D$2:$D$1644,"<0",MODAL!$E$2:$E$1644,">0") -> -1600 | E11: =SUMIF(MODAL!$C$2:C$1644,B11,MODAL!$D$2:D$1644) -> 3300 | F11: =IF(C11<>0,(SUMIFS(MODAL!$F$2:$F$1644,MODAL!$C$2:$C$1644,$B11,MODAL!$F$2:$F$1644,">0",MODAL!$F$2:$F$1644,">0"))/$C11,0) -> 2.8636585 | G11: =IF($C11<>0,(SUMIFS(MODAL!$K$2:$K$1644,MODAL!$C$2:$C$1644,$B11,MODAL!$K$2:$K$1644,">0",MODAL!$K$2:$K$1644,">0"))/$C11,0) -> 2.8884073 | H11: =SUMIFS(MODAL!$O$2:$O$1644,MODAL!$C$2:$C$1644,$B11) -> 191.18 | I11: =SUMIFS(MODAL!$P$2:$P$1636,MODAL!$C$2:$C$1636,$B11) -> 62.65 | J11: =SUMIFS(MODAL!$N$2:$N$1644,MODAL!$C$2:$C$1644,$B11) -> 0 | L11: 1.17 | M11: =(E11+K11)*L11 -> 3861
B12: ODPV3 | C12: =SUMIFS(XP!$D$3:$D$307,XP!$C$3:$C$307,B12,XP!$D$3:$D$307,">0",XP!$E$3:$E$307,">0")+SUMIFS(MODAL!$D$2:$D$1644,MODAL!$C$2:$C$1644,B12,MODAL!$D$2:$D$1644,">0",MODAL!$E$2:$E$1644,">0") -> 100 | D12: =SUMIFS(XP!$D$3:$D$307,XP!$C$3:$C$307,B12,XP!$D$3:$D$307,"<0",XP!$E$3:$E$307,">0")+SUMIFS(MODAL!$D$2:$D$1644,MODAL!$C$2:$C$1644,B12,MODAL!$D$2:$D$1644,"<0",MODAL!$E$2:$E$1644,">0") -> -100 | E12: =SUMIF(XP!$C$3:C$307,B12,XP!$D$3:D$307) -> 0 | F12: =IF(C12<>0,(SUMIFS(XP!$F$3:$F$307,XP!$C$3:$C$307,$B12,XP!$F$3:$F$307,">0",XP!$F$3:$F$307,">0")+SUMIFS(MODAL!$F$2:$F$1644,MODAL!$C$2:$C$1644,$B12,MODAL!$F$2:$F$1644,">0",MODAL!$F$2:$F$1644,">0"))/$C12,0) -> 9.5 | G12: =IF($C12<>0,(SUMIFS(XP!$J$3:$J$307,XP!$C$3:$C$307,$B12,XP!$J$3:$J$307,">0",XP!$J$3:$J$307,">0")+SUMIFS(MODAL!$K$2:$K$1644,MODAL!$C$2:$C$1644,$B12,MODAL!$K$2:$K$1644,">0",MODAL!$K$2:$K$1644,">0"))/$C12,0) -> 9.5046 | H12: =SUMIFS(XP!$N$3:$N$307,XP!$C$3:$C$307,$B12)+SUMIFS(MODAL!$O$2:$O$1644,MODAL!$C$2:$C$1644,$B12) -> 13.7 | I12: =SUMIFS(XP!$O$3:$O$307,XP!$C$3:$C$307,$B12)+SUMIFS(MODAL!$P$2:$P$1636,MODAL!$C$2:$C$1636,$B12) -> 0 | J12: =SUMIFS(XP!$M$3:$M$307,XP!$C$3:$C$307,$B12)+SUMIFS(MODAL!$N$2:$N$1644,MODAL!$C$2:$C$1644,$B12) -> 0 | M12: =(E12+K12)*L12 -> 0
A13: XP | B13: OIBR3 | C13: =SUMIFS(XP!$D$3:$D$307,XP!$C$3:$C$307,B13,XP!$D$3:$D$307,">0",XP!$E$3:$E$307,">0") -> 1000 | D13: =SUMIFS(XP!$D$3:$D$307,XP!$C$3:$C$307,B13,XP!$D$3:$D$307,"<0",XP!$E$3:$E$307,">0") -> -100 | E13: =SUMIF(XP!$C$3:C$307,B13,XP!$D$3:D$307) -> 900 | F13: =IF(C13<>0,(SUMIFS(XP!$F$3:$F$307,XP!$C$3:$C$307,$B13,XP!$F$3:$F$307,">0",XP!$F$3:$F$307,">0")+SUMIFS(MODAL!$F$2:$F$1644,MODAL!$C$2:$C$1644,$B13,MODAL!$F$2:$F$1644,">0",MODAL!$F$2:$F$1644,">0"))/$C13,0) -> 8.5 | G13: =IF($C13<>0,(SUMIFS(XP!$J$3:$J$307,XP!$C$3:$C$307,$B13,XP!$J$3:$J$307,">0",XP!$J$3:$J$307,">0")+SUMIFS(MODAL!$K$2:$K$1644,MODAL!$C$2:$C$1644,$B13,MODAL!$K$2:$K$1644,">0",MODAL!$K$2:$K$1644,">0"))/$C13,0) -> 8.56641 | H13: =SUMIFS(XP!$N$3:$N$307,XP!$C$3:$C$307,$B13)+SUMIFS(MODAL!$O$2:$O$1644,MODAL!$C$2:$C$1644,$B13) -> 152.43 | I13: =SUMIFS(XP!$O$3:$O$307,XP!$C$3:$C$307,$B13)+SUMIFS(MODAL!$P$2:$P$1636,MODAL!$C$2:$C$1636,$B13) -> 0 | J13: =SUMIFS(XP!$M$3:$M$307,XP!$C$3:$C$307,$B13)+SUMIFS(MODAL!$N$2:$N$1644,MODAL!$C$2:$C$1644,$B13) -> 0 | M13: =(E13+K13)*L13 -> 0 | O13: Obs: houve agrupamento de ações na proporção de 10:1
A14: XP | B14: PETR3 | C14: =SUMIFS(XP!$D$3:$D$307,XP!$C$3:$C$307,B14,XP!$D$3:$D$307,">0",XP!$E$3:$E$307,">0")+SUMIFS(MODAL!$D$2:$D$1644,MODAL!$C$2:$C$1644,B14,MODAL!$D$2:$D$1644,">0",MODAL!$E$2:$E$1644,">0") -> 700 | D14: =SUMIFS(XP!$D$3:$D$307,XP!$C$3:$C$307,B14,XP!$D$3:$D$307,"<0",XP!$E$3:$E$307,">0")+SUMIFS(MODAL!$D$2:$D$1644,MODAL!$C$2:$C$1644,B14,MODAL!$D$2:$D$1644,"<0",MODAL!$E$2:$E$1644,">0") -> -700 | E14: =SUMIF(XP!$C$3:C$307,B14,XP!$D$3:D$307)+SUMIF(MODAL!$C$2:C$1644,B14,MODAL!$D$2:D$1644) -> 0 | F14: =IF(C14<>0,(SUMIFS(XP!$F$3:$F$307,XP!$C$3:$C$307,$B14,XP!$F$3:$F$307,">0",XP!$F$3:$F$307,">0")+SUMIFS(MODAL!$F$2:$F$1644,MODAL!$C$2:$C$1644,$B14,MODAL!$F$2:$F$1644,">0",MODAL!$F$2:$F$1644,">0"))/$C14,0) -> 10.461429 | G14: =IF($C14<>0,(SUMIFS(XP!$J$3:$J$307,XP!$C$3:$C$307,$B14,XP!$J$3:$J$307,">0",XP!$J$3:$J$307,">0")+SUMIFS(MODAL!$K$2:$K$1644,MODAL!$C$2:$C$1644,$B14,MODAL!$K$2:$K$1644,">0",MODAL!$K$2:$K$1644,">0"))/$C14,0) -> 10.554871 | H14: =SUMIFS(XP!$N$3:$N$307,XP!$C$3:$C$307,$B14)+SUMIFS(MODAL!$O$2:$O$1644,MODAL!$C$2:$C$1644,$B14) -> 45.62 | I14: =SUMIFS(XP!$O$3:$O$307,XP!$C$3:$C$307,$B14)+SUMIFS(MODAL!$P$2:$P$1636,MODAL!$C$2:$C$1636,$B14) -> 0 | J14: =SUMIFS(XP!$M$3:$M$307,XP!$C$3:$C$307,$B14)+SUMIFS(MODAL!$N$2:$N$1644,MODAL!$C$2:$C$1644,$B14) -> 0 | M14: =(E14+K14)*L14 -> 0
B15: SULA11 | C15: =SUMIFS(XP!$D$3:$D$307,XP!$C$3:$C$307,B15,XP!$D$3:$D$307,">0",XP!$E$3:$E$307,">0")+SUMIFS(MODAL!$D$2:$D$1644,MODAL!$C$2:$C$1644,B15,MODAL!$D$2:$D$1644,">0",MODAL!$E$2:$E$1644,">0") -> 100 | D15: =SUMIFS(XP!$D$3:$D$307,XP!$C$3:$C$307,B15,XP!$D$3:$D$307,"<0",XP!$E$3:$E$307,">0")+SUMIFS(MODAL!$D$2:$D$1644,MODAL!$C$2:$C$1644,B15,MODAL!$D$2:$D$1644,"<0",MODAL!$E$2:$E$1644,">0") -> -100 | E15: =SUMIF(XP!$C$3:C$307,B15,XP!$D$3:D$307)+SUMIF(MODAL!$C$2:C$1644,B15,MODAL!$D$2:D$1644) -> 0 | F15: =IF(C15<>0,(SUMIFS(XP!$F$3:$F$307,XP!$C$3:$C$307,$B15,XP!$F$3:$F$307,">0",XP!$F$3:$F$307,">0")+SUMIFS(MODAL!$F$2:$F$1644,MODAL!$C$2:$C$1644,$B15,MODAL!$F$2:$F$1644,">0",MODAL!$F$2:$F$1644,">0"))/$C15,0) -> 13.57 | G15: =IF($C15<>0,(SUMIFS(XP!$J$3:$J$307,XP!$C$3:$C$307,$B15,XP!$J$3:$J$307,">0",XP!$J$3:$J$307,">0")+SUMIFS(MODAL!$K$2:$K$1644,MODAL!$C$2:$C$1644,$B15,MODAL!$K$2:$K$1644,">0",MODAL!$K$2:$K$1644,">0"))/$C15,0) -> 13.5743 | H15: =SUMIFS(XP!$N$3:$N$307,XP!$C$3:$C$307,$B15)+SUMIFS(MODAL!$O$2:$O$1644,MODAL!$C$2:$C$1644,$B15) -> 21.18 | I15: =SUMIFS(XP!$O$3:$O$307,XP!$C$3:$C$307,$B15)+SUMIFS(MODAL!$P$2:$P$1636,MODAL!$C$2:$C$1636,$B15) -> 7.63 | J15: =SUMIFS(XP!$M$3:$M$307,XP!$C$3:$C$307,$B15)+SUMIFS(MODAL!$N$2:$N$1644,MODAL!$C$2:$C$1644,$B15) -> 0 | M15: =(E15+K15)*L15 -> 0
B16: SUZB5 | C16: =SUMIFS(XP!$D$3:$D$307,XP!$C$3:$C$307,B16,XP!$D$3:$D$307,">0",XP!$E$3:$E$307,">0")+SUMIFS(MODAL!$D$2:$D$1644,MODAL!$C$2:$C$1644,B16,MODAL!$D$2:$D$1644,">0",MODAL!$E$2:$E$1644,">0") -> 200 | D16: =SUMIFS(XP!$D$3:$D$307,XP!$C$3:$C$307,B16,XP!$D$3:$D$307,"<0",XP!$E$3:$E$307,">0")+SUMIFS(MODAL!$D$2:$D$1644,MODAL!$C$2:$C$1644,B16,MODAL!$D$2:$D$1644,"<0",MODAL!$E$2:$E$1644,">0") -> -200 | E16: =SUMIF(XP!$C$3:C$307,B16,XP!$D$3:D$307)+SUMIF(MODAL!$C$2:C$1644,B16,MODAL!$D$2:D$1644) -> 0 | F16: =IF(C16<>0,(SUMIFS(XP!$F$3:$F$307,XP!$C$3:$C$307,$B16,XP!$F$3:$F$307,">0",XP!$F$3:$F$307,">0")+SUMIFS(MODAL!$F$2:$F$1644,MODAL!$C$2:$C$1644,$B16,MODAL!$F$2:$F$1644,">0",MODAL!$F$2:$F$1644,">0"))/$C16,0) -> 7.8 | G16: =IF($C16<>0,(SUMIFS(XP!$J$3:$J$307,XP!$C$3:$C$307,$B16,XP!$J$3:$J$307,">0",XP!$J$3:$J$307,">0")+SUMIFS(MODAL!$K$2:$K$1644,MODAL!$C$2:$C$1644,$B16,MODAL!$K$2:$K$1644,">0",MODAL!$K$2:$K$1644,">0"))/$C16,0) -> 7.8813 | H16: =SUMIFS(XP!$N$3:$N$307,XP!$C$3:$C$307,$B16)+SUMIFS(MODAL!$O$2:$O$1644,MODAL!$C$2:$C$1644,$B16) -> 23.2 | I16: =SUMIFS(XP!$O$3:$O$307,XP!$C$3:$C$307,$B16)+SUMIFS(MODAL!$P$2:$P$1636,MODAL!$C$2:$C$1636,$B16) -> 0 | J16: =SUMIFS(XP!$M$3:$M$307,XP!$C$3:$C$307,$B16)+SUMIFS(MODAL!$N$2:$N$1644,MODAL!$C$2:$C$1644,$B16) -> 0 | M16: =(E16+K16)*L16 -> 0
A17: MODAL | B17: VALE5 | C17: =SUMIFS(MODAL!$D$2:$D$1644,MODAL!$C$2:$C$1644,B17,MODAL!$D$2:$D$1644,">0",MODAL!$E$2:$E$1644,">0") -> 300 | D17: =SUMIFS(MODAL!$D$2:$D$1644,MODAL!$C$2:$C$1644,B17,MODAL!$D$2:$D$1644,"<0",MODAL!$E$2:$E$1644,">0") -> -300 | E17: =SUMIF(MODAL!$C$2:C$1644,B17,MODAL!$D$2:D$1644) -> 0 | F17: =IF(C17<>0,(SUMIFS(MODAL!$F$2:$F$1644,MODAL!$C$2:$C$1644,$B17,MODAL!$F$2:$F$1644,">0",MODAL!$F$2:$F$1644,">0"))/$C17,0) -> 26.272333 | G17: =IF($C17<>0,(SUMIFS(MODAL!$K$2:$K$1644,MODAL!$C$2:$C$1644,$B17,MODAL!$K$2:$K$1644,">0",MODAL!$K$2:$K$1644,">0"))/$C17,0) -> 26.370633 | H17: =SUMIFS(MODAL!$O$2:$O$1644,MODAL!$C$2:$C$1644,$B17) -> 255.46 | I17: =SUMIFS(MODAL!$P$2:$P$1636,MODAL!$C$2:$C$1636,$B17) -> 165.97 | J17: =SUMIFS(MODAL!$N$2:$N$1644,MODAL!$C$2:$C$1644,$B17) -> 0 | M17: =(E17+K17)*L17 -> 0
A18: XP | B18: ETER3 | C18: =SUMIFS(XP!$D$3:$D$307,XP!$C$3:$C$307,B18,XP!$D$3:$D$307,">0",XP!$E$3:$E$307,">0") -> 2500 | D18: =SUMIFS(XP!$D$3:$D$307,XP!$C$3:$C$307,B18,XP!$D$3:$D$307,"<0",XP!$E$3:$E$307,">0")+SUMIFS(MODAL!$D$2:$D$1644,MODAL!$C$2:$C$1644,B18,MODAL!$D$2:$D$1644,"<0",MODAL!$E$2:$E$1644,">0") -> -1600 | E18: =SUMIF(XP!$C$3:C$307,B18,XP!$D$3:D$307) -> 2500 | F18: =IF(C18<>0,(SUMIFS(XP!$F$3:$F$307,XP!$C$3:$C$307,$B18,XP!$F$3:$F$307,">0",XP!$F$3:$F$307,">0"))/$C18,0) -> 3.168 | G18: =IF($C18<>0,(SUMIFS(XP!$J$3:$J$307,XP!$C$3:$C$307,$B18,XP!$J$3:$J$307,">0",XP!$J$3:$J$307,">0"))/$C18,0) -> 3.201464 | H18: =SUMIFS(XP!$N$3:$N$307,XP!$C$3:$C$307,$B18) -> 275.65 | I18: =SUMIFS(XP!$O$3:$O$307,XP!$C$3:$C$307,$B18) -> 436.41 | J18: =SUMIFS(XP!$M$3:$M$307,XP!$C$3:$C$307,$B18) -> 0 | L18: 1.17 | M18: =(E18+K18)*L18 -> 2925
A19: XP | B19: VALE5 | C19: =SUMIFS(XP!$D$3:$D$307,XP!$C$3:$C$307,B19,XP!$D$3:$D$307,">0",XP!$E$3:$E$307,">0") -> 800 | D19: =SUMIFS(XP!$D$3:$D$307,XP!$C$3:$C$307,B19,XP!$D$3:$D$307,"<0",XP!$E$3:$E$307,">0") -> -800 | E19: =SUMIF(XP!$C$3:C$307,B19,XP!$D$3:D$307) -> 0 | F19: =IF(C19<>0,(SUMIFS(XP!$F$3:$F$263,XP!$C$3:$C$263,$B19,XP!$F$3:$F$263,">0",XP!$F$3:$F$263,">0"))/$C19,0) -> 17.31 | G19: =IF($C19<>0,(SUMIFS(XP!$J$3:$J$263,XP!$C$3:$C$263,$B19,XP!$J$3:$J$263,">0",XP!$J$3:$J$263,">0"))/$C19,0) -> 17.4158 | H19: =SUMIFS(XP!$N$3:$N$307,XP!$C$3:$C$307,$B19) -> 0 | I19: =SUMIFS(XP!$O$3:$O$307,XP!$C$3:$C$307,$B19) -> 204.6 | J19: =SUMIFS(XP!$M$3:$M$307,XP!$C$3:$C$307,$B19) -> 0 | M19: =(E19+K19)*L19 -> 0
A20: XP | B20: USIM5 | C20: =SUMIFS(XP!$D$3:$D$307,XP!$C$3:$C$307,B20,XP!$D$3:$D$307,">0",XP!$E$3:$E$307,">0") -> 500 | D20: =SUMIFS(XP!$D$3:$D$307,XP!$C$3:$C$307,B20,XP!$D$3:$D$307,"<0",XP!$E$3:$E$307,">0") -> -500 | E20: =SUMIF(XP!$C$3:C$307,B20,XP!$D$3:D$307) -> 0 | F20: =IF(C20<>0,(SUMIFS(XP!$F$3:$F$307,XP!$C$3:$C$307,$B20,XP!$F$3:$F$307,">0",XP!$F$3:$F$307,">0")+SUMIFS(MODAL!$F$2:$F$1644,MODAL!$C$2:$C$1644,$B20,MODAL!$F$2:$F$1644,">0",MODAL!$F$2:$F$1644,">0"))/$C20,0) -> 5.33 | G20: =IF($C20<>0,(SUMIFS(XP!$J$3:$J$307,XP!$C$3:$C$307,$B20,XP!$J$3:$J$307,">0",XP!$J$3:$J$307,">0")+SUMIFS(MODAL!$K$2:$K$1644,MODAL!$C$2:$C$1644,$B20,MODAL!$K$2:$K$1644,">0",MODAL!$K$2:$K$1644,">0"))/$C20,0) -> 5.36554 | H20: =SUMIFS(XP!$N$3:$N$307,XP!$C$3:$C$307,$B20) -> 0 | I20: =SUMIFS(XP!$O$3:$O$307,XP!$C$3:$C$307,$B20) -> 0 | J20: =SUMIFS(XP!$M$3:$M$307,XP!$C$3:$C$307,$B20) -> 0 | M20: =(E20+K20)*L20 -> 0
A21: XP | B21: GETI3 | C21: =SUMIFS(XP!$D$3:$D$307,XP!$C$3:$C$307,B21,XP!$D$3:$D$307,">0",XP!$E$3:$E$307,">0") -> 200 | D21: =SUMIFS(XP!$D$3:$D$307,XP!$C$3:$C$307,B21,XP!$D$3:$D$307,"<0",XP!$E$3:$E$307,">0") -> -200 | E21: =SUMIF(XP!$C$3:C$307,B21,XP!$D$3:D$307) -> 0 | F21: =IF(C21<>0,(SUMIFS(XP!$F$3:$F$307,XP!$C$3:$C$307,$B21,XP!$F$3:$F$307,">0",XP!$F$3:$F$307,">0")+SUMIFS(MODAL!$F$2:$F$1644,MODAL!$C$2:$C$1644,$B21,MODAL!$F$2:$F$1644,">0",MODAL!$F$2:$F$1644,">0"))/$C21,0) -> 14.58 | G21: =IF($C21<>0,(SUMIFS(XP!$J$3:$J$307,XP!$C$3:$C$307,$B21,XP!$J$3:$J$307,">0",XP!$J$3:$J$307,">0")+SUMIFS(MODAL!$K$2:$K$1644,MODAL!$C$2:$C$1644,$B21,MODAL!$K$2:$K$1644,">0",MODAL!$K$2:$K$1644,">0"))/$C21,0) -> 14.66925 | H21: =SUMIFS(XP!$N$3:$N$307,XP!$C$3:$C$307,$B21) -> 0 | I21: =SUMIFS(XP!$O$3:$O$307,XP!$C$3:$C$307,$B21) -> 0 | J21: =SUMIFS(XP!$M$3:$M$307,XP!$C$3:$C$307,$B21) -> 0 | M21: =(E21+K21)*L21 -> 0
A22: MODAL | B22: BBAS3 | C22: =SUMIFS(MODAL!$D$2:$D$1644,MODAL!$C$2:$C$1644,B22,MODAL!$D$2:$D$1644,">0",MODAL!$E$2:$E$1644,">0") -> 400 | D22: =SUMIFS(MODAL!$D$2:$D$1644,MODAL!$C$2:$C$1644,B22,MODAL!$D$2:$D$1644,"<0",MODAL!$E$2:$E$1644,">0") -> -500 | E22: =SUMIF(MODAL!$C$2:C$1644,B22,MODAL!$D$2:D$1644) -> 300 | F22: =IF(C22<>0,(SUMIFS(MODAL!$F$2:$F$1644,MODAL!$C$2:$C$1644,$B22,MODAL!$F$2:$F$1644,">0",MODAL!$F$2:$F$1644,">0"))/$C22,0) -> 23.703125 | G22: =IF($C22<>0,(SUMIFS(MODAL!$K$2:$K$1644,MODAL!$C$2:$C$1644,$B22,MODAL!$K$2:$K$1644,">0",MODAL!$K$2:$K$1644,">0"))/$C22,0) -> 23.785675 | H22: =SUMIFS(MODAL!$O$2:$O$1644,MODAL!$C$2:$C$1644,$B22) -> 16.06 | I22: =SUMIFS(MODAL!$P$2:$P$1636,MODAL!$C$2:$C$1636,$B22) -> 714.03 | J22: =SUMIFS(MODAL!$N$2:$N$1644,MODAL!$C$2:$C$1644,$B22) -> 0 | L22: 30.42 | M22: =(E22+K22)*L22 -> 9126
A23: MODAL | B23: ITSA4 | C23: =SUMIFS(MODAL!$D$2:$D$1644,MODAL!$C$2:$C$1644,B23,MODAL!$D$2:$D$1644,">0",MODAL!$E$2:$E$1644,">0") -> 3061 | D23: =SUMIFS(MODAL!$D$2:$D$1644,MODAL!$C$2:$C$1644,B23,MODAL!$D$2:$D$1644,"<0",MODAL!$E$2:$E$1644,">0") -> 0 | E23: =SUMIF(MODAL!$C$2:C$1644,B23,MODAL!$D$2:D$1644) -> 3267 | F23: =IF(C23<>0,(SUMIFS(MODAL!$F$2:$F$1644,MODAL!$C$2:$C$1644,$B23,MODAL!$F$2:$F$1644,">0",MODAL!$F$2:$F$1644,">0"))/$C23,0) -> 9.3057563 | G23: =IF($C23<>0,(SUMIFS(MODAL!$K$2:$K$1644,MODAL!$C$2:$C$1644,$B23,MODAL!$K$2:$K$1644,">0",MODAL!$K$2:$K$1644,">0"))/$C23,0) -> 9.3623064 | H23: =SUMIFS(MODAL!$O$2:$O$1644,MODAL!$C$2:$C$1644,$B23) -> 4399.97 | I23: =SUMIFS(MODAL!$P$2:$P$1636,MODAL!$C$2:$C$1636,$B23) -> 3097.72 | J23: =SUMIFS(MODAL!$N$2:$N$1644,MODAL!$C$2:$C$1644,$B23) -> 0 | K23: 22 | L23: 9.94 | M23: =(E23+K23)*L23 -> 32692.66
A24: MODAL | B24: KLBN4 | C24: =SUMIFS(MODAL!$D$2:$D$1644,MODAL!$C$2:$C$1644,B24,MODAL!$D$2:$D$1644,">0",MODAL!$E$2:$E$1644,">0") -> 3600 | D24: =SUMIFS(MODAL!$D$2:$D$1644,MODAL!$C$2:$C$1644,B24,MODAL!$D$2:$D$1644,"<0",MODAL!$E$2:$E$1644,">0") -> 0 | E24: =SUMIF(MODAL!$C$2:C$1644,B24,MODAL!$D$2:D$1644) -> 3600 | F24: =IF(C24<>0,(SUMIFS(MODAL!$F$2:$F$1644,MODAL!$C$2:$C$1644,$B24,MODAL!$F$2:$F$1644,">0",MODAL!$F$2:$F$1644,">0"))/$C24,0) -> 2.8933333 | G24: =IF($C24<>0,(SUMIFS(MODAL!$K$2:$K$1644,MODAL!$C$2:$C$1644,$B24,MODAL!$K$2:$K$1644,">0",MODAL!$K$2:$K$1644,">0"))/$C24,0) -> 2.9071556 | H24: =SUMIFS(MODAL!$O$2:$O$1644,MODAL!$C$2:$C$1644,$B24) -> 1074.15 | I24: =SUMIFS(MODAL!$P$2:$P$1636,MODAL!$C$2:$C$1636,$B24) -> 406.24 | J24: =SUMIFS(MODAL!$N$2:$N$1644,MODAL!$C$2:$C$1644,$B24) -> 0 | L24: 2.97 | M24: =(E24+K24)*L24 -> 10692
A25: MODAL | B25: PETR4 | C25: =SUMIFS(MODAL!$D$2:$D$1644,MODAL!$C$2:$C$1644,B25,MODAL!$D$2:$D$1644,">0",MODAL!$E$2:$E$1644,">0") -> 1500 | D25: =SUMIFS(MODAL!$D$2:$D$1644,MODAL!$C$2:$C$1644,B25,MODAL!$D$2:$D$1644,"<0",MODAL!$E$2:$E$1644,">0") -> -1300 | E25: =SUMIF(MODAL!$C$2:C$1644,B25,MODAL!$D$2:D$1644) -> 200 | F25: =IF(C25<>0,(SUMIFS(MODAL!$F$2:$F$1644,MODAL!$C$2:$C$1644,$B25,MODAL!$F$2:$F$1644,">0",MODAL!$F$2:$F$1644,">0"))/$C25,0) -> 8.35 | G25: =IF($C25<>0,(SUMIFS(MODAL!$K$2:$K$1644,MODAL!$C$2:$C$1644,$B25,MODAL!$K$2:$K$1644,">0",MODAL!$K$2:$K$1644,">0"))/$C25,0) -> 8.3822133 | H25: =SUMIFS(MODAL!$O$2:$O$1644,MODAL!$C$2:$C$1644,$B25) -> 6.52 | I25: =SUMIFS(MODAL!$P$2:$P$1636,MODAL!$C$2:$C$1636,$B25) -> 309.84 | J25: =SUMIFS(MODAL!$N$2:$N$1644,MODAL!$C$2:$C$1644,$B25) -> 0 | L25: 13.6 | M25: =(E25+K25)*L25 -> 2720
A26: MODAL | B26: TAEE11 | C26: =SUMIFS(MODAL!$D$2:$D$1644,MODAL!$C$2:$C$1644,B26,MODAL!$D$2:$D$1644,">0",MODAL!$E$2:$E$1644,">0") -> 625 | D26: =SUMIFS(MODAL!$D$2:$D$1644,MODAL!$C$2:$C$1644,B26,MODAL!$D$2:$D$1644,"<0",MODAL!$E$2:$E$1644,">0") -> 0 | E26: =SUMIF(MODAL!$C$2:C$1644,B26,MODAL!$D$2:D$1644) -> 625 | F26: =IF(C26<>0,(SUMIFS(MODAL!$F$2:$F$1644,MODAL!$C$2:$C$1644,$B26,MODAL!$F$2:$F$1644,">0",MODAL!$F$2:$F$1644,">0"))/$C26,0) -> 20.597168 | G26: =IF($C26<>0,(SUMIFS(MODAL!$K$2:$K$1644,MODAL!$C$2:$C$1644,$B26,MODAL!$K$2:$K$1644,">0",MODAL!$K$2:$K$1644,">0"))/$C26,0) -> 20.68136 | H26: =SUMIFS(MODAL!$O$2:$O$1644,MODAL!$C$2:$C$1644,$B26) -> 3935.14 | I26: =SUMIFS(MODAL!$P$2:$P$1636,MODAL!$C$2:$C$1636,$B26) -> 1656 | J26: =SUMIFS(MODAL!$N$2:$N$1644,MODAL!$C$2:$C$1644,$B26) -> 0 | L26: 22.7 | M26: =(E26+K26)*L26 -> 14187.5
A27: MODAL | B27: CMIG3 | C27: =SUMIFS(MODAL!$D$2:$D$1644,MODAL!$C$2:$C$1644,B27,MODAL!$D$2:$D$1644,">0",MODAL!$E$2:$E$1644,">0") -> 2500 | D27: =SUMIFS(MODAL!$D$2:$D$1644,MODAL!$C$2:$C$1644,B27,MODAL!$D$2:$D$1644,"<0",MODAL!$E$2:$E$1644,">0") -> -1000 | E27: =SUMIF(MODAL!$C$2:C$1644,B27,MODAL!$D$2:D$1644) -> 1500 | F27: =IF(C27<>0,(SUMIFS(MODAL!$F$2:$F$1644,MODAL!$C$2:$C$1644,$B27,MODAL!$F$2:$F$1644,">0",MODAL!$F$2:$F$1644,">0"))/$C27,0) -> 8.048 | G27: =IF($C27<>0,(SUMIFS(MODAL!$K$2:$K$1644,MODAL!$C$2:$C$1644,$B27,MODAL!$K$2:$K$1644,">0",MODAL!$K$2:$K$1644,">0"))/$C27,0) -> 8.086988 | H27: =SUMIFS(MODAL!$O$2:$O$1644,MODAL!$C$2:$C$1644,$B27) -> 1334.17 | I27: =SUMIFS(MODAL!$P$2:$P$1636,MODAL!$C$2:$C$1636,$B27) -> 953.28 | J27: =SUMIFS(MODAL!$N$2:$N$1644,MODAL!$C$2:$C$1644,$B27) -> 0 | L27: 8.4 | M27: =(E27+K27)*L27 -> 12600
A28: MODAL | B28: HGTX3 | C28: =SUMIFS(MODAL!$D$2:$D$1644,MODAL!$C$2:$C$1644,B28,MODAL!$D$2:$D$1644,">0",MODAL!$E$2:$E$1644,">0") -> 400 | D28: =SUMIFS(MODAL!$D$2:$D$1644,MODAL!$C$2:$C$1644,B28,MODAL!$D$2:$D$1644,"<0",MODAL!$E$2:$E$1644,">0") -> -500 | E28: =SUMIF(MODAL!$C$2:C$1644,B28,MODAL!$D$2:D$1644) -> -100 | F28: =IF(C28<>0,(SUMIFS(MODAL!$F$2:$F$1644,MODAL!$C$2:$C$1644,$B28,MODAL!$F$2:$F$1644,">0",MODAL!$F$2:$F$1644,">0"))/$C28,0) -> 16.76425 | G28: =IF($C28<>0,(SUMIFS(MODAL!$K$2:$K$1644,MODAL!$C$2:$C$1644,$B28,MODAL!$K$2:$K$1644,">0",MODAL!$K$2:$K$1644,">0"))/$C28,0) -> 16.845175 | H28: =SUMIFS(MODAL!$O$2:$O$1644,MODAL!$C$2:$C$1644,$B28) -> 896.01 | I28: =SUMIFS(MODAL!$P$2:$P$1636,MODAL!$C$2:$C$1636,$B28) -> 338.68 | J28: =SUMIFS(MODAL!$N$2:$N$1644,MODAL!$C$2:$C$1644,$B28) -> 0 | L28: 24.26 | M28: =(E28+K28)*L28 -> -2426
A29: MODAL | B29: BCFF11 | C29: =SUMIFS(MODAL!$D$2:$D$1630,MODAL!$C$2:$C$1630,B29,MODAL!$D$2:$D$1630,">0",MODAL!$E$2:$E$1630,">0") -> 617 | D29: =SUMIFS(MODAL!$D$2:$D$1630,MODAL!$C$2:$C$1630,C29,MODAL!$D$2:$D$1630,">0",MODAL!$E$2:$E$1630,">0") -> 0 | E29: =SUMIF(MODAL!$C$2:C$1630,B29,MODAL!$D$2:D$1630) -> 617 | F29: =IF(C29<>0,(SUMIFS(XP!$F$3:$F$307,XP!$C$3:$C$307,$B29,XP!$F$3:$F$307,">0",XP!$F$3:$F$307,">0"))/$C29,0) -> 0 | G29: =IF($C29<>0,(SUMIFS(XP!$J$3:$J$307,XP!$C$3:$C$307,$B29,XP!$J$3:$J$307,">0",XP!$J$3:$J$307,">0")+SUMIFS(MODAL!$K$2:$K$1644,MODAL!$C$2:$C$1644,$B29,MODAL!$K$2:$K$1644,">0",MODAL!$K$2:$K$1644,">0"))/$C29,0) -> 77.503987 | H29: =SUMIFS(XP!$N$3:$N$307,XP!$C$3:$C$307,$B29)+SUMIFS(MODAL!$O$2:$O$1644,MODAL!$C$2:$C$1644,$B29) -> 0 | I29: =SUMIFS(XP!$O$3:$O$307,XP!$C$3:$C$307,$B29)+SUMIFS(MODAL!$P$2:$P$1636,MODAL!$C$2:$C$1636,$B29) -> 0 | J29: =SUMIFS(XP!$M$3:$M$307,XP!$C$3:$C$307,$B29)+SUMIFS(MODAL!$N$2:$N$1644,MODAL!$C$2:$C$1644,$B29) -> 11558.95 | L29: 69.8 | M29: =(E29+K29)*L29 -> 43066.6
A30: TOTAIS | B30: =COUNTIF(E3:E28,"<>0") -> 10 | E30: =SUM(E3:E28) -> 16092 | H30: =SUM(H3:H28) -> 14291.87 | I30: =SUM(I3:I28) -> 9471.19 | J30: =SUM(J3:J28) -> 83.31 | K30: =SUM(K3:K28) -> 22 | M30: =SUM(M3:M28) -> 86378.16
A34: RENTABILIDADE CARTEIRA | I34: POSIÇÃO GERAL ATUAL
A35: DATA | B35: INVESTIDO | C35: RETIRADAS | D35: SALDO EM CONTA NA CORRETORA | E35: POSIÇÃO | F35: DINHEIRO | G35: RENTABILIDADE | I35: CORRETORA | J35: DEPÓSITOS | K35: RETIRADAS | L35: SALDO EM CONTA NA CORRETORA | M35: POSIÇÃO
A36: 42153 | B36: =SUM(J36:J37) -> 127230 | C36: =SUM(K36:K37) -> 25562.32 | D36: =SUM(L36:L37) -> 2189.03 | E36: =SUM(M36:M37) -> 86378.16 | F36: =C36+D36+E36 -> 114129.51 | G36: =F36/B36-1 -> -0.10296699 | I36: XP | J36: =SUMIFS(XP!$B$3:$B218,XP!$B$3:$B218,">0") -> 44130 | K36: =ABS(SUMIFS(XP!$B$3:$B218,XP!$B$3:$B218,"<0")) -> 25562.32 | L36: =XP!R218 -> 8.5 | M36: =SUMIFS($M$3:$M28,$A$3:$A28,"XP") -> 2925
I37: MODAL | J37: =SUMIFS(MODAL!$B$36:$B204,MODAL!$B$36:$B204,">0") -> 83100 | K37: =ABS(SUMIFS(MODAL!$B$36:$B204,MODAL!$B$36:$B204,"<0")) -> 0 | L37: =MODAL!Q204 -> 2180.53 | M37: =SUMIFS($M$3:$M28,$A$3:$A28,"MODAL") -> 83453.16
A38: 41873 | B38: 28830 | C38: 6652.32 | D38: 6061.26 | E38: 19672.8 | F38: 32386.38 | G38: 0 | I38: TOTAIS | J38: =SUM(J36:J37) -> 127230 | K38: =SUM(K36:K37) -> 25562.32 | L38: =SUM(L36:L37) -> 2189.03 | M38: =SUM(M36:M37) -> 86378.16
A39: 41877 | B39: 28830 | C39: 6652.32 | D39: 3014.05 | E39: 22961.8 | F39: 32628.17 | G39: =F39/F38-1 -> 0.0074657927
A40: 41878 | B40: 28830 | C40: 6652.32 | D40: 3014.05 | E40: 23436.5 | F40: 33102.87 | G40: =F40/F39-1 -> 0.014548778
A41: 41879 | B41: 28830 | C41: 6652.32 | D41: 1235.93 | E41: 25137 | F41: 33025.25 | G41: =F41/F40-1 -> -0.0023448118 | I41: SALDO (DEPOSITO-RETIRADA) | L41: =J38-K38 -> 101667.68
A42: 41880 | B42: 28830 | C42: 6652.32 | D42: 1236.06 | E42: 25404.5 | F42: 33292.88 | G42: =F42/F41-1 -> 0.0081037994 | I42: POSIÇÃO ATUAL | L42: =M38 -> 86378.16
A43: 41885 | B43: 28830 | C43: 6652.32 | D43: 7575.48 | E43: 18955 | F43: 33182.8 | G43: =F43/F42-1 -> -0.0033064127 | I43: LUCRO/PREJUIZO | L43: =(L42+L38)-L41 -> -13100.49
A44: 41887 | B44: 28830 | C44: 10152.32 | D44: 1595.7 | E44: 21529.5 | F44: 33277.52 | G44: =F44/F43-1 -> 0.0028544909
A45: 41894 | B45: 28830 | C45: 10152.32 | D45: 1595.7 | E45: 22393.5 | F45: 34141.52 | G45: =F45/F44-1 -> 0.025963473
A46: 41900 | B46: 28830 | C46: 10152.32 | D46: 21.95 | E46: 24163 | F46: 34337.27 | G46: =F46/F45-1 -> 0.0057334881 | I46: SALDO (DEPOSITO-RETIRADA) | L46: =J38-K38 -> 101667.68
A47: 41901 | B47: 30560 | C47: 10152.32 | D47: 21.95 | E47: 23731 | F47: 33905.27 | G47: =F47/F46-1 -> -0.012581082 | I47: POSIÇÃO ATUAL | L47: =M38 -> 86378.16
A48: 41912 | B48: 30560 | C48: 10152.32 | D48: 21.95 | E48: 22821 | F48: 32995.27 | G48: =F48/F47-1 -> -0.026839485 | I48: DIVIDENDOS + JCP | L48: =#REF! -> #REF!
A49: 41915 | B49: 31990 | C49: 10152.32 | D49: 22.1 | E49: 24027.5 | F49: 34201.92 | G49: =F49/F48-1 -> 0.036570393 | I49: LUCRO/PREJUIZO | L49: =(L42+L38+L48)-L41 -> #REF!
A50: 41920 | B50: 31990 | C50: 10152.32 | D50: 22.1 | E50: 24980 | F50: 35154.42 | G50: =F50/F49-1 -> 0.027849314
A51: 41929 | B51: 33090 | C51: 10152.32 | D51: 22.1 | E51: 24685.5 | F51: 34859.92 | G51: =F51/F50-1 -> -0.008377325
A52: 41943 | B52: 34560 | C52: 10152.32 | D52: 22.18 | E52: 24250.5 | F52: 34425 | G52: =F52/F51-1 -> -0.012476219
A53: 42038 | B53: 41010 | C53: 15533.88 | D53: 18.18 | E53: 23062.5 | F53: 38614.56 | G53: -0.058411119
A54: 42096 | B54: 45930 | C54: 19515.44 | D54: 238.21 | E54: 28685 | F54: 48438.65 | G54: 0.054618985
A55: 42124 | B55: 45930 | C55: 19515.44 | D55: 7526.62 | E55: 28883 | F55: 55925.06 | G55: 0.21761507
A56: 42137 | B56: 45930 | C56: 19515.44 | D56: 6166.27 | E56: 29207 | F56: 54888.71 | G56: 0.19505138
A57: 42146 | B57: 45930 | C57: 19515.44 | D57: 3476.6 | E57: 27972 | F57: 50964.04 | G57: 0.10960244

Sheet Tesouro_Direto
A1: TESOURO DIRETO
A2: DATA | B2: TITULOS | C2: PREÇO TITULO | D2: TOTAL | E2: RENTAB CONTR | F2: ACUMULAD ANUAL | G2: ACUMUL % | H2: VLR BRUTO | I2: TEMPO | J2: ALIQUOTA I.R. | K2: IMP. RENDA | L2: IOF | M2: TX BOVESPA | N2: TX INSTITUICAO | O2: VLR LIQUIDO | P2: JUROS | R2: LUCRO LIQUIDO
A3: 42580 | B3: 0.2 | C3: 3004.6 | D3: 600.92 | E3: IPCA + 5,96% | F3: IPCA + 7,66% | G3: 4 | H3: 624.95 | I3: 337 | J3: 20 | K3: 4.8 | L3: 0 | M3: 0 | N3: 0 | O3: 620.15
A4: 42611 | B4: 0.2 | C4: 2960.01 | D4: 592 | E4: IPCA + 5,90% | F4: IPCA + 7,32% | G4: 5.57 | H4: 624.95 | I4: 306 | J4: 20 | K4: 6.59 | L4: 0 | M4: 0 | N4: 0 | O4: 618.36 | P4: 17.2
A5: 42638 | B5: 0.18 | C5: 2989.75 | D5: 538.15 | E5: IPCA + 5,86% | F5: IPCA + 7,05% | G5: 4.52 | H5: 562.45 | I5: 279 | J5: 20 | K5: 4.86 | L5: 0 | M5: 0 | N5: 0 | O5: 557.59
A6: 42638 | B6: 0.19 | C6: 2989.75 | D6: 568.05 | E6: IPCA + 5,86% | F6: IPCA + 7,05% | G6: 4.52 | H6: 593.7 | I6: 279 | J6: 20 | K6: 5.13 | L6: 0 | M6: 0 | N6: 0 | O6: 588.57
A7: 42654 | B7: 0.2 | C7: 3019.29 | D7: 603.85 | E7: IPCA + 5,76% | F7: IPCA + 6,06% | G7: 3.49 | H7: 624.95 | I7: 263 | J7: 20 | K7: 4.21 | L7: 0 | M7: 0 | N7: 0 | O7: 620.74
A8: 42677 | B8: 0.15 | C8: 3001.17 | D8: 450.17 | E8: IPCA + 5,92% | F8: IPCA + 7,95% | G8: 4.12 | H8: 468.71 | I8: 240 | J8: 20 | K8: 3.7 | L8: 0 | M8: 0 | N8: 0 | O8: 465.01
A9: 42692 | B9: 0.2 | C9: 2927.76 | D9: 585.55 | E9: IPCA + 6,33% | F9: IPCA + 13,29% | G9: 6.73 | H9: 624.95 | I9: 225 | J9: 20 | K9: 7.88 | L9: 0 | M9: 0 | N9: 0 | O9: 617.07
A10: 42705 | B10: 0.1 | C10: 2959.45 | D10: 295.94 | E10: IPCA + 6,22% | F10: IPCA + 12,24% | G10: 5.59 | H10: 312.47 | I10: 212 | J10: 20 | K10: 3.3 | L10: 0 | M10: 0 | N10: 0 | O10: 309.17
A11: 42713 | B11: 0.12 | C11: 3002.46 | D11: 360.29 | E11: IPCA + 6,03% | F11: IPCA + 9,84% | G11: 4.07 | H11: 374.97 | I11: 204 | J11: 20 | K11: 2.93 | L11: 0 | M11: 0 | N11: 0 | O11: 372.04
A12: 42724 | B12: 0.2 | C12: 3014.83 | D12: 602.96 | E12: IPCA + 6,01% | F12: IPCA + 9,72% | G12: 3.65 | H12: 624.95 | I12: 193 | J12: 20 | K12: 4.39 | L12: 0 | M12: 0 | N12: 0 | O12: 620.56
A13: 42758 | B13: 0.2 | C13: 3120.2 | D13: 624.04 | E13: IPCA + 5,64% | F13: IPCA + 4,17% | G13: 0.15 | H13: 624.95 | I13: 159 | J13: 22.5 | K13: 0.2 | L13: 0 | M13: 0 | N13: 0 | O13: 624.75
A14: 42769 | B14: 0.2 | C14: 3134.88 | D14: 626.97 | E14: IPCA + 5,63% | F14: IPCA + 3,86% | G14: -0.32 | H14: 624.95 | I14: 148 | J14: 22.5 | K14: 0 | L14: 0 | M14: 0 | N14: 0 | O14: 624.95
A15: 42781 | B15: 0.17 | C15: 3121.3 | D15: 530.62 | E15: IPCA + 5,32% | F15: IPCA - 2,18% | G15: 0.11 | H15: 531.21 | I15: 136 | J15: 22.5 | K15: 0.13 | L15: 0 | M15: 0 | N15: 0 | O15: 531.08 | P15: 161.59
A16: 42807 | B16: 0.24 | C16: 3145.42 | D16: 754.9 | E16: IPCA + 5,30% | F16: IPCA - 4,16% | G16: -0.66 | H16: 749.94 | I16: 110 | J16: 22.5 | K16: 0 | L16: 0 | M16: 0 | N16: 0 | O16: 749.94
A17: 42821 | B17: 0.25 | C17: 3170.82 | D17: 792.7 | E17: IPCA + 5,23% | F17: IPCA - 7,31% | G17: -1.45 | H17: 781.19 | I17: 96 | J17: 22.5 | K17: 0 | L17: 0 | M17: 0 | N17: 0 | O17: 781.19
A18: 42829 | B18: 0.15 | C18: 3178.84 | D18: 476.82 | E18: IPCA + 5,22% | F18: IPCA - 8,77% | G18: -1.7 | H18: 468.71 | I18: 88 | J18: 22.5 | K18: 0 | L18: 0 | M18: 0 | N18: 0 | O18: 468.71
A19: 42853 | B19: 0.16 | C19: 3164.22 | D19: 506.27 | E19: IPCA + 5,36% | F19: IPCA - 8,47% | G19: -1.25 | H19: 499.96 | I19: 64 | J19: 22.5 | K19: 0 | L19: 0 | M19: 0 | N19: 0 | O19: 499.96
A20: 42879 | B20: 0.35 | C20: 3132.63 | D20: 1096.42 | E20: IPCA + 5,59% | F20: IPCA - 2,90% | G20: -0.25 | H20: 1093.66 | I20: 38 | J20: 22.5 | K20: 0 | L20: 0 | M20: 0 | N20: 0 | O20: 1093.66
A21: 42905 | B21: 0.15 | C21: 3167.46 | D21: 475.11 | E21: IPCA + 5,50% | F21: IPCA - 30,02% | G21: -1.35 | H21: 468.71 | I21: 12 | J21: 22.5 | K21: 0 | L21: 0 | M21: 0 | N21: 0 | O21: 468.71
A23: TOTAL | B23: =SUM(B3:B22) -> 3.61 | D23: =SUM(D3:D22) -> 11081.73 | H23: =SUM(H3:H22) -> 11280.33 | K23: =SUM(K3:K22) -> 48.12 | L23: =SUM(L3:L22) -> 0 | M23: =SUM(M3:M22) -> 0 | N23: =SUM(N3:N22) -> 0 | O23: =SUM(O3:O22) -> 11232.21 | P23: =SUM(P3:P22) -> 178.79 | R23: =(O23+P23)-D23 -> 329.27 | S23: =R23/D23 -> 0.02971287

Sheet IR 2018
A1: ACOES | B1: POSICAO EM 31/12/2018 | H1: PROVENTOS | Q1: COMPRAS
A2: CNPJ | B2: ATIVO | C2: EMPRESA | D2: QTD | E2: PR MEDIO | F2: VLR TOTAL | H2: DIVIDENDOS | I2: JCP | Q2: FIIs
A3: 033.000.167/0001-01 | B3: PETR4 | C3: PETROBRAS | D3: 200 | E3: 12.78 | F3: 2555 | I3: 34 | Q3: BCFF11 | R3: 43834.27
A4: 000.000.000/0001-91 | B4: BBAS3 | C4: BANCO DO BRASIL | D4: 100 | E4: 20.7 | F4: 2069.51 | I4: 128.37 | Q4: BPFF11 | R4: 12648.22
A5: 017.155.730/0001-64 | B5: CMIG3 | C5: CEMIG | D5: 2500 | E5: 8.19 | F5: 20481 | H5: 76.43 | Q5: EDGA11 | R5: 4123.04
A6: 061.532.644/0001-15 | B6: ITSA4 | C6: ITAUSA | D6: 2424 | E6: 7.84 | F6: 19004 | H6: 1162.01 | I6: 655.17 | Q6: FIGS11 | R6: 9100.37
A7: 007.859.971/0001-30 | B7: TAEE11 | C7: TAESA | D7: 625 | E7: 20.6 | F7: 12873.23 | H7: 1191.18 | I7: 417.26 | Q7: GGRC11 | R7: 4918.36
A8: 089.637.490/0001-45 | B8: KLBN4 | C8: KLABIN | D8: 3300 | E8: 2.86 | F8: 9438 | H8: 360.67 | Q8: HGRU11 | R8: 3200.2
A9: 061.092.037/0001-81 | B9: ETER3 | C9: ETERNIT | D9: 550 | E9: 9.26 | F9: 5094 | Q9: HTMX11 | R9: 1494.95
A10: 078.876.950/0001-71 | B10: HGTX3 | C10: HERING | D10: 500 | E10: 16.67 | F10: 8334.7 | H10: 192.46 | Q10: MXRF11 | R10: 7972.84
A11: 028.195.667/0001-06 | B11: ABCB4 | C11: BANCO ABC BRASIL | D11: 785 | E11: 15.93 | F11: 12501.85 | Q11: RBGS11 | R11: 3107.75
A12: 004.149.454/0001-80 | B12: ECOR3 | C12: ECORODOVIAS | D12: 400 | E12: 8.13 | F12: 3252 | H12: 214.28 | Q12: RBRR11 | R12: 4034.85
A13: 076.484.013/0001-45 | B13: SAPR4 | C13: SANEPAR | D13: 200 | E13: 9.67 | F13: 1934 | Q13: SDIL11 | R13: 8800.75
A14: 017.184.037/0001-10 | B14: BMEB4 | C14: BANCO MERCANTIL | D14: 200 | E14: 5.69 | F14: 1138 | Q14: SPTW11 | R14: 6241.73
A15: 004.128.563/0001-10 | B15: TIET11 | C15: AES TIETEE | D15: 100 | E15: 9.66 | F15: 966 | H15: 10.01 | Q15: VGIR11 | R15: 3097.48
A16: 060.398.369/0001-79 | B16: PMAM3 | C16: PARANAPANEMA | D16: 500 | E16: 1.49 | F16: 745 | Q16: VISC11 | R16: 14502.95
A17: 042.278.473/0001-03 | B17: WIZS3 | C17: WIZ S.A. | D17: 200 | E17: 7.02 | F17: 1404 | Q17: XPLG11 | R17: 11735.69
Q18: XPML11 | R18: 6573.37
Q21: TOTAL | R21: =SUM(R3:R19) -> 145386.82
A22: FUNDOS IMOBILIARIOS | B22: POSICAO EM 31/12/2018 | H22: PROVENTOS | Q22: RENDA | R22: 906.01
A23: CNPJ | B23: ATIVO | C23: EMPRESA | D23: QTD | E23: PR MEDIO | F23: VLR TOTAL | H23: RENDIMENTOS | Q23: PERCENT | R23: =R22/R21 -> 0.0062317203
A24: 011.026.627/0001-38 | B24: BCFF11 | C24: FII BC FFII | D24: 520 | E24: 76.14 | F24: 39591.73 | H24: 2997.46
A25: 017.554.274/0001-25 | B25: VISC11 | C25: FII VINCI SC | D25: 95 | E25: 101.96 | F25: 9686.1 | H25: 466.1
A26: 013.652.006/0001-95 | B26: RBGS11 | C26: FII RB GSB I | D26: 45 | E26: 49.53 | F26: 2228.75 | H26: 54.58
A27: 015.333.306/0001-37 | B27: EDGA11 | C27: FII GALERIA | D27: 86 | E27: 42.88 | F27: 3688.04 | H27: 103.4
A28: 016.671.412/0001-93 | B28: SDIL11 | C28: FII SDI LOG | D28: 70 | E28: 92.11 | F28: 6447.8 | H28: 294.61
A29: 017.590.518/0001-25 | B29: FIGS11 | C29: FII GEN SHOP | D29: 105 | E29: 71.9 | F29: 7549.97 | H29: 445.83
A30: 015.538.445/0001-05 | B30: SPTW11 | C30: FII SP DOWNT | D30: 75 | E30: 72.58 | F30: 5443.73 | H30: 138.65
A31: 026.502.794/0001-85 | B31: XPLG11 | C31: FII XP LOG | D31: 55 | E31: 93.17 | F31: 5124.44 | H31: 66.24
A32: 029.467.977/0001-03 | B32: RBRR11 | C32: FII RBRHGRAD | D32: 20 | E32: 98.72 | F32: 1974.35 | H32: 46.11
A33: 097.521.225/0001-25 | B33: MXRF11 | C33: FII MAXI REN | D33: 300 | E33: 10 | F33: 2998.7 | H33: 57.1
A34: 017.324.357/0001-28 | B34: BPFF11 | C34: FII ABSOLUTO | D34: 23 | E34: 90.37 | F34: 2078.42 | H34: 47.36
A35: 026.614.291/0001-00 | B35: GGRC11 | C35: FII GGRCOVEP | D35: 19 | E35: 123.15 | F35: 2339.76 | H35: 40.28

Sheet IR 2019
A1: POSIÇÃO EM 31/12/2019 | I1: POSIÇÃO EM 31/12/2019
A2: AÇOES | I2: FUNDOS IMOBILIÁRIOS
A3: SEQ | B3: CNPJ | C3: ATIVO | D3: NOME | E3: QUANTIDADE | F3: PREÇO MÉDIO | G3: VALOR | I3: SEQ | J3: CNPJ | K3: ATIVO | L3: NOME | M3: QUANTIDADE | N3: PREÇO MÉDIO | O3: VALOR
A4: 1 | B4: 33.000.167/0001-01 | C4: PETR4 | D4: PETROBRAS | E4: 200 | F4: 12.78 | G4: =E4*F4 -> 2556 | I4: 1 | J4: 11.026.627/0001-38 | K4: BCFF11 | M4: 590 | N4: 77.18 | O4: =M4*N4 -> 45536.2
A5: =A4+1 -> 2 | B5: 00.000.000/0001-91 | C5: BBAS3 | D5: BANCO DO BRASIL | E5: 100 | F5: 20.7 | G5: =E5*F5 -> 2070 | I5: =I4+1 -> 2 | J5: 17.554.274/0001-25 | K5: VISC11 | M5: 145 | N5: 103.76 | O5: =M5*N5 -> 15045.2
A6: =A5+1 -> 3 | B6: 17.155.730/0001-64 | C6: CMIG3 | D6: CEMIG | E6: 1500 | F6: 8.19 | G6: =E6*F6 -> 12285 | I6: =I5+1 -> 3 | J6: 13.652.006/0001-95 | K6: RBGS11 | M6: 75 | N6: 47.77 | O6: =M6*N6 -> 3582.75
A7: =A6+1 -> 4 | B7: 61.532.644/0001-15 | C7: ITSA4 | D7: ITAUSA | E7: 2424 | F7: 7.84 | G7: =E7*F7 -> 19004.16 | I7: =I6+1 -> 4 | J7: 15.333.306/0001-37 | K7: EDGA11 | M7: 96 | N7: 42.95 | O7: =M7*N7 -> 4123.2
A8: =A7+1 -> 5 | B8: 07.859.971/0001-30 | C8: TAEE11 | D8: TAESA | E8: 625 | F8: 20.6 | G8: =E8*F8 -> 12875 | I8: =I7+1 -> 5 | J8: 16.671.412/0001-93 | K8: SDIL11 | M8: 105 | N8: 94.06 | O8: =M8*N8 -> 9876.3
A9: =A8+1 -> 6 | B9: 89.637.490/0001-45 | C9: KLBN4 | D9: KLABIN | E9: 4100 | F9: 2.88 | G9: =E9*F9 -> 11808 | I9: =I8+1 -> 6 | J9: 17.590.518/0001-25 | K9: FIGS11 | M9: 190 | N9: 68.67 | O9: =M9*N9 -> 13047.3
A10: =A9+1 -> 7 | B10: 61.092.037/0001-81 | C10: ETER3 | D10: ETERNIT | E10: 550 | F10: 9.26 | G10: =E10*F10 -> 5093 | I10: =I9+1 -> 7 | J10: 15.538.445/0001-05 | K10: SPTW11 | M10: 100 | N10: 75.64 | O10: =M10*N10 -> 7564
A11: =A10+1 -> 8 | B11: 28.195.667/0001-06 | C11: ABCB4 | D11: BANCO ABC BRASIL | E11: 851 | F11: 15.89 | G11: =E11*F11 -> 13522.39 | I11: =I10+1 -> 8 | J11: 26.502.794/0001-85 | K11: XPLG11 | M11: 153 | N11: 98.86 | O11: =M11*N11 -> 15125.58
A12: =A11+1 -> 9 | B12: 76.484.013/0001-45 | C12: SAPR4 | D12: SANEPAR | E12: 200 | F12: 9.67 | G12: =E12*F12 -> 1934 | I12: =I11+1 -> 9 | J12: 29.467.977/0001-03 | K12: RBRR11 | M12: 40 | N12: 100.88 | O12: =M12*N12 -> 4035.2
A13: =A12+1 -> 10 | B13: 17.184.037/0001-10 | C13: BMEB4 | D13: BANCO MERCANTIL | E13: 400 | F13: 6.56 | G13: =E13*F13 -> 2624 | I13: =I12+1 -> 10 | J13: 97.521.225/0001-25 | K13: MXRF11 | M13: 1442 | N13: 10.81 | O13: =M13*N13 -> 15588.02
A14: =A13+1 -> 11 | B14: 04.128.563/0001-10 | C14: TIET11 | D14: AES TIETE | E14: 500 | F14: 11.33 | G14: =E14*F14 -> 5665 | I14: =I13+1 -> 11 | J14: 17.324.357/0001-28 | K14: BPFF11 | M14: 155 | N14: 92.75 | O14: =M14*N14 -> 14376.25
A15: =A14+1 -> 12 | B15: 60.398.369/0004-79 | C15: PMAM3 | D15: PARANAPANEMA | E15: 100 | F15: 24.5 | G15: =E15*F15 -> 2450 | I15: =I14+1 -> 12 | J15: 26.614.291/0001-00 | K15: GGRC11 | M15: 40 | N15: 122.97 | O15: =M15*N15 -> 4918.8
A16: =A15+1 -> 13 | B16: 42.278.473/0001-03 | C16: WIZS3 | D16: WIZ | E16: 200 | F16: 7.02 | G16: =E16*F16 -> 1404 | I16: =I15+1 -> 13 | J16: 29.641.226/0001-53 | K16: HGRU11 | M16: 30 | N16: 106.68 | O16: =M16*N16 -> 3200.4
A17: =A16+1 -> 14 | B17: 17.155.730/0001-64 | C17: CMIG4 | D17: CEMIG | E17: 100 | F17: 13.73 | G17: =E17*F17 -> 1373 | I17: =I16+1 -> 14 | J17: 28.757.546/0001-00 | K17: XPML11 | M17: 77 | N17: 106.76 | O17: =M17*N17 -> 8220.52
I18: =I17+1 -> 15 | J18: 08.706.065/0001-69 | K18: HTMX11 | M18: 10 | N18: 149.54 | O18: =M18*N18 -> 1495.4
I19: =I18+1 -> 16 | J19: 29.852.732/0001-91 | K19: VGIR11 | M19: 95 | N19: 102.67 | O19: =M19*N19 -> 9753.65
I20: =I19+1 -> 17 | J20: 28.152.272/0001-26 | K20: RECR11 | M20: 78 | N20: 107.02 | O20: =M20*N20 -> 8347.56
I21: =I20+1 -> 18 | J21: 17.329.029/0001-14 | K21: RBFF11 | M21: 50 | N21: 77.49 | O21: =M21*N21 -> 3874.5
I22: =I21+1 -> 19 | J22: 26.499.833/0001-32 | K22: MALL11 | M22: 25 | N22: 104.07 | O22: =M22*N22 -> 2601.75
I23: =I22+1 -> 20 | J23: 30.791.386/0001-68 | K23: OUFF11 | M23: 30 | N23: 96.13 | O23: =M23*N23 -> 2883.9
F27: TOTAL | G27: =SUM(G4:G20) -> 94663.55 | N27: TOTAL | O27: =SUM(O4:O25) -> 193196.48
A31: RENDIMENTOS NO ANO DE 2020
A32: DIVIDENDOS DAS AÇÕES | F32: JUROS SOBRE CAPITAL PROPRIO - JCP | K32: PROVENTOS DOS FUNDOS IMOBILIÁRIOS
A33: CNPJ | B33: ATIVO | C33: NOME | D33: VALOR | F33: CNPJ | G33: ATIVO | H33: NOME | I33: VALOR | K33: CNPJ | L33: ATIVO | M33: NOME | N33: VALOR
A34: 33.000.167/0001-01 | B34: PETR4 | C34: PETROBRAS | D34: 3.88 | F34: 33.000.167/0001-01 | G34: PETR4 | H34: PETROBRAS | I34: 170 | K34: 11.026.627/0001-38 | L34: BCFF11 | M34: FII BC FFII | N34: 3634.34
A35: 00.000.000/0001-91 | B35: BBAS3 | C35: BRASIL | D35: 0.87 | F35: 00.000.000/0001-91 | G35: BBAS3 | H35: BRASIL | I35: 216.15 | K35: 17.554.274/0001-25 | L35: VISC11 | M35: FII VINCI SC | N35: 1040.21
A36: 17.155.730/0001-64 | B36: CMIG4 | C36: CEMIG | D36: 676.2 | F36: 17.155.730/0001-64 | G36: CMIG4 | H36: CEMIG | I36: 306.03 | K36: 13.652.006/0001-95 | L36: RBGS11 | M36: FII RB GSB I | N36: 169.22
A37: 61.532.644/0001-15 | B37: ITSA4 | C37: ITAUSA | D37: 2117.85 | F37: 61.532.644/0001-15 | G37: ITSA4 | H37: ITAUSA | I37: 657.68 | K37: 15.333.306/0001-37 | L37: EDGA11 | M37: FII GALERIA | N37: 259.24
A38: 07.859.971/0001-30 | B38: TAE11 | C38: TAESA | D38: 684.37 | F38: 07.859.971/0001-30 | G38: TAE11 | H38: TAESA | I38: 422.72 | K38: 16.671.412/0001-93 | L38: SDIL11 | M38: FII SDI LOG | N38: 692.5
A39: 89.637.490/0001-45 | B39: KLBN4 | C39: KLABIN S/A | D39: 439.2 | F39: 89.637.490/0001-45 | G39: KLBN4 | H39: KLABIN S/A | I39: 199.36 | K39: 17.590.518/0001-25 | L39: FIGS11 | M39: FII GEN SHOP | N39: 614.46
A40: 04.128.563/0001-10 | B40: TIET11 | C40: AES TIETE E | D40: 268.53 | F40: 28.195.667/0001-06 | G40: ABCB4 | H40: ABC BRASIL | I40: 744.99 | K40: 15.538.445/0001-05 | L40: SPTW10 | M40: FII SP DOWNT | N40: 716.45
A41: 42.278.473/0001-03 | B41: WIZS3 | C41: WIZ S.A. | D41: 222.29 | F41: 76.484.013/0001-45 | G41: SAPR4 | H41: SANEPAR | I41: 58.06 | K41: 26.502.794/0001-85 | L41: FII XP LOG | M41: FII XP LOG | N41: 865.09
A42: 78.876.950/0001-71 | B42: HERING | C42: HERING | D42: 154.4 | F42: 17.184.037/0001-10 | G42: BMEB4 | H42: MERC BRASIL | I42: 225.6 | K42: 29.467.977/0001-03 | L42: RBRR11 | M42: FII RBRHGRAD | N42: 256.89
F43: 04.128.563/0001-10 | G43: TIET11 | H43: AES TIETE E | I43: 10.23 | K43: 97.521.225/0001-25 | L43: MXRF11 | M43: FII MAXI REN | N43: 689.98
C44: TOTAL | D44: =SUM(D34:D42) -> 4567.59 | F44: 78.876.950/0001-71 | G44: HERING | H44: HERING | I44: 270.68 | K44: 17.324.357/0001-28 | L44: BPFF11 | M44: FII ABSOLUTO | N44: 903.1
K45: 26.614.291/0001-00 | L45: GGRC11 | M45: FII GGRCOVEP | N45: 280.71
H46: TOTAL | I46: =SUM(I34:I44) -> 3281.5 | K46: 29.641.226/0001-53 | L46: HGRU11 | M46: FII CSHG URB | N46: 217.6
K47: 28.757.546/0001-00 | L47: FII XP MALLS | M47: FII XP MALLS | N47: 348.83
K48: 08.706.065/0001-69 | L48: HGTX11 | M48: FII HOTEL MX | N48: 87.85
K49: 29.852.732/0001-91 | L49: VGIR11 | M49: FII VALREIII | N49: 276.08
K50: 28.152.272/0001-26 | L50: FII UBS (BR) | M50: FII UBS (BR) | N50: 109.23
K51: 17.329.029/0001-14 | L51: RBFF11 | M51: FII FATORFIX | N51: 80
K52: 26.499.833/0001-32 | L52: MALL11 | M52: FII MALLS BP | N52: 11.1
K53: 30.791.386/0001-68 | L53: OUFF11 | M53: FII OURI FOF | N53: 11
M57: TOTAL | N57: =SUM(N34:N55) -> 11263.88

Sheet IR 2020
A1: POSIÇÃO EM 31/12/2020 | I1: POSIÇÃO EM 31/12/2020
A2: AÇOES | I2: FUNDOS IMOBILIÁRIOS
A3: SEQ | B3: CNPJ | C3: ATIVO | D3: NOME | E3: QUANTIDADE | F3: PREÇO MÉDIO | G3: VALOR | I3: SEQ | J3: CNPJ | K3: ATIVO | L3: NOME | M3: QUANTIDADE | N3: PREÇO MÉDIO | O3: VALOR
A4: 1 | B4: 33.000.167/0001-01 | C4: PETR4 | D4: PETROBRAS | E4: 200 | F4: 12.78 | G4: 2555 | I4: 1 | J4: 11.026.627/0001-38 | K4: BCFF11 | M4: 615 | N4: 77.56 | O4: 47698
A5: =A4+1 -> 2 | B5: 00.000.000/0001-91 | C5: BBAS3 | D5: BANCO DO BRASIL | E5: 134 | F5: 21.76 | G5: 2915.93 | I5: =I4+1 -> 2 | J5: 17.554.274/0001-25 | K5: VISC11 | M5: 153 | N5: 103.06 | O5: 15767.78
A6: =A5+1 -> 3 | B6: 17.155.730/0001-64 | C6: CMIG3 | D6: CEMIG | E6: 1561 | F6: 7.87 | G6: 12288.6 | I6: =I5+1 -> 3 | J6: 13.652.006/0001-95 | K6: RBGS11 | M6: 75 | N6: 47.77 | O6: 3582.9
A7: =A6+1 -> 4 | B7: 61.532.644/0001-15 | C7: ITSA4 | D7: ITAUSA | E7: 3290 | F7: 8.56 | G7: 28166.02 | I7: =I6+1 -> 4 | J7: 15.333.306/0001-37 | K7: EDGA11 | M7: 116 | N7: 40.67 | O7: 4717.83
A8: =A7+1 -> 5 | B8: 07.859.971/0001-30 | C8: TAEE11 | D8: TAESA | E8: 625 | F8: 20.6 | G8: 12873.23 | I8: =I7+1 -> 5 | J8: 16.671.412/0001-93 | K8: SDIL11 | M8: 105 | N8: 94.06 | O8: 9875.92
A9: =A8+1 -> 6 | B9: 89.637.490/0001-45 | C9: KLBN4 | D9: KLABIN | E9: 4100 | F9: 2.88 | G9: 11789.08 | I9: =I8+1 -> 6 | J9: 17.590.518/0001-25 | K9: FIGS11 | M9: 210 | N9: 68.87 | O9: 14462.17
A10: =A9+1 -> 7 | B10: 61.092.037/0001-81 | C10: ETER3 | D10: ETERNIT | E10: 550 | F10: 9.26 | G10: 5094 | I10: =I9+1 -> 7 | J10: 15.538.445/0001-05 | K10: SPTW11 | M10: 100 | N10: 75.64 | O10: 7564.1
A11: =A10+1 -> 8 | B11: 28.195.667/0001-06 | C11: ABCB4 | D11: BANCO ABC BRASIL | E11: 861 | F11: 15.87 | G11: 13662.35 | I11: =I10+1 -> 8 | J11: 26.502.794/0001-85 | K11: XPLG11 | M11: 153 | N11: 98.86 | O11: 15125.58
A12: =A11+1 -> 9 | B12: 76.484.013/0001-45 | C12: SAPR4 | D12: SANEPAR | E12: 600 | F12: 3.22 | G12: 1934 | I12: =I11+1 -> 9 | J12: 29.467.977/0001-03 | K12: RBRR11 | M12: 60 | N12: 99.04 | O12: 5942.1
A13: =A12+1 -> 10 | B13: 17.184.037/0001-10 | C13: BMEB4 | D13: BANCO MERCANTIL | E13: 400 | F13: 6.56 | G13: 2625.85 | I13: =I12+1 -> 10 | J13: 97.521.225/0001-25 | K13: MXRF11 | M13: 2392 | N13: 10.59 | O13: 25337.14
A14: =A13+1 -> 11 | B14: 04.128.563/0001-10 | C14: TIET11 | D14: AES TIETE | E14: 500 | F14: 11.33 | G14: 5662.93 | I14: =I13+1 -> 11 | J14: 17.324.357/0001-28 | K14: BPFF11 | M14: 205 | N14: 90.61 | O14: 18575.61
A15: =A14+1 -> 12 | B15: 60.398.369/0004-79 | C15: PMAM3 | D15: PARANAPANEMA | E15: 100 | F15: 24.5 | G15: 2450 | I15: =I14+1 -> 12 | J15: 26.614.291/0001-00 | K15: GGRC11 | M15: 40 | N15: 122.97 | O15: 4918.81
A16: =A15+1 -> 13 | B16: 42.278.473/0001-03 | C16: WIZS3 | D16: WIZ | E16: 200 | F16: 7.02 | G16: 1404 | I16: =I15+1 -> 13 | J16: 29.641.226/0001-53 | K16: HGRU11 | M16: 30 | N16: 106.68 | O16: 3200.42
... A20: =A19+1 -> 17 | B20: 17.344.597/0001-94 | C20: BBSE3 | D20: BB SEGURIDADE | E20: 42 | F20: 29.87 | G20: 1254.61 | I20: =I19+1 -> 17 | J20: 28.152.272/0001-26 | K20: RECR11 | M20: 148 | N20: 103.17 | O20: 15269.01
I21: =I20+1 -> 18 | J21: 17.329.029/0001-14 | K21: RBFF11 | M21: 156 | N21: 74.56 | O21: 11631.78
I22: =I21+1 -> 19 | J22: 26.499.833/0001-32 | K22: MALL11 | M22: 58 | N22: 95.15 | O22: 5518.74
I23: =I22+1 -> 20 | J23: 30.791.386/0001-68 | K23: OUFF11 | M23: 90 | N23: 90.3 | O23: 8127.26
I24: =I23+1 -> 21 | J24: 12.516.185/0001-70 | K24: VINO11 | M24: 100 | N24: 62.31 | O24: 6230.97
I25: =I24+1 -> 22 | J25: 17.156.502/0001-09 | K25: PORD11 | M25: 30 | N25: 101.28 | O25: 3038.46
F27: TOTAL | G27: =SUM(G4:G20) -> 125368.22 | N27: TOTAL | O27: =SUM(O4:O25) -> 247761.12
A31: RENDIMENTOS NO ANO DE 2020
A32: DIVIDENDOS DAS AÇÕES | F32: JUROS SOBRE CAPITAL PROPRIO - JCP | K32: PROVENTOS DOS FUNDOS IMOBILIÁRIOS
A33: CNPJ | B33: ATIVO | C33: NOME | D33: VALOR | F33: CNPJ | G33: ATIVO | H33: NOME | I33: VALOR | K33: CNPJ | L33: ATIVO | M33: NOME | N33: VALOR
A34: 33.000.167/0001-01 | B34: PERT4 | C34: PETROBRAS | D34: 0.09 | F34: 33.000.167/0001-01 | G34: PETR4 | H34: PETROBRAS | I34: 105.4 | K34: 11.026.627/0001-38 | L34: BCFF11 | M34: FII BC FFII | N34: 3436.95
A35: 00.000.000/0001-91 | B35: BBAS3 | C35: BRASIL | D35: 0.41 | F35: 00.000.000/0001-91 | G35: BBAS3 | H35: BRASIL | I35: 149.86 | K35: 17.554.274/0001-25 | L35: VISC11 | M35: FII VINCI SC | N35: 650.74
A36: 17.155.730/0001-64 | B36: CMIG4 | C36: CEMIG | D36: 415.83 | F36: 17.155.730/0001-64 | G36: CMIG4 | H36: CEMIG | I36: 186.53 | K36: 13.652.006/0001-95 | L36: RBGS11 | M36: FII RB GSB I | N36: 94.08
A37: 61.532.644/0001-15 | B37: ITSA4 | C37: ITAUSA | D37: 871.48 | F37: 61.532.644/0001-15 | G37: ITSA4 | H37: ITAUSA | I37: 492.71 | K37: 15.333.306/0001-37 | L37: EDGA11 | M37: FII GALERIA | N37: 171.68
A38: 07.859.971/0001-30 | B38: TAE11 | C38: TAESA | D38: 1584.76 | F38: 07.859.971/0001-30 | G38: TAE11 | H38: TAESA | I38: 358.81 | K38: 16.671.412/0001-93 | L38: SDIL11 | M38: FII SDI LOG | N38: 651
A39: 89.637.490/0001-45 | B39: KLBN4 | C39: KLABIN S/A | D39: 17.89 | F39: 89.637.490/0001-45 | G39: KLBN4 | H39: KLABIN S/A | I39: 132.25 | K39: 17.590.518/0001-25 | L39: FIGS11 | M39: FII GEN SHOP | N39: 696.9
A40: 04.128.563/0001-10 | B40: TIET11 | C40: AES TIETE E | D40: 481.98 | F40: 28.195.667/0001-06 | G40: ABCB4 | H40: ABC BRASIL | I40: 469.94 | K40: 15.538.445/0001-05 | L40: SPTW10 | M40: FII SP DOWNT | N40: 830
A41: 42.278.473/0001-03 | B41: WIZS3 | C41: WIZ S.A. | D41: 133.76 | F41: 76.484.013/0001-45 | G41: SAPR4 | H41: SANEPAR | I41: 114.99 | K41: 26.502.794/0001-85 | L41: FII XP LOG | M41: FII XP LOG | N41: 1078.65
A42: 92.702.067/0001-96 | B42: BRSR6 | C42: BANRISUL | D42: 72.06 | F42: 17.184.037/0001-10 | G42: BMEB4 | H42: MERC BRASIL | I42: 233.31 | K42: 29.467.977/0001-03 | L42: RBRR11 | M42: FII RBRHGRAD | N42: 326.34
F43: 04.128.563/0001-10 | G43: TIET11 | H43: AES TIETE E | I43: 47.3 | K43: 97.521.225/0001-25 | L43: MXRF11 | M43: FII MAXI REN | N43: 1724.24
C44: TOTAL | D44: =SUM(D34:D42) -> 3578.26 | F44: 92.702.067/0001-96 | G44: BRSR6 | H44: BANRISUL | I44: 164.65 | K44: 17.324.357/0001-28 | L44: BPFF11 | M44: FII ABSOLUTO | N44: 1277.75
K45: 02.671.743/0001-19 | L45: GGRC11 | M45: CM CAPITAL MARKETS DTVM LTDA | N45: 344.8
H46: TOTAL | I46: =SUM(I34:I44) -> 2455.75 | K46: 29.641.226/0001-53 | L46: HGRU11 | M46: FII CSHG URB | N46: 246.6
K47: 28.757.546/0001-00 | L47: FII XP MALLS | M47: FII XP MALLS | N47: 241.4
K48: 08.706.065/0001-69 | L48: HGTX11 | M48: FII HOTEL MX | N48: 17.62
K49: 29.852.732/0001-91 | L49: FII VALREIII | M49: VGIR11 | N49: 648.01
K50: 28.152.272/0001-26 | L50: FII UBS (BR) | M50: FII UBS (BR) | N50: 1306.72
K51: 17.329.029/0001-14 | L51: FII FATORFIX | M51: RBFF11 | N51: 729.48
K52: 26.499.833/0001-32 | L52: MALL11 | M52: FII MALLS BP | N52: 171.12
K53: 30.791.386/0001-68 | L53: OUFF11 | M53: FII OURI FOF | N53: 331
K54: 12.516.185/0001-70 | L54: VINO11 | M54: FII VINC COR | N54: 316.71
K55: 17.156.502/0001-09 | L55: PORD11 | M55: FII POLO CRI | N55: 24.3
M57: TOTAL | N57: =SUM(N34:N55) -> 15316.09
